Workbook

Sheet Summary
B1: CHURCH FARM ROAD PUMP STATION & PIPELINE
B2: Material supply bid comparison · 4 supplier quotes · Washington City, Utah · prepared 9/29/2026
B4: COLOR KEY | C4: Lowest bid | D4: 2nd lowest | E4: Middle (3rd of 4) | F4: Highest bid | G4: Only one quote
B6: 1 · WHAT EACH SUPPLIER ACTUALLY QUOTED (the headline numbers — not comparable on their own)
B7: Supplier | C7: Quote / date | D7: Valid through | E7: Sum of transcribed lines | F7: Printed on quote (pre-tax) | G7: Difference | H7: Sales tax (quoted) | I7: Total incl. tax | J7: Lines | K7: Scope excluded from quote
B8: Ferguson | C8: Est. 006QQ000019fSKPYA2 · 9/18/26 | D8: ~10/18/26 (30 days) | E8: =SUMIFS('Quote Lines'!$I$3:$I$805,'Quote Lines'!$A$3:$A$805,$B8,'Quote Lines'!$M$3:$M$805,"Y") -> 1313834.4 | F8: 1313834.4 | G8: =E8-F8 -> 0 | H8: 88683.82 | I8: =F8+H8 -> 1402518.2 | J8: =COUNTIFS('Quote Lines'!$A$3:$A$805,$B8,'Quote Lines'!$M$3:$M$805,"Y") -> 207 | K8: Not guaranteed to be complete; award of ENTIRE BOM required; tariffs excluded
B9: HD Fowler | C9: Q647047 · bid date 9/9/26 | D9: Not stated | E9: =SUMIFS('Quote Lines'!$I$3:$I$805,'Quote Lines'!$A$3:$A$805,$B9,'Quote Lines'!$M$3:$M$805,"Y") -> 1036912.8 | F9: 1036912.8 | G9: =E9-F9 -> 0 | H9: 69991.77 | I9: =F9+H9 -> 1106904.6 | J9: =COUNTIFS('Quote Lines'!$A$3:$A$805,$B9,'Quote Lines'!$M$3:$M$805,"Y") -> 229 | K9: Casing pipe (no bid), spacers & end seals (TBD), bell restraints (qty by contractor), pipe supports, precast, steel fab
B10: Mountainland | C10: S108187947 · 9/16/26 | D10: 9/15/26 (before issue date) | E10: =SUMIFS('Quote Lines'!$I$3:$I$805,'Quote Lines'!$A$3:$A$805,$B10,'Quote Lines'!$M$3:$M$805,"Y") -> 1247235.1 | F10: 1247235.1 | G10: =E10-F10 -> 0 | H10: 84188.34 | I10: =F10+H10 -> 1331423.4 | J10: =COUNTIFS('Quote Lines'!$A$3:$A$805,$B10,'Quote Lines'!$M$3:$M$805,"Y") -> 173 | K10: Bid Items 1-4, 13, 15 no bid; owner supplies pumps & 12" meter/Cla-Val at vault
B11: Scholzen | C11: 7003117-00 · 7/24/26 | D11: 24 hours (expired 7/25/26) | E11: =SUMIFS('Quote Lines'!$I$3:$I$805,'Quote Lines'!$A$3:$A$805,$B11,'Quote Lines'!$M$3:$M$805,"Y") -> 1114950.3 | F11: 1114950.3 | G11: =E11-F11 -> 0 | H11: 78938.48 | I11: =F11+H11 -> 1193888.8 | J11: =COUNTIFS('Quote Lines'!$A$3:$A$805,$B11,'Quote Lines'!$M$3:$M$805,"Y") -> 183 | K11: Casing pipe, spacers, end seals; link seals 'not available'; spool lengths to be verified
B12: Printed totals are blue inputs read from each quote's last page; 'Difference' proves every line was transcribed. Sales tax is as quoted (Scholzen's implies 7.08% vs 6.75% on the other three).
B14: 2 · APPLES-TO-APPLES (same quantities for everyone; skipped items filled at the lowest competing price)
B15: Supplier | C15: Comparable rows priced | D15: Est. value of skipped rows | E15: Comparable-basis total | F15: vs. lowest ($) | G15: vs. lowest (%) | H15: Rank
B16: Ferguson | C16: =COUNTIFS('Material Comparison'!$AE$7:$AE$338,">=1",'Material Comparison'!$AE$7:$AE$338,"<=4")&" of "&COUNTIF('Material Comparison'!$S$7:$S$338,">=2") -> 155 of 177 | D16: =SUM('Material Comparison'!$AI$7:$AI$338)-SUMIFS('Material Comparison'!$K$7:$K$338,'Material Comparison'!$S$7:$S$338,">=2") -> 24598.41 | E16: =SUM('Material Comparison'!$AI$7:$AI$338) -> 1329066 | F16: =E16-MIN($E$16:$E$19) -> 54502.747 | G16: =E16/MIN($E$16:$E$19)-1 -> 0.042761899 | H16: =RANK(E16,$E$16:$E$19,1) -> 4
B17: HD Fowler | C17: =COUNTIFS('Material Comparison'!$AF$7:$AF$338,">=1",'Material Comparison'!$AF$7:$AF$338,"<=4")&" of "&COUNTIF('Material Comparison'!$S$7:$S$338,">=2") -> 145 of 177 | D17: =SUM('Material Comparison'!$AJ$7:$AJ$338)-SUMIFS('Material Comparison'!$L$7:$L$338,'Material Comparison'!$S$7:$S$338,">=2") -> 197167.62 | E17: =SUM('Material Comparison'!$AJ$7:$AJ$338) -> 1290937.8 | F17: =E17-MIN($E$16:$E$19) -> 16374.55 | G17: =E17/MIN($E$16:$E$19)-1 -> 0.012847185 | H17: =RANK(E17,$E$16:$E$19,1) -> 2
B18: Mountainland | C18: =COUNTIFS('Material Comparison'!$AG$7:$AG$338,">=1",'Material Comparison'!$AG$7:$AG$338,"<=4")&" of "&COUNTIF('Material Comparison'!$S$7:$S$338,">=2") -> 138 of 177 | D18: =SUM('Material Comparison'!$AK$7:$AK$338)-SUMIFS('Material Comparison'!$M$7:$M$338,'Material Comparison'!$S$7:$S$338,">=2") -> 52229.587 | E18: =SUM('Material Comparison'!$AK$7:$AK$338) -> 1274563.3 | F18: =E18-MIN($E$16:$E$19) -> 0 | G18: =E18/MIN($E$16:$E$19)-1 -> 0 | H18: =RANK(E18,$E$16:$E$19,1) -> 1
B19: Scholzen | C19: =COUNTIFS('Material Comparison'!$AH$7:$AH$338,">=1",'Material Comparison'!$AH$7:$AH$338,"<=4")&" of "&COUNTIF('Material Comparison'!$S$7:$S$338,">=2") -> 132 of 177 | D19: =SUM('Material Comparison'!$AL$7:$AL$338)-SUMIFS('Material Comparison'!$N$7:$N$338,'Material Comparison'!$S$7:$S$338,">=2") -> 208085.45 | E19: =SUM('Material Comparison'!$AL$7:$AL$338) -> 1293215.6 | F19: =E19-MIN($E$16:$E$19) -> 18652.298 | G19: =E19/MIN($E$16:$E$19)-1 -> 0.014634266 | H19: =RANK(E19,$E$16:$E$19,1) -> 3
B20: Comparable rows = material lines priced by at least two suppliers. Single-supplier lines (specialty spools, unique accessories) can't be compared and are excluded here.
B22: 3 · COLOR TALLY (how often each supplier lands in each color, across all comparable rows)
B23: Supplier | C23: Lowest (green) | D23: 2nd lowest (yellow) | E23: Middle (orange) | F23: Highest (red) | G23: Only quote | H23: Not quoted
B24: Ferguson | C24: =COUNTIF('Material Comparison'!$AE$7:$AE$338,1) -> 63 | D24: =COUNTIF('Material Comparison'!$AE$7:$AE$338,2) -> 18 | E24: =COUNTIF('Material Comparison'!$AE$7:$AE$338,3) -> 17 | F24: =COUNTIF('Material Comparison'!$AE$7:$AE$338,4) -> 57 | G24: =COUNTIF('Material Comparison'!$AE$7:$AE$338,5) -> 19 | H24: =COUNTIF('Material Comparison'!$AE$7:$AE$338,0) -> 132
B25: HD Fowler | C25: =COUNTIF('Material Comparison'!$AF$7:$AF$338,1) -> 48 | D25: =COUNTIF('Material Comparison'!$AF$7:$AF$338,2) -> 48 | E25: =COUNTIF('Material Comparison'!$AF$7:$AF$338,3) -> 25 | F25: =COUNTIF('Material Comparison'!$AF$7:$AF$338,4) -> 24 | G25: =COUNTIF('Material Comparison'!$AF$7:$AF$338,5) -> 35 | H25: =COUNTIF('Material Comparison'!$AF$7:$AF$338,0) -> 126
B26: Mountainland | C26: =COUNTIF('Material Comparison'!$AG$7:$AG$338,1) -> 48 | D26: =COUNTIF('Material Comparison'!$AG$7:$AG$338,2) -> 31 | E26: =COUNTIF('Material Comparison'!$AG$7:$AG$338,3) -> 25 | F26: =COUNTIF('Material Comparison'!$AG$7:$AG$338,4) -> 34 | G26: =COUNTIF('Material Comparison'!$AG$7:$AG$338,5) -> 30 | H26: =COUNTIF('Material Comparison'!$AG$7:$AG$338,0) -> 138
B27: Scholzen | C27: =COUNTIF('Material Comparison'!$AH$7:$AH$338,1) -> 18 | D27: =COUNTIF('Material Comparison'!$AH$7:$AH$338,2) -> 27 | E27: =COUNTIF('Material Comparison'!$AH$7:$AH$338,3) -> 24 | F27: =COUNTIF('Material Comparison'!$AH$7:$AH$338,4) -> 63 | G27: =COUNTIF('Material Comparison'!$AH$7:$AH$338,5) -> 45 | H27: =COUNTIF('Material Comparison'!$AH$7:$AH$338,0) -> 129
B28: Ties count for every tied supplier. 'Not quoted' = rows other suppliers priced that this supplier skipped.
B30: 4 · SPLIT-AWARD VIEW (buy every comparable line from its lowest bidder)
B31: Supplier | C31: Lines won | D31: $ awarded | E31: Share of split total
B32: Ferguson | C32: =COUNTIF('Material Comparison'!$AQ$7:$AQ$338,$B32) -> 63 | D32: =SUMIFS('Material Comparison'!$AP$7:$AP$338,'Material Comparison'!$AQ$7:$AQ$338,$B32) -> 695002.58 | E32: =D32/$D$36 -> 0.57683141
B33: HD Fowler | C33: =COUNTIF('Material Comparison'!$AQ$7:$AQ$338,$B33) -> 48 | D33: =SUMIFS('Material Comparison'!$AP$7:$AP$338,'Material Comparison'!$AQ$7:$AQ$338,$B33) -> 210897.75 | E33: =D33/$D$36 -> 0.17503884
B34: Mountainland | C34: =COUNTIF('Material Comparison'!$AQ$7:$AQ$338,$B34) -> 48 | D34: =SUMIFS('Material Comparison'!$AP$7:$AP$338,'Material Comparison'!$AQ$7:$AQ$338,$B34) -> 170346.29 | E34: =D34/$D$36 -> 0.14138233
B35: Scholzen | C35: =COUNTIF('Material Comparison'!$AQ$7:$AQ$338,$B35) -> 18 | D35: =SUMIFS('Material Comparison'!$AP$7:$AP$338,'Material Comparison'!$AQ$7:$AQ$338,$B35) -> 128615.97 | E35: =D35/$D$36 -> 0.10674742
B36: Split total | C36: =SUM(C32:C35) -> 177 | D36: =SUM(D32:D35) -> 1204862.6 | E36: =SUM(E32:E35) -> 1
B37: Best single-supplier total (section 2) | D37: =MIN(E16:E19) -> 1274563.3
B38: Potential saving from splitting | D38: =D37-D36 -> 69700.701 | E38: =D38/D37 -> 0.054685947
B39: Middle path: award each BID ITEM to its cheapest supplier | D39: =SUM('By Bid Item'!H5:H30) -> 1242308.5 | E39: =D37-D39 -> 32254.758
B40: Caveat: Ferguson's quote is 'contingent upon award of entire bill of materials' — splitting the buy can void its unit prices. Ties are awarded to the first supplier listed.
B42: 5 · CLEAN HEAD-TO-HEAD (only rows all four suppliers priced — no gap-filling, no judgment calls)
B43: Supplier | C43: Rows in basket | D43: Basket total | E43: vs. lowest (%)
B44: Ferguson | C44: =COUNTIF('Material Comparison'!$S$7:$S$338,4) -> 92 | D44: =SUMIFS('Material Comparison'!$K$7:$K$338,'Material Comparison'!$S$7:$S$338,4) -> 1047651.1 | E44: =IFERROR(D44/MIN($D$44:$D$47)-1,0) -> 0.052118452
B45: HD Fowler | C45: =COUNTIF('Material Comparison'!$S$7:$S$338,4) -> 92 | D45: =SUMIFS('Material Comparison'!$L$7:$L$338,'Material Comparison'!$S$7:$S$338,4) -> 1028533.5 | E45: =IFERROR(D45/MIN($D$44:$D$47)-1,0) -> 0.032919368
B46: Mountainland | C46: =COUNTIF('Material Comparison'!$S$7:$S$338,4) -> 92 | D46: =SUMIFS('Material Comparison'!$M$7:$M$338,'Material Comparison'!$S$7:$S$338,4) -> 995753.93 | E46: =IFERROR(D46/MIN($D$44:$D$47)-1,0) -> 0
B47: Scholzen | C47: =COUNTIF('Material Comparison'!$S$7:$S$338,4) -> 92 | D47: =SUMIFS('Material Comparison'!$N$7:$N$338,'Material Comparison'!$S$7:$S$338,4) -> 1025633.8 | E47: =IFERROR(D47/MIN($D$44:$D$47)-1,0) -> 0.030007273
B49: 6 · BIGGEST PRICE GAPS (where negotiating or switching supplier moves the most money)
B50: # | C50: Material | E50: Bid item | F50: Lowest bidder | G50: Lowest unit ($) | H50: Highest bidder | I50: Highest unit ($) | J50: $ spread @ ref qty | K50: High vs low
B51: 1 | C51: =INDEX('Material Comparison'!$D$7:$D$338,MATCH(LARGE('Material Comparison'!$AM$7:$AM$338,1),'Material Comparison'!$AM$7:$AM$338,0)) -> 16" bell-joint restraint (pipe-to-pipe, C900/C905) | E51: =INDEX('Material Comparison'!$B$7:$B$338,MATCH(LARGE('Material Comparison'!$AM$7:$AM$338,1),'Material Comparison'!$AM$7:$AM$338,0)) -> Item 7 | F51: =INDEX('Material Comparison'!$AQ$7:$AQ$338,MATCH(LARGE('Material Comparison'!$AM$7:$AM$338,1),'Material Comparison'!$AM$7:$AM$338,0)) -> Scholzen | G51: =INDEX('Material Comparison'!$O$7:$O$338,MATCH(LARGE('Material Comparison'!$AM$7:$AM$338,1),'Material Comparison'!$AM$7:$AM$338,0)) -> 408.48 | H51: =INDEX('Material Comparison'!$AO$7:$AO$338,MATCH(LARGE('Material Comparison'!$AM$7:$AM$338,1),'Material Comparison'!$AM$7:$AM$338,0)) -> Ferguson | I51: =INDEX('Material Comparison'!$AN$7:$AN$338,MATCH(LARGE('Material Comparison'!$AM$7:$AM$338,1),'Material Comparison'!$AM$7:$AM$338,0)) -> 677.79 | J51: =INDEX('Material Comparison'!$R$7:$R$338,MATCH(LARGE('Material Comparison'!$AM$7:$AM$338,1),'Material Comparison'!$AM$7:$AM$338,0)) -> 23968.59 | K51: =INDEX('Material Comparison'!$Q$7:$Q$338,MATCH(LARGE('Material Comparison'!$AM$7:$AM$338,1),'Material Comparison'!$AM$7:$AM$338,0)) -> 0.65929788
B52: 2 | C52: =INDEX('Material Comparison'!$D$7:$D$338,MATCH(LARGE('Material Comparison'!$AM$7:$AM$338,2),'Material Comparison'!$AM$7:$AM$338,0)) -> 16" bell restraint for DI pipe (Fast-Grip / bell restraint) | E52: =INDEX('Material Comparison'!$B$7:$B$338,MATCH(LARGE('Material Comparison'!$AM$7:$AM$338,2),'Material Comparison'!$AM$7:$AM$338,0)) -> Item 16 | F52: =INDEX('Material Comparison'!$AQ$7:$AQ$338,MATCH(LARGE('Material Comparison'!$AM$7:$AM$338,2),'Material Comparison'!$AM$7:$AM$338,0)) -> Mountainland | G52: =INDEX('Material Comparison'!$O$7:$O$338,MATCH(LARGE('Material Comparison'!$AM$7:$AM$338,2),'Material Comparison'!$AM$7:$AM$338,0)) -> 408.48242 | H52: =INDEX('Material Comparison'!$AO$7:$AO$338,MATCH(LARGE('Material Comparison'!$AM$7:$AM$338,2),'Material Comparison'!$AM$7:$AM$338,0)) -> Scholzen | I52: =INDEX('Material Comparison'!$AN$7:$AN$338,MATCH(LARGE('Material Comparison'!$AM$7:$AM$338,2),'Material Comparison'!$AM$7:$AM$338,0)) -> 1083.29 | J52: =INDEX('Material Comparison'!$R$7:$R$338,MATCH(LARGE('Material Comparison'!$AM$7:$AM$338,2),'Material Comparison'!$AM$7:$AM$338,0)) -> 22943.458 | K52: =INDEX('Material Comparison'!$Q$7:$Q$338,MATCH(LARGE('Material Comparison'!$AM$7:$AM$338,2),'Material Comparison'!$AM$7:$AM$338,0)) -> 1.6519868
B53: 3 | C53: =INDEX('Material Comparison'!$D$7:$D$338,MATCH(LARGE('Material Comparison'!$AM$7:$AM$338,3),'Material Comparison'!$AM$7:$AM$338,0)) -> 12" C900 DR18 PVC pipe (gasketed) | E53: =INDEX('Material Comparison'!$B$7:$B$338,MATCH(LARGE('Material Comparison'!$AM$7:$AM$338,3),'Material Comparison'!$AM$7:$AM$338,0)) -> Item 8 | F53: =INDEX('Material Comparison'!$AQ$7:$AQ$338,MATCH(LARGE('Material Comparison'!$AM$7:$AM$338,3),'Material Comparison'!$AM$7:$AM$338,0)) -> Ferguson | G53: =INDEX('Material Comparison'!$O$7:$O$338,MATCH(LARGE('Material Comparison'!$AM$7:$AM$338,3),'Material Comparison'!$AM$7:$AM$338,0)) -> 28.64 | H53: =INDEX('Material Comparison'!$AO$7:$AO$338,MATCH(LARGE('Material Comparison'!$AM$7:$AM$338,3),'Material Comparison'!$AM$7:$AM$338,0)) -> Scholzen | I53: =INDEX('Material Comparison'!$AN$7:$AN$338,MATCH(LARGE('Material Comparison'!$AM$7:$AM$338,3),'Material Comparison'!$AM$7:$AM$338,0)) -> 30.29 | J53: =INDEX('Material Comparison'!$R$7:$R$338,MATCH(LARGE('Material Comparison'!$AM$7:$AM$338,3),'Material Comparison'!$AM$7:$AM$338,0)) -> 20625 | K53: =INDEX('Material Comparison'!$Q$7:$Q$338,MATCH(LARGE('Material Comparison'!$AM$7:$AM$338,3),'Material Comparison'!$AM$7:$AM$338,0)) -> 0.057611732
B54: 4 | C54: =INDEX('Material Comparison'!$D$7:$D$338,MATCH(LARGE('Material Comparison'!$AM$7:$AM$338,4),'Material Comparison'!$AM$7:$AM$338,0)) -> 16" MJ x flange butterfly valve (AWWA C504 Class 250B / 150B) | E54: =INDEX('Material Comparison'!$B$7:$B$338,MATCH(LARGE('Material Comparison'!$AM$7:$AM$338,4),'Material Comparison'!$AM$7:$AM$338,0)) -> Item 9.4 | F54: =INDEX('Material Comparison'!$AQ$7:$AQ$338,MATCH(LARGE('Material Comparison'!$AM$7:$AM$338,4),'Material Comparison'!$AM$7:$AM$338,0)) -> Scholzen | G54: =INDEX('Material Comparison'!$O$7:$O$338,MATCH(LARGE('Material Comparison'!$AM$7:$AM$338,4),'Material Comparison'!$AM$7:$AM$338,0)) -> 4100 | H54: =INDEX('Material Comparison'!$AO$7:$AO$338,MATCH(LARGE('Material Comparison'!$AM$7:$AM$338,4),'Material Comparison'!$AM$7:$AM$338,0)) -> Ferguson | I54: =INDEX('Material Comparison'!$AN$7:$AN$338,MATCH(LARGE('Material Comparison'!$AM$7:$AM$338,4),'Material Comparison'!$AM$7:$AM$338,0)) -> 5586.2 | J54: =INDEX('Material Comparison'!$R$7:$R$338,MATCH(LARGE('Material Comparison'!$AM$7:$AM$338,4),'Material Comparison'!$AM$7:$AM$338,0)) -> 17834.4 | K54: =INDEX('Material Comparison'!$Q$7:$Q$338,MATCH(LARGE('Material Comparison'!$AM$7:$AM$338,4),'Material Comparison'!$AM$7:$AM$338,0)) -> 0.3624878
B55: 5 | C55: =INDEX('Material Comparison'!$D$7:$D$338,MATCH(LARGE('Material Comparison'!$AM$7:$AM$338,5),'Material Comparison'!$AM$7:$AM$338,0)) -> 36" steel casing pipe | E55: =INDEX('Material Comparison'!$B$7:$B$338,MATCH(LARGE('Material Comparison'!$AM$7:$AM$338,5),'Material Comparison'!$AM$7:$AM$338,0)) -> Item 16 | F55: =INDEX('Material Comparison'!$AQ$7:$AQ$338,MATCH(LARGE('Material Comparison'!$AM$7:$AM$338,5),'Material Comparison'!$AM$7:$AM$338,0)) -> Ferguson | G55: =INDEX('Material Comparison'!$O$7:$O$338,MATCH(LARGE('Material Comparison'!$AM$7:$AM$338,5),'Material Comparison'!$AM$7:$AM$338,0)) -> 240.58 | H55: =INDEX('Material Comparison'!$AO$7:$AO$338,MATCH(LARGE('Material Comparison'!$AM$7:$AM$338,5),'Material Comparison'!$AM$7:$AM$338,0)) -> Mountainland | I55: =INDEX('Material Comparison'!$AN$7:$AN$338,MATCH(LARGE('Material Comparison'!$AM$7:$AM$338,5),'Material Comparison'!$AM$7:$AM$338,0)) -> 267.05264 | J55: =INDEX('Material Comparison'!$R$7:$R$338,MATCH(LARGE('Material Comparison'!$AM$7:$AM$338,5),'Material Comparison'!$AM$7:$AM$338,0)) -> 15354.13 | K55: =INDEX('Material Comparison'!$Q$7:$Q$338,MATCH(LARGE('Material Comparison'!$AM$7:$AM$338,5),'Material Comparison'!$AM$7:$AM$338,0)) -> 0.11003674
B56: 6 | C56: =INDEX('Material Comparison'!$D$7:$D$338,MATCH(LARGE('Material Comparison'!$AM$7:$AM$338,6),'Material Comparison'!$AM$7:$AM$338,0)) -> 12" bell-joint restraint (pipe-to-pipe, C900) | E56: =INDEX('Material Comparison'!$B$7:$B$338,MATCH(LARGE('Material Comparison'!$AM$7:$AM$338,6),'Material Comparison'!$AM$7:$AM$338,0)) -> Item 8 | F56: =INDEX('Material Comparison'!$AQ$7:$AQ$338,MATCH(LARGE('Material Comparison'!$AM$7:$AM$338,6),'Material Comparison'!$AM$7:$AM$338,0)) -> Scholzen | G56: =INDEX('Material Comparison'!$O$7:$O$338,MATCH(LARGE('Material Comparison'!$AM$7:$AM$338,6),'Material Comparison'!$AM$7:$AM$338,0)) -> 164.48 | H56: =INDEX('Material Comparison'!$AO$7:$AO$338,MATCH(LARGE('Material Comparison'!$AM$7:$AM$338,6),'Material Comparison'!$AM$7:$AM$338,0)) -> Ferguson | I56: =INDEX('Material Comparison'!$AN$7:$AN$338,MATCH(LARGE('Material Comparison'!$AM$7:$AM$338,6),'Material Comparison'!$AM$7:$AM$338,0)) -> 259.37 | J56: =INDEX('Material Comparison'!$R$7:$R$338,MATCH(LARGE('Material Comparison'!$AM$7:$AM$338,6),'Material Comparison'!$AM$7:$AM$338,0)) -> 12525.48 | K56: =INDEX('Material Comparison'!$Q$7:$Q$338,MATCH(LARGE('Material Comparison'!$AM$7:$AM$338,6),'Material Comparison'!$AM$7:$AM$338,0)) -> 0.57690905
B57: 7 | C57: =INDEX('Material Comparison'!$D$7:$D$338,MATCH(LARGE('Material Comparison'!$AM$7:$AM$338,7),'Material Comparison'!$AM$7:$AM$338,0)) -> 12" MJ x flange resilient-wedge gate valve | E57: =INDEX('Material Comparison'!$B$7:$B$338,MATCH(LARGE('Material Comparison'!$AM$7:$AM$338,7),'Material Comparison'!$AM$7:$AM$338,0)) -> Item 9.3 | F57: =INDEX('Material Comparison'!$AQ$7:$AQ$338,MATCH(LARGE('Material Comparison'!$AM$7:$AM$338,7),'Material Comparison'!$AM$7:$AM$338,0)) -> HD Fowler | G57: =INDEX('Material Comparison'!$O$7:$O$338,MATCH(LARGE('Material Comparison'!$AM$7:$AM$338,7),'Material Comparison'!$AM$7:$AM$338,0)) -> 3181.88 | H57: =INDEX('Material Comparison'!$AO$7:$AO$338,MATCH(LARGE('Material Comparison'!$AM$7:$AM$338,7),'Material Comparison'!$AM$7:$AM$338,0)) -> Ferguson | I57: =INDEX('Material Comparison'!$AN$7:$AN$338,MATCH(LARGE('Material Comparison'!$AM$7:$AM$338,7),'Material Comparison'!$AM$7:$AM$338,0)) -> 3889.27 | J57: =INDEX('Material Comparison'!$R$7:$R$338,MATCH(LARGE('Material Comparison'!$AM$7:$AM$338,7),'Material Comparison'!$AM$7:$AM$338,0)) -> 11318.24 | K57: =INDEX('Material Comparison'!$Q$7:$Q$338,MATCH(LARGE('Material Comparison'!$AM$7:$AM$338,7),'Material Comparison'!$AM$7:$AM$338,0)) -> 0.22231825
B58: 8 | C58: =INDEX('Material Comparison'!$D$7:$D$338,MATCH(LARGE('Material Comparison'!$AM$7:$AM$338,8),'Material Comparison'!$AM$7:$AM$338,0)) -> 8" Cla-Val 131 electronic control valve + VC-22D controller | E58: =INDEX('Material Comparison'!$B$7:$B$338,MATCH(LARGE('Material Comparison'!$AM$7:$AM$338,8),'Material Comparison'!$AM$7:$AM$338,0)) -> Item 5 | F58: =INDEX('Material Comparison'!$AQ$7:$AQ$338,MATCH(LARGE('Material Comparison'!$AM$7:$AM$338,8),'Material Comparison'!$AM$7:$AM$338,0)) -> Mountainland | G58: =INDEX('Material Comparison'!$O$7:$O$338,MATCH(LARGE('Material Comparison'!$AM$7:$AM$338,8),'Material Comparison'!$AM$7:$AM$338,0)) -> 27719.12 | H58: =INDEX('Material Comparison'!$AO$7:$AO$338,MATCH(LARGE('Material Comparison'!$AM$7:$AM$338,8),'Material Comparison'!$AM$7:$AM$338,0)) -> Ferguson | I58: =INDEX('Material Comparison'!$AN$7:$AN$338,MATCH(LARGE('Material Comparison'!$AM$7:$AM$338,8),'Material Comparison'!$AM$7:$AM$338,0)) -> 37321.6 | J58: =INDEX('Material Comparison'!$R$7:$R$338,MATCH(LARGE('Material Comparison'!$AM$7:$AM$338,8),'Material Comparison'!$AM$7:$AM$338,0)) -> 9602.48 | K58: =INDEX('Material Comparison'!$Q$7:$Q$338,MATCH(LARGE('Material Comparison'!$AM$7:$AM$338,8),'Material Comparison'!$AM$7:$AM$338,0)) -> 0.34642081
B59: 9 | C59: =INDEX('Material Comparison'!$D$7:$D$338,MATCH(LARGE('Material Comparison'!$AM$7:$AM$338,9),'Material Comparison'!$AM$7:$AM$338,0)) -> 16" DR18 PVC pipe (gasketed) | E59: =INDEX('Material Comparison'!$B$7:$B$338,MATCH(LARGE('Material Comparison'!$AM$7:$AM$338,9),'Material Comparison'!$AM$7:$AM$338,0)) -> Item 7 | F59: =INDEX('Material Comparison'!$AQ$7:$AQ$338,MATCH(LARGE('Material Comparison'!$AM$7:$AM$338,9),'Material Comparison'!$AM$7:$AM$338,0)) -> Ferguson | G59: =INDEX('Material Comparison'!$O$7:$O$338,MATCH(LARGE('Material Comparison'!$AM$7:$AM$338,9),'Material Comparison'!$AM$7:$AM$338,0)) -> 35.9 | H59: =INDEX('Material Comparison'!$AO$7:$AO$338,MATCH(LARGE('Material Comparison'!$AM$7:$AM$338,9),'Material Comparison'!$AM$7:$AM$338,0)) -> HD Fowler | I59: =INDEX('Material Comparison'!$AN$7:$AN$338,MATCH(LARGE('Material Comparison'!$AM$7:$AM$338,9),'Material Comparison'!$AM$7:$AM$338,0)) -> 38.83 | J59: =INDEX('Material Comparison'!$R$7:$R$338,MATCH(LARGE('Material Comparison'!$AM$7:$AM$338,9),'Material Comparison'!$AM$7:$AM$338,0)) -> 8790 | K59: =INDEX('Material Comparison'!$Q$7:$Q$338,MATCH(LARGE('Material Comparison'!$AM$7:$AM$338,9),'Material Comparison'!$AM$7:$AM$338,0)) -> 0.081615599
B60: 10 | C60: =INDEX('Material Comparison'!$D$7:$D$338,MATCH(LARGE('Material Comparison'!$AM$7:$AM$338,10),'Material Comparison'!$AM$7:$AM$338,0)) -> Casing spacers (stainless, multi-carrier cluster) | E60: =INDEX('Material Comparison'!$B$7:$B$338,MATCH(LARGE('Material Comparison'!$AM$7:$AM$338,10),'Material Comparison'!$AM$7:$AM$338,0)) -> Item 16 | F60: =INDEX('Material Comparison'!$AQ$7:$AQ$338,MATCH(LARGE('Material Comparison'!$AM$7:$AM$338,10),'Material Comparison'!$AM$7:$AM$338,0)) -> Mountainland | G60: =INDEX('Material Comparison'!$O$7:$O$338,MATCH(LARGE('Material Comparison'!$AM$7:$AM$338,10),'Material Comparison'!$AM$7:$AM$338,0)) -> 363.75 | H60: =INDEX('Material Comparison'!$AO$7:$AO$338,MATCH(LARGE('Material Comparison'!$AM$7:$AM$338,10),'Material Comparison'!$AM$7:$AM$338,0)) -> Ferguson | I60: =INDEX('Material Comparison'!$AN$7:$AN$338,MATCH(LARGE('Material Comparison'!$AM$7:$AM$338,10),'Material Comparison'!$AM$7:$AM$338,0)) -> 437.65 | J60: =INDEX('Material Comparison'!$R$7:$R$338,MATCH(LARGE('Material Comparison'!$AM$7:$AM$338,10),'Material Comparison'!$AM$7:$AM$338,0)) -> 8646.3 | K60: =INDEX('Material Comparison'!$Q$7:$Q$338,MATCH(LARGE('Material Comparison'!$AM$7:$AM$338,10),'Material Comparison'!$AM$7:$AM$338,0)) -> 0.20316151
B61: 11 | C61: =INDEX('Material Comparison'!$D$7:$D$338,MATCH(LARGE('Material Comparison'!$AM$7:$AM$338,11),'Material Comparison'!$AM$7:$AM$338,0)) -> 36" MJ restraint (DI) | E61: =INDEX('Material Comparison'!$B$7:$B$338,MATCH(LARGE('Material Comparison'!$AM$7:$AM$338,11),'Material Comparison'!$AM$7:$AM$338,0)) -> Item 10.6 | F61: =INDEX('Material Comparison'!$AQ$7:$AQ$338,MATCH(LARGE('Material Comparison'!$AM$7:$AM$338,11),'Material Comparison'!$AM$7:$AM$338,0)) -> Ferguson | G61: =INDEX('Material Comparison'!$O$7:$O$338,MATCH(LARGE('Material Comparison'!$AM$7:$AM$338,11),'Material Comparison'!$AM$7:$AM$338,0)) -> 1028.27 | H61: =INDEX('Material Comparison'!$AO$7:$AO$338,MATCH(LARGE('Material Comparison'!$AM$7:$AM$338,11),'Material Comparison'!$AM$7:$AM$338,0)) -> HD Fowler | I61: =INDEX('Material Comparison'!$AN$7:$AN$338,MATCH(LARGE('Material Comparison'!$AM$7:$AM$338,11),'Material Comparison'!$AM$7:$AM$338,0)) -> 2064.13 | J61: =INDEX('Material Comparison'!$R$7:$R$338,MATCH(LARGE('Material Comparison'!$AM$7:$AM$338,11),'Material Comparison'!$AM$7:$AM$338,0)) -> 4143.44 | K61: =INDEX('Material Comparison'!$Q$7:$Q$338,MATCH(LARGE('Material Comparison'!$AM$7:$AM$338,11),'Material Comparison'!$AM$7:$AM$338,0)) -> 1.0073813
B62: 12 | C62: =INDEX('Material Comparison'!$D$7:$D$338,MATCH(LARGE('Material Comparison'!$AM$7:$AM$338,12),'Material Comparison'!$AM$7:$AM$338,0)) -> Fire hydrant, MJ inlet, 6" (red) | E62: =INDEX('Material Comparison'!$B$7:$B$338,MATCH(LARGE('Material Comparison'!$AM$7:$AM$338,12),'Material Comparison'!$AM$7:$AM$338,0)) -> Item 11 | F62: =INDEX('Material Comparison'!$AQ$7:$AQ$338,MATCH(LARGE('Material Comparison'!$AM$7:$AM$338,12),'Material Comparison'!$AM$7:$AM$338,0)) -> Mountainland | G62: =INDEX('Material Comparison'!$O$7:$O$338,MATCH(LARGE('Material Comparison'!$AM$7:$AM$338,12),'Material Comparison'!$AM$7:$AM$338,0)) -> 3570.4476 | H62: =INDEX('Material Comparison'!$AO$7:$AO$338,MATCH(LARGE('Material Comparison'!$AM$7:$AM$338,12),'Material Comparison'!$AM$7:$AM$338,0)) -> Ferguson | I62: =INDEX('Material Comparison'!$AN$7:$AN$338,MATCH(LARGE('Material Comparison'!$AM$7:$AM$338,12),'Material Comparison'!$AM$7:$AM$338,0)) -> 3772 | J62: =INDEX('Material Comparison'!$R$7:$R$338,MATCH(LARGE('Material Comparison'!$AM$7:$AM$338,12),'Material Comparison'!$AM$7:$AM$338,0)) -> 3224.8376 | K62: =INDEX('Material Comparison'!$Q$7:$Q$338,MATCH(LARGE('Material Comparison'!$AM$7:$AM$338,12),'Material Comparison'!$AM$7:$AM$338,0)) -> 0.056450163
B64: 7 · WHAT THIS MEANS (read before awarding anything)
B65: Headline totals mislead. | C65: HD Fowler ($1.04M) and Scholzen ($1.11M) look cheapest only because they left scope out: no steel casing pipe, spacers or end seals (about $183K at competing prices), and HD Fowler priced its pipe-joint restraints but left the quantities 'to contractor' (about $78K, not in its total). Put every supplier on the same scope and quantities and the order flips: Mountainland $1.27M (lowest), HD Fowler +1.3%, Scholzen +1.5%, Ferguson +4.3%.
B66: Price won't decide this — certainty will. | C66: The three lowest comparable totals sit within 1.5% of each other. The real differences are scope completeness, quote validity and terms. Your blind spot is comparing four takeoffs, not four prices: suppliers disagree on quantities (e.g. 12" bell restraints: 154 / 92 / 132) and on spool lengths, so whoever counted fewest looks cheapest.
B67: Ferguson: best and worst prices in one quote. | C67: Ferguson ranks last in total (+4.3%) yet is lowest on 63 rows (incl. the big-dollar 12"/16" pipe and casing) and highest on 57 — mostly restraints, fittings and small parts, which is where to negotiate. Scholzen is highest on 63 rows and lowest on only 18 — line for line it is the priciest; its total is low only because of skipped scope. HD Fowler has the best low/high ratio (48 vs 24).
B68: Split-buy upside is real but conditional. | C68: Buying every comparable line from its lowest bidder totals $1.20M, $70K (5.5%) under the best single-supplier award; awarding each bid item to its cheapest supplier gets $32K (2.5%). But Ferguson's prices are 'contingent upon award of entire bill of materials' — splitting can void them. Get that in writing before you rely on the split.
B69: Three of four quotes are stale. | C69: Scholzen's quote is dated 7/24/26 and valid 24 hours; Mountainland's expired 9/15/26 (the day before its own issue date); HD Fowler prints no date or validity and reserves tariff repricing at shipment. Only Ferguson (9/18/26, good ~30 days) is current. Treat every number here as indicative until re-confirmed.
B70: Challenge these before award (details on Notes & Flags). | C70: Ferguson: $1,871.76 curb-stop handle (vs $40), 4" Sch 80 PVC at $20.98/ft (vs ~$5), bell restraints 40–65% over Mountainland/Scholzen. Scholzen: no valve bolt sets on Items 9.1–9.4, both Sch 80 and Sch 40 3" conduit, $1,083 split Stargrips. Mountainland: 12" AV-TEK valve quoted without its electric actuator (~$12K short).
B71: Next steps, in order. | C71: 1) Send all four the same quantity list (the Ref Qty column) and require a price on every row — especially bell restraints, casing/spacers/end seals and valve hardware. 2) Get written validity of 30+ days from Scholzen, Mountainland and HD Fowler. 3) Use Mountainland/Scholzen restraint and fitting prices to push Ferguson down. 4) Confirm alt-spec rows (Cla-Val voltage, butterfly-valve class, casing wall, hydrant bury) with the engineer. 5) Decide single vs split award only after steps 1–4 — then update the blue cells and this workbook re-ranks itself.
B73: Prepared by Claude from the four supplier quotes in the repo. Quote lines were extracted programmatically (Ferguson, HD Fowler, Mountainland) and transcribed from the scanned Scholzen PDF; every supplier's lines tie to its printed total. Verify quantities and specs against the plans before buying.

Sheet Material Comparison
A1: CHURCH FARM ROAD PUMP STATION & PIPELINE — MATERIAL BID COMPARISON
A2: Washington City, Utah · 4 supplier quotes · unit prices normalized to a common UoM · Extended = unit price × Ref Qty (blue, editable) so every supplier is compared on the same quantity
A3: KEY: | D3: Lowest bid | G3: 2nd lowest | I3: Middle (3rd of 4) | K3: Highest bid | M3: Only one quote | O3: — = not quoted | V3: 3 quotes → green / yellow / red · 2 quotes → green / red · ties share the better color · blue cells are inputs
A4: Tip: filter column T to 'Like-for-like' for the cleanest head-to-head; expand the [+] group above column W for each supplier's own quoted quantities.
A5: MATERIAL | G5: UNIT PRICE ($ per UoM) | K5: EXTENDED @ REF QTY ($) | O5: ANALYSIS | V5: NOTES / SPEC FLAGS | W5: QUOTED QTY (each supplier's own takeoff)
A6: Row | B6: Bid item | C6: Group | D6: Material | E6: UoM | F6: Ref qty | G6: Ferguson | H6: HD Fowler | I6: Mountainland | J6: Scholzen | K6: Ferguson | L6: HD Fowler | M6: Mountainland | N6: Scholzen | O6: Lowest unit ($) | P6: Best supplier | Q6: High vs low | R6: $ spread @ ref qty | S6: # quotes | T6: Comparability | U6: Qty check | V6: Notes | W6: Ferguson | X6: HD Fowler | Y6: Mountainland | Z6: Scholzen | AA6: Rank: Ferguson | AB6: Rank: HD Fowler | AC6: Rank: Mountainland | AD6: Rank: Scholzen | AE6: Color code: Ferguson | AF6: Color code: HD Fowler | AG6: Color code: Mountainland | AH6: Color code: Scholzen | AI6: Comparable-basis ext: Ferguson | AJ6: Comparable-basis ext: HD Fowler | AK6: Comparable-basis ext: Mountainland | AL6: Comparable-basis ext: Scholzen | AM6: Spread key | AN6: Highest unit | AO6: Highest supplier | AP6: Best ext | AQ6: Winner (first)
B7: BID ITEM 5 — Pump station, meter vault & valve vault
A8: R001 | B8: Item 5 | C8: DI fittings | D8: 16" flanged 90° elbow | E8: EA | F8: 2 | G8: =IF(COUNTIF('Quote Lines'!$P$3:$P$805,$A8&"|"&G$6&"|1")=0,"—",SUMIFS('Quote Lines'!$O$3:$O$805,'Quote Lines'!$P$3:$P$805,$A8&"|"&G$6&"|1")/SUMIFS('Quote Lines'!$L$3:$L$805,'Quote Lines'!$P$3:$P$805,$A8&"|"&G$6&"|1")) -> 1493.17 | H8: =IF(COUNTIF('Quote Lines'!$P$3:$P$805,$A8&"|"&H$6&"|1")=0,"—",SUMIFS('Quote Lines'!$O$3:$O$805,'Quote Lines'!$P$3:$P$805,$A8&"|"&H$6&"|1")/SUMIFS('Quote Lines'!$L$3:$L$805,'Quote Lines'!$P$3:$P$805,$A8&"|"&H$6&"|1")) -> 1560.11 | I8: =IF(COUNTIF('Quote Lines'!$P$3:$P$805,$A8&"|"&I$6&"|1")=0,"—",SUMIFS('Quote Lines'!$O$3:$O$805,'Quote Lines'!$P$3:$P$805,$A8&"|"&I$6&"|1")/SUMIFS('Quote Lines'!$L$3:$L$805,'Quote Lines'!$P$3:$P$805,$A8&"|"&I$6&"|1")) -> 1693.9 | J8: =IF(COUNTIF('Quote Lines'!$P$3:$P$805,$A8&"|"&J$6&"|1")=0,"—",SUMIFS('Quote Lines'!$O$3:$O$805,'Quote Lines'!$P$3:$P$805,$A8&"|"&J$6&"|1")/SUMIFS('Quote Lines'!$L$3:$L$805,'Quote Lines'!$P$3:$P$805,$A8&"|"&J$6&"|1")) -> 1634 | K8: =IF(ISNUMBER(G8),G8*$F8,"—") -> 2986.34 | L8: =IF(ISNUMBER(H8),H8*$F8,"—") -> 3120.22 | M8: =IF(ISNUMBER(I8),I8*$F8,"—") -> 3387.8 | N8: =IF(ISNUMBER(J8),J8*$F8,"—") -> 3268 | O8: =IF($S8=0,"—",MIN(G8:J8)) -> 1493.17 | P8: =IF($S8=0,"—",IF(COUNTIF(G8:J8,O8)>1,"Tie",INDEX($G$6:$J$6,MATCH(O8,G8:J8,0)))) -> Ferguson | Q8: =IF($S8>=2,MAX(G8:J8)/MIN(G8:J8)-1,"—") -> 0.13443211 | R8: =IF($S8>=2,(MAX(G8:J8)-MIN(G8:J8))*$F8,"—") -> 401.46 | S8: =COUNT(G8:J8) -> 4 | T8: =IF($S8<=1,IF($S8=1,"Single quote","—"),"Like-for-like") -> Like-for-like | U8: =IF(COUNT(W8:Z8)<2,"",IF(MAX(W8:Z8)=MIN(W8:Z8),"OK","Qty differs")) -> OK | W8: =IF(COUNTIFS('Quote Lines'!$P$3:$P$805,$A8&"|"&G$6&"|1",'Quote Lines'!$M$3:$M$805,"Y")=0,"",SUMIFS('Quote Lines'!$L$3:$L$805,'Quote Lines'!$P$3:$P$805,$A8&"|"&G$6&"|1",'Quote Lines'!$M$3:$M$805,"Y")) -> 2 | X8: =IF(COUNTIFS('Quote Lines'!$P$3:$P$805,$A8&"|"&H$6&"|1",'Quote Lines'!$M$3:$M$805,"Y")=0,"",SUMIFS('Quote Lines'!$L$3:$L$805,'Quote Lines'!$P$3:$P$805,$A8&"|"&H$6&"|1",'Quote Lines'!$M$3:$M$805,"Y")) -> 2 | Y8: =IF(COUNTIFS('Quote Lines'!$P$3:$P$805,$A8&"|"&I$6&"|1",'Quote Lines'!$M$3:$M$805,"Y")=0,"",SUMIFS('Quote Lines'!$L$3:$L$805,'Quote Lines'!$P$3:$P$805,$A8&"|"&I$6&"|1",'Quote Lines'!$M$3:$M$805,"Y")) -> 2 | Z8: =IF(COUNTIFS('Quote Lines'!$P$3:$P$805,$A8&"|"&J$6&"|1",'Quote Lines'!$M$3:$M$805,"Y")=0,"",SUMIFS('Quote Lines'!$L$3:$L$805,'Quote Lines'!$P$3:$P$805,$A8&"|"&J$6&"|1",'Quote Lines'!$M$3:$M$805,"Y")) -> 2 | AA8: =IF(ISNUMBER(G8),1+SUMPRODUCT(ISNUMBER($G8:$J8)*($G8:$J8<G8)),"") -> 1 | AB8: =IF(ISNUMBER(H8),1+SUMPRODUCT(ISNUMBER($G8:$J8)*($G8:$J8<H8)),"") -> 2 | AC8: =IF(ISNUMBER(I8),1+SUMPRODUCT(ISNUMBER($G8:$J8)*($G8:$J8<I8)),"") -> 4 | AD8: =IF(ISNUMBER(J8),1+SUMPRODUCT(ISNUMBER($G8:$J8)*($G8:$J8<J8)),"") -> 3 | AE8: =IF(NOT(ISNUMBER(G8)),0,IF($S8<2,5,IF(AA8=1,1,IF(G8=MAX($G8:$J8),4,IF(AA8=2,2,3))))) -> 1 | AF8: =IF(NOT(ISNUMBER(H8)),0,IF($S8<2,5,IF(AB8=1,1,IF(H8=MAX($G8:$J8),4,IF(AB8=2,2,3))))) -> 2 | AG8: =IF(NOT(ISNUMBER(I8)),0,IF($S8<2,5,IF(AC8=1,1,IF(I8=MAX($G8:$J8),4,IF(AC8=2,2,3))))) -> 4 | AH8: =IF(NOT(ISNUMBER(J8)),0,IF($S8<2,5,IF(AD8=1,1,IF(J8=MAX($G8:$J8),4,IF(AD8=2,2,3))))) -> 3 | AI8: =IF($S8>=2,IF(ISNUMBER(G8),G8*$F8,MIN($G8:$J8)*$F8),0) -> 2986.34 | AJ8: =IF($S8>=2,IF(ISNUMBER(H8),H8*$F8,MIN($G8:$J8)*$F8),0) -> 3120.22 | AK8: =IF($S8>=2,IF(ISNUMBER(I8),I8*$F8,MIN($G8:$J8)*$F8),0) -> 3387.8 | AL8: =IF($S8>=2,IF(ISNUMBER(J8),J8*$F8,MIN($G8:$J8)*$F8),0) -> 3268 | AM8: =IF($S8>=2,$R8+ROW()/1000000,"") -> 401.46001 | AN8: =IF($S8>=2,MAX(G8:J8),"") -> 1693.9 | AO8: =IF($S8>=2,INDEX($G$6:$J$6,MATCH(MAX(G8:J8),G8:J8,0)),"") -> Mountainland | AP8: =IF($S8>=2,MIN(G8:J8)*$F8,0) -> 2986.34 | AQ8: =IF($S8>=2,INDEX($G$6:$J$6,MATCH(MIN(G8:J8),G8:J8,0)),"") -> Ferguson
A9: R002 | B9: Item 5 | C9: DI fittings | D9: 16" x 10" flanged concentric reducer | E9: EA | F9: 2 | G9: =IF(COUNTIF('Quote Lines'!$P$3:$P$805,$A9&"|"&G$6&"|1")=0,"—",SUMIFS('Quote Lines'!$O$3:$O$805,'Quote Lines'!$P$3:$P$805,$A9&"|"&G$6&"|1")/SUMIFS('Quote Lines'!$L$3:$L$805,'Quote Lines'!$P$3:$P$805,$A9&"|"&G$6&"|1")) -> 946.86 | H9: =IF(COUNTIF('Quote Lines'!$P$3:$P$805,$A9&"|"&H$6&"|1")=0,"—",SUMIFS('Quote Lines'!$O$3:$O$805,'Quote Lines'!$P$3:$P$805,$A9&"|"&H$6&"|1")/SUMIFS('Quote Lines'!$L$3:$L$805,'Quote Lines'!$P$3:$P$805,$A9&"|"&H$6&"|1")) -> 989.3 | I9: =IF(COUNTIF('Quote Lines'!$P$3:$P$805,$A9&"|"&I$6&"|1")=0,"—",SUMIFS('Quote Lines'!$O$3:$O$805,'Quote Lines'!$P$3:$P$805,$A9&"|"&I$6&"|1")/SUMIFS('Quote Lines'!$L$3:$L$805,'Quote Lines'!$P$3:$P$805,$A9&"|"&I$6&"|1")) -> 1074.145 | J9: =IF(COUNTIF('Quote Lines'!$P$3:$P$805,$A9&"|"&J$6&"|1")=0,"—",SUMIFS('Quote Lines'!$O$3:$O$805,'Quote Lines'!$P$3:$P$805,$A9&"|"&J$6&"|1")/SUMIFS('Quote Lines'!$L$3:$L$805,'Quote Lines'!$P$3:$P$805,$A9&"|"&J$6&"|1")) -> 1054.02 | K9: =IF(ISNUMBER(G9),G9*$F9,"—") -> 1893.72 | L9: =IF(ISNUMBER(H9),H9*$F9,"—") -> 1978.6 | M9: =IF(ISNUMBER(I9),I9*$F9,"—") -> 2148.29 | N9: =IF(ISNUMBER(J9),J9*$F9,"—") -> 2108.04 | O9: =IF($S9=0,"—",MIN(G9:J9)) -> 946.86 | P9: =IF($S9=0,"—",IF(COUNTIF(G9:J9,O9)>1,"Tie",INDEX($G$6:$J$6,MATCH(O9,G9:J9,0)))) -> Ferguson | Q9: =IF($S9>=2,MAX(G9:J9)/MIN(G9:J9)-1,"—") -> 0.13442853 | R9: =IF($S9>=2,(MAX(G9:J9)-MIN(G9:J9))*$F9,"—") -> 254.57 | S9: =COUNT(G9:J9) -> 4 | T9: =IF($S9<=1,IF($S9=1,"Single quote","—"),"Like-for-like") -> Like-for-like | U9: =IF(COUNT(W9:Z9)<2,"",IF(MAX(W9:Z9)=MIN(W9:Z9),"OK","Qty differs")) -> OK | W9: =IF(COUNTIFS('Quote Lines'!$P$3:$P$805,$A9&"|"&G$6&"|1",'Quote Lines'!$M$3:$M$805,"Y")=0,"",SUMIFS('Quote Lines'!$L$3:$L$805,'Quote Lines'!$P$3:$P$805,$A9&"|"&G$6&"|1",'Quote Lines'!$M$3:$M$805,"Y")) -> 2 | X9: =IF(COUNTIFS('Quote Lines'!$P$3:$P$805,$A9&"|"&H$6&"|1",'Quote Lines'!$M$3:$M$805,"Y")=0,"",SUMIFS('Quote Lines'!$L$3:$L$805,'Quote Lines'!$P$3:$P$805,$A9&"|"&H$6&"|1",'Quote Lines'!$M$3:$M$805,"Y")) -> 2 | Y9: =IF(COUNTIFS('Quote Lines'!$P$3:$P$805,$A9&"|"&I$6&"|1",'Quote Lines'!$M$3:$M$805,"Y")=0,"",SUMIFS('Quote Lines'!$L$3:$L$805,'Quote Lines'!$P$3:$P$805,$A9&"|"&I$6&"|1",'Quote Lines'!$M$3:$M$805,"Y")) -> 2 | Z9: =IF(COUNTIFS('Quote Lines'!$P$3:$P$805,$A9&"|"&J$6&"|1",'Quote Lines'!$M$3:$M$805,"Y")=0,"",SUMIFS('Quote Lines'!$L$3:$L$805,'Quote Lines'!$P$3:$P$805,$A9&"|"&J$6&"|1",'Quote Lines'!$M$3:$M$805,"Y")) -> 2 | AA9: =IF(ISNUMBER(G9),1+SUMPRODUCT(ISNUMBER($G9:$J9)*($G9:$J9<G9)),"") -> 1 | AB9: =IF(ISNUMBER(H9),1+SUMPRODUCT(ISNUMBER($G9:$J9)*($G9:$J9<H9)),"") -> 2 | AC9: =IF(ISNUMBER(I9),1+SUMPRODUCT(ISNUMBER($G9:$J9)*($G9:$J9<I9)),"") -> 4 | AD9: =IF(ISNUMBER(J9),1+SUMPRODUCT(ISNUMBER($G9:$J9)*($G9:$J9<J9)),"") -> 3 | AE9: =IF(NOT(ISNUMBER(G9)),0,IF($S9<2,5,IF(AA9=1,1,IF(G9=MAX($G9:$J9),4,IF(AA9=2,2,3))))) -> 1 | AF9: =IF(NOT(ISNUMBER(H9)),0,IF($S9<2,5,IF(AB9=1,1,IF(H9=MAX($G9:$J9),4,IF(AB9=2,2,3))))) -> 2 | AG9: =IF(NOT(ISNUMBER(I9)),0,IF($S9<2,5,IF(AC9=1,1,IF(I9=MAX($G9:$J9),4,IF(AC9=2,2,3))))) -> 4 | AH9: =IF(NOT(ISNUMBER(J9)),0,IF($S9<2,5,IF(AD9=1,1,IF(J9=MAX($G9:$J9),4,IF(AD9=2,2,3))))) -> 3 | AI9: =IF($S9>=2,IF(ISNUMBER(G9),G9*$F9,MIN($G9:$J9)*$F9),0) -> 1893.72 | AJ9: =IF($S9>=2,IF(ISNUMBER(H9),H9*$F9,MIN($G9:$J9)*$F9),0) -> 1978.6 | AK9: =IF($S9>=2,IF(ISNUMBER(I9),I9*$F9,MIN($G9:$J9)*$F9),0) -> 2148.29 | AL9: =IF($S9>=2,IF(ISNUMBER(J9),J9*$F9,MIN($G9:$J9)*$F9),0) -> 2108.04 | AM9: =IF($S9>=2,$R9+ROW()/1000000,"") -> 254.57001 | AN9: =IF($S9>=2,MAX(G9:J9),"") -> 1074.145 | AO9: =IF($S9>=2,INDEX($G$6:$J$6,MATCH(MAX(G9:J9),G9:J9,0)),"") -> Mountainland | AP9: =IF($S9>=2,MIN(G9:J9)*$F9,0) -> 1893.72 | AQ9: =IF($S9>=2,INDEX($G$6:$J$6,MATCH(MIN(G9:J9),G9:J9,0)),"") -> Ferguson
A10: R003 | B10: Item 5 | C10: DI fittings | D10: 16" x 12" flanged concentric reducer | E10: EA | F10: 1 | G10: — | H10: =IF(COUNTIF('Quote Lines'!$P$3:$P$805,$A10&"|"&H$6&"|1")=0,"—",SUMIFS('Quote Lines'!$O$3:$O$805,'Quote Lines'!$P$3:$P$805,$A10&"|"&H$6&"|1")/SUMIFS('Quote Lines'!$L$3:$L$805,'Quote Lines'!$P$3:$P$805,$A10&"|"&H$6&"|1")) -> 1309.41 | I10: — | J10: =IF(COUNTIF('Quote Lines'!$P$3:$P$805,$A10&"|"&J$6&"|1")=0,"—",SUMIFS('Quote Lines'!$O$3:$O$805,'Quote Lines'!$P$3:$P$805,$A10&"|"&J$6&"|1")/SUMIFS('Quote Lines'!$L$3:$L$805,'Quote Lines'!$P$3:$P$805,$A10&"|"&J$6&"|1")) -> 1395.07 | K10: =IF(ISNUMBER(G10),G10*$F10,"—") -> — | L10: =IF(ISNUMBER(H10),H10*$F10,"—") -> 1309.41 | M10: =IF(ISNUMBER(I10),I10*$F10,"—") -> — | N10: =IF(ISNUMBER(J10),J10*$F10,"—") -> 1395.07 | O10: =IF($S10=0,"—",MIN(G10:J10)) -> 1309.41 | P10: =IF($S10=0,"—",IF(COUNTIF(G10:J10,O10)>1,"Tie",INDEX($G$6:$J$6,MATCH(O10,G10:J10,0)))) -> HD Fowler | Q10: =IF($S10>=2,MAX(G10:J10)/MIN(G10:J10)-1,"—") -> 0.065418776 | R10: =IF($S10>=2,(MAX(G10:J10)-MIN(G10:J10))*$F10,"—") -> 85.66 | S10: =COUNT(G10:J10) -> 2 | T10: =IF($S10<=1,IF($S10=1,"Single quote","—"),"Like-for-like") -> Like-for-like | U10: =IF(COUNT(W10:Z10)<2,"",IF(MAX(W10:Z10)=MIN(W10:Z10),"OK","Qty differs")) -> OK | V10: Ferguson quoted MJ-end 16x12 reducers instead (next row). | X10: =IF(COUNTIFS('Quote Lines'!$P$3:$P$805,$A10&"|"&H$6&"|1",'Quote Lines'!$M$3:$M$805,"Y")=0,"",SUMIFS('Quote Lines'!$L$3:$L$805,'Quote Lines'!$P$3:$P$805,$A10&"|"&H$6&"|1",'Quote Lines'!$M$3:$M$805,"Y")) -> 1 | Z10: =IF(COUNTIFS('Quote Lines'!$P$3:$P$805,$A10&"|"&J$6&"|1",'Quote Lines'!$M$3:$M$805,"Y")=0,"",SUMIFS('Quote Lines'!$L$3:$L$805,'Quote Lines'!$P$3:$P$805,$A10&"|"&J$6&"|1",'Quote Lines'!$M$3:$M$805,"Y")) -> 1 | AA10: =IF(ISNUMBER(G10),1+SUMPRODUCT(ISNUMBER($G10:$J10)*($G10:$J10<G10)),"") | AB10: =IF(ISNUMBER(H10),1+SUMPRODUCT(ISNUMBER($G10:$J10)*($G10:$J10<H10)),"") -> 1 | AC10: =IF(ISNUMBER(I10),1+SUMPRODUCT(ISNUMBER($G10:$J10)*($G10:$J10<I10)),"") | AD10: =IF(ISNUMBER(J10),1+SUMPRODUCT(ISNUMBER($G10:$J10)*($G10:$J10<J10)),"") -> 2 | AE10: =IF(NOT(ISNUMBER(G10)),0,IF($S10<2,5,IF(AA10=1,1,IF(G10=MAX($G10:$J10),4,IF(AA10=2,2,3))))) -> 0 | AF10: =IF(NOT(ISNUMBER(H10)),0,IF($S10<2,5,IF(AB10=1,1,IF(H10=MAX($G10:$J10),4,IF(AB10=2,2,3))))) -> 1 | AG10: =IF(NOT(ISNUMBER(I10)),0,IF($S10<2,5,IF(AC10=1,1,IF(I10=MAX($G10:$J10),4,IF(AC10=2,2,3))))) -> 0 | AH10: =IF(NOT(ISNUMBER(J10)),0,IF($S10<2,5,IF(AD10=1,1,IF(J10=MAX($G10:$J10),4,IF(AD10=2,2,3))))) -> 4 | AI10: =IF($S10>=2,IF(ISNUMBER(G10),G10*$F10,MIN($G10:$J10)*$F10),0) -> 1309.41 | AJ10: =IF($S10>=2,IF(ISNUMBER(H10),H10*$F10,MIN($G10:$J10)*$F10),0) -> 1309.41 | AK10: =IF($S10>=2,IF(ISNUMBER(I10),I10*$F10,MIN($G10:$J10)*$F10),0) -> 1309.41 | AL10: =IF($S10>=2,IF(ISNUMBER(J10),J10*$F10,MIN($G10:$J10)*$F10),0) -> 1395.07 | AM10: =IF($S10>=2,$R10+ROW()/1000000,"") -> 85.66001 | AN10: =IF($S10>=2,MAX(G10:J10),"") -> 1395.07 | AO10: =IF($S10>=2,INDEX($G$6:$J$6,MATCH(MAX(G10:J10),G10:J10,0)),"") -> Scholzen | AP10: =IF($S10>=2,MIN(G10:J10)*$F10,0) -> 1309.41 | AQ10: =IF($S10>=2,INDEX($G$6:$J$6,MATCH(MIN(G10:J10),G10:J10,0)),"") -> HD Fowler
A11: R004 | B11: Item 5 | C11: DI fittings | D11: 16" x 12" MJ reducer (all-bell / large-end) | E11: EA | F11: 2 | G11: =IF(COUNTIF('Quote Lines'!$P$3:$P$805,$A11&"|"&G$6&"|1")=0,"—",SUMIFS('Quote Lines'!$O$3:$O$805,'Quote Lines'!$P$3:$P$805,$A11&"|"&G$6&"|1")/SUMIFS('Quote Lines'!$L$3:$L$805,'Quote Lines'!$P$3:$P$805,$A11&"|"&G$6&"|1")) -> 519.874 | H11: =IF(COUNTIF('Quote Lines'!$P$3:$P$805,$A11&"|"&H$6&"|1")=0,"—",SUMIFS('Quote Lines'!$O$3:$O$805,'Quote Lines'!$P$3:$P$805,$A11&"|"&H$6&"|1")/SUMIFS('Quote Lines'!$L$3:$L$805,'Quote Lines'!$P$3:$P$805,$A11&"|"&H$6&"|1")) -> 542.5 | I11: =IF(COUNTIF('Quote Lines'!$P$3:$P$805,$A11&"|"&I$6&"|1")=0,"—",SUMIFS('Quote Lines'!$O$3:$O$805,'Quote Lines'!$P$3:$P$805,$A11&"|"&I$6&"|1")/SUMIFS('Quote Lines'!$L$3:$L$805,'Quote Lines'!$P$3:$P$805,$A11&"|"&I$6&"|1")) -> 589.02333 | J11: =IF(COUNTIF('Quote Lines'!$P$3:$P$805,$A11&"|"&J$6&"|1")=0,"—",SUMIFS('Quote Lines'!$O$3:$O$805,'Quote Lines'!$P$3:$P$805,$A11&"|"&J$6&"|1")/SUMIFS('Quote Lines'!$L$3:$L$805,'Quote Lines'!$P$3:$P$805,$A11&"|"&J$6&"|1")) -> 568 | K11: =IF(ISNUMBER(G11),G11*$F11,"—") -> 1039.748 | L11: =IF(ISNUMBER(H11),H11*$F11,"—") -> 1085 | M11: =IF(ISNUMBER(I11),I11*$F11,"—") -> 1178.0467 | N11: =IF(ISNUMBER(J11),J11*$F11,"—") -> 1136 | O11: =IF($S11=0,"—",MIN(G11:J11)) -> 519.874 | P11: =IF($S11=0,"—",IF(COUNTIF(G11:J11,O11)>1,"Tie",INDEX($G$6:$J$6,MATCH(O11,G11:J11,0)))) -> Ferguson | Q11: =IF($S11>=2,MAX(G11:J11)/MIN(G11:J11)-1,"—") -> 0.13301172 | R11: =IF($S11>=2,(MAX(G11:J11)-MIN(G11:J11))*$F11,"—") -> 138.29867 | S11: =COUNT(G11:J11) -> 4 | T11: =IF($S11<=1,IF($S11=1,"Single quote","—"),"Alt spec – verify") -> Alt spec – verify | U11: =IF(COUNT(W11:Z11)<2,"",IF(MAX(W11:Z11)=MIN(W11:Z11),"OK","Qty differs")) -> Qty differs | V11: Ferguson mixes all-bell and large-end MJ reducers; H = 'MJ BXB'. Quantities differ by takeoff. | W11: =IF(COUNTIFS('Quote Lines'!$P$3:$P$805,$A11&"|"&G$6&"|1",'Quote Lines'!$M$3:$M$805,"Y")=0,"",SUMIFS('Quote Lines'!$L$3:$L$805,'Quote Lines'!$P$3:$P$805,$A11&"|"&G$6&"|1",'Quote Lines'!$M$3:$M$805,"Y")) -> 5 | X11: =IF(COUNTIFS('Quote Lines'!$P$3:$P$805,$A11&"|"&H$6&"|1",'Quote Lines'!$M$3:$M$805,"Y")=0,"",SUMIFS('Quote Lines'!$L$3:$L$805,'Quote Lines'!$P$3:$P$805,$A11&"|"&H$6&"|1",'Quote Lines'!$M$3:$M$805,"Y")) -> 2 | Y11: =IF(COUNTIFS('Quote Lines'!$P$3:$P$805,$A11&"|"&I$6&"|1",'Quote Lines'!$M$3:$M$805,"Y")=0,"",SUMIFS('Quote Lines'!$L$3:$L$805,'Quote Lines'!$P$3:$P$805,$A11&"|"&I$6&"|1",'Quote Lines'!$M$3:$M$805,"Y")) -> 3 | Z11: =IF(COUNTIFS('Quote Lines'!$P$3:$P$805,$A11&"|"&J$6&"|1",'Quote Lines'!$M$3:$M$805,"Y")=0,"",SUMIFS('Quote Lines'!$L$3:$L$805,'Quote Lines'!$P$3:$P$805,$A11&"|"&J$6&"|1",'Quote Lines'!$M$3:$M$805,"Y")) -> 2 | AA11: =IF(ISNUMBER(G11),1+SUMPRODUCT(ISNUMBER($G11:$J11)*($G11:$J11<G11)),"") -> 1 | AB11: =IF(ISNUMBER(H11),1+SUMPRODUCT(ISNUMBER($G11:$J11)*($G11:$J11<H11)),"") -> 2 | AC11: =IF(ISNUMBER(I11),1+SUMPRODUCT(ISNUMBER($G11:$J11)*($G11:$J11<I11)),"") -> 4 | AD11: =IF(ISNUMBER(J11),1+SUMPRODUCT(ISNUMBER($G11:$J11)*($G11:$J11<J11)),"") -> 3 | AE11: =IF(NOT(ISNUMBER(G11)),0,IF($S11<2,5,IF(AA11=1,1,IF(G11=MAX($G11:$J11),4,IF(AA11=2,2,3))))) -> 1 | AF11: =IF(NOT(ISNUMBER(H11)),0,IF($S11<2,5,IF(AB11=1,1,IF(H11=MAX($G11:$J11),4,IF(AB11=2,2,3))))) -> 2 | AG11: =IF(NOT(ISNUMBER(I11)),0,IF($S11<2,5,IF(AC11=1,1,IF(I11=MAX($G11:$J11),4,IF(AC11=2,2,3))))) -> 4 | AH11: =IF(NOT(ISNUMBER(J11)),0,IF($S11<2,5,IF(AD11=1,1,IF(J11=MAX($G11:$J11),4,IF(AD11=2,2,3))))) -> 3 | AI11: =IF($S11>=2,IF(ISNUMBER(G11),G11*$F11,MIN($G11:$J11)*$F11),0) -> 1039.748 | AJ11: =IF($S11>=2,IF(ISNUMBER(H11),H11*$F11,MIN($G11:$J11)*$F11),0) -> 1085 | AK11: =IF($S11>=2,IF(ISNUMBER(I11),I11*$F11,MIN($G11:$J11)*$F11),0) -> 1178.0467 | AL11: =IF($S11>=2,IF(ISNUMBER(J11),J11*$F11,MIN($G11:$J11)*$F11),0) -> 1136 | AM11: =IF($S11>=2,$R11+ROW()/1000000,"") -> 138.29868 | AN11: =IF($S11>=2,MAX(G11:J11),"") -> 589.02333 | AO11: =IF($S11>=2,INDEX($G$6:$J$6,MATCH(MAX(G11:J11),G11:J11,0)),"") -> Mountainland | AP11: =IF($S11>=2,MIN(G11:J11)*$F11,0) -> 1039.748 | AQ11: =IF($S11>=2,INDEX($G$6:$J$6,MATCH(MIN(G11:J11),G11:J11,0)),"") -> Ferguson
A12: R005 | B12: Item 5 | C12: DI fittings | D12: 12" flanged tee | E12: EA | F12: 1 | G12: =IF(COUNTIF('Quote Lines'!$P$3:$P$805,$A12&"|"&G$6&"|1")=0,"—",SUMIFS('Quote Lines'!$O$3:$O$805,'Quote Lines'!$P$3:$P$805,$A12&"|"&G$6&"|1")/SUMIFS('Quote Lines'!$L$3:$L$805,'Quote Lines'!$P$3:$P$805,$A12&"|"&G$6&"|1")) -> 1468.02 | H12: =IF(COUNTIF('Quote Lines'!$P$3:$P$805,$A12&"|"&H$6&"|1")=0,"—",SUMIFS('Quote Lines'!$O$3:$O$805,'Quote Lines'!$P$3:$P$805,$A12&"|"&H$6&"|1")/SUMIFS('Quote Lines'!$L$3:$L$805,'Quote Lines'!$P$3:$P$805,$A12&"|"&H$6&"|1")) -> 1533.83 | I12: — | J12: =IF(COUNTIF('Quote Lines'!$P$3:$P$805,$A12&"|"&J$6&"|1")=0,"—",SUMIFS('Quote Lines'!$O$3:$O$805,'Quote Lines'!$P$3:$P$805,$A12&"|"&J$6&"|1")/SUMIFS('Quote Lines'!$L$3:$L$805,'Quote Lines'!$P$3:$P$805,$A12&"|"&J$6&"|1")) -> 1707 | K12: =IF(ISNUMBER(G12),G12*$F12,"—") -> 1468.02 | L12: =IF(ISNUMBER(H12),H12*$F12,"—") -> 1533.83 | M12: =IF(ISNUMBER(I12),I12*$F12,"—") -> — | N12: =IF(ISNUMBER(J12),J12*$F12,"—") -> 1707 | O12: =IF($S12=0,"—",MIN(G12:J12)) -> 1468.02 | P12: =IF($S12=0,"—",IF(COUNTIF(G12:J12,O12)>1,"Tie",INDEX($G$6:$J$6,MATCH(O12,G12:J12,0)))) -> Ferguson | Q12: =IF($S12>=2,MAX(G12:J12)/MIN(G12:J12)-1,"—") -> 0.1627907 | R12: =IF($S12>=2,(MAX(G12:J12)-MIN(G12:J12))*$F12,"—") -> 238.98 | S12: =COUNT(G12:J12) -> 3 | T12: =IF($S12<=1,IF($S12=1,"Single quote","—"),"Like-for-like") -> Like-for-like | U12: =IF(COUNT(W12:Z12)<2,"",IF(MAX(W12:Z12)=MIN(W12:Z12),"OK","Qty differs")) -> OK | W12: =IF(COUNTIFS('Quote Lines'!$P$3:$P$805,$A12&"|"&G$6&"|1",'Quote Lines'!$M$3:$M$805,"Y")=0,"",SUMIFS('Quote Lines'!$L$3:$L$805,'Quote Lines'!$P$3:$P$805,$A12&"|"&G$6&"|1",'Quote Lines'!$M$3:$M$805,"Y")) -> 1 | X12: =IF(COUNTIFS('Quote Lines'!$P$3:$P$805,$A12&"|"&H$6&"|1",'Quote Lines'!$M$3:$M$805,"Y")=0,"",SUMIFS('Quote Lines'!$L$3:$L$805,'Quote Lines'!$P$3:$P$805,$A12&"|"&H$6&"|1",'Quote Lines'!$M$3:$M$805,"Y")) -> 1 | Z12: =IF(COUNTIFS('Quote Lines'!$P$3:$P$805,$A12&"|"&J$6&"|1",'Quote Lines'!$M$3:$M$805,"Y")=0,"",SUMIFS('Quote Lines'!$L$3:$L$805,'Quote Lines'!$P$3:$P$805,$A12&"|"&J$6&"|1",'Quote Lines'!$M$3:$M$805,"Y")) -> 1 | AA12: =IF(ISNUMBER(G12),1+SUMPRODUCT(ISNUMBER($G12:$J12)*($G12:$J12<G12)),"") -> 1 | AB12: =IF(ISNUMBER(H12),1+SUMPRODUCT(ISNUMBER($G12:$J12)*($G12:$J12<H12)),"") -> 2 | AC12: =IF(ISNUMBER(I12),1+SUMPRODUCT(ISNUMBER($G12:$J12)*($G12:$J12<I12)),"") | AD12: =IF(ISNUMBER(J12),1+SUMPRODUCT(ISNUMBER($G12:$J12)*($G12:$J12<J12)),"") -> 3 | AE12: =IF(NOT(ISNUMBER(G12)),0,IF($S12<2,5,IF(AA12=1,1,IF(G12=MAX($G12:$J12),4,IF(AA12=2,2,3))))) -> 1 | AF12: =IF(NOT(ISNUMBER(H12)),0,IF($S12<2,5,IF(AB12=1,1,IF(H12=MAX($G12:$J12),4,IF(AB12=2,2,3))))) -> 2 | AG12: =IF(NOT(ISNUMBER(I12)),0,IF($S12<2,5,IF(AC12=1,1,IF(I12=MAX($G12:$J12),4,IF(AC12=2,2,3))))) -> 0 | AH12: =IF(NOT(ISNUMBER(J12)),0,IF($S12<2,5,IF(AD12=1,1,IF(J12=MAX($G12:$J12),4,IF(AD12=2,2,3))))) -> 4 | AI12: =IF($S12>=2,IF(ISNUMBER(G12),G12*$F12,MIN($G12:$J12)*$F12),0) -> 1468.02 | AJ12: =IF($S12>=2,IF(ISNUMBER(H12),H12*$F12,MIN($G12:$J12)*$F12),0) -> 1533.83 | AK12: =IF($S12>=2,IF(ISNUMBER(I12),I12*$F12,MIN($G12:$J12)*$F12),0) -> 1468.02 | AL12: =IF($S12>=2,IF(ISNUMBER(J12),J12*$F12,MIN($G12:$J12)*$F12),0) -> 1707 | AM12: =IF($S12>=2,$R12+ROW()/1000000,"") -> 238.98001 | AN12: =IF($S12>=2,MAX(G12:J12),"") -> 1707 | AO12: =IF($S12>=2,INDEX($G$6:$J$6,MATCH(MAX(G12:J12),G12:J12,0)),"") -> Scholzen | AP12: =IF($S12>=2,MIN(G12:J12)*$F12,0) -> 1468.02 | AQ12: =IF($S12>=2,INDEX($G$6:$J$6,MATCH(MIN(G12:J12),G12:J12,0)),"") -> Ferguson
A13: R006 | B13: Item 5 | C13: DI fittings | D13: 10" flanged tee | E13: EA | F13: 2 | G13: =IF(COUNTIF('Quote Lines'!$P$3:$P$805,$A13&"|"&G$6&"|1")=0,"—",SUMIFS('Quote Lines'!$O$3:$O$805,'Quote Lines'!$P$3:$P$805,$A13&"|"&G$6&"|1")/SUMIFS('Quote Lines'!$L$3:$L$805,'Quote Lines'!$P$3:$P$805,$A13&"|"&G$6&"|1")) -> 1012 | H13: =IF(COUNTIF('Quote Lines'!$P$3:$P$805,$A13&"|"&H$6&"|1")=0,"—",SUMIFS('Quote Lines'!$O$3:$O$805,'Quote Lines'!$P$3:$P$805,$A13&"|"&H$6&"|1")/SUMIFS('Quote Lines'!$L$3:$L$805,'Quote Lines'!$P$3:$P$805,$A13&"|"&H$6&"|1")) -> 1057.37 | I13: =IF(COUNTIF('Quote Lines'!$P$3:$P$805,$A13&"|"&I$6&"|1")=0,"—",SUMIFS('Quote Lines'!$O$3:$O$805,'Quote Lines'!$P$3:$P$805,$A13&"|"&I$6&"|1")/SUMIFS('Quote Lines'!$L$3:$L$805,'Quote Lines'!$P$3:$P$805,$A13&"|"&I$6&"|1")) -> 1148.05 | J13: =IF(COUNTIF('Quote Lines'!$P$3:$P$805,$A13&"|"&J$6&"|1")=0,"—",SUMIFS('Quote Lines'!$O$3:$O$805,'Quote Lines'!$P$3:$P$805,$A13&"|"&J$6&"|1")/SUMIFS('Quote Lines'!$L$3:$L$805,'Quote Lines'!$P$3:$P$805,$A13&"|"&J$6&"|1")) -> 1176.75 | K13: =IF(ISNUMBER(G13),G13*$F13,"—") -> 2024 | L13: =IF(ISNUMBER(H13),H13*$F13,"—") -> 2114.74 | M13: =IF(ISNUMBER(I13),I13*$F13,"—") -> 2296.1 | N13: =IF(ISNUMBER(J13),J13*$F13,"—") -> 2353.5 | O13: =IF($S13=0,"—",MIN(G13:J13)) -> 1012 | P13: =IF($S13=0,"—",IF(COUNTIF(G13:J13,O13)>1,"Tie",INDEX($G$6:$J$6,MATCH(O13,G13:J13,0)))) -> Ferguson | Q13: =IF($S13>=2,MAX(G13:J13)/MIN(G13:J13)-1,"—") -> 0.16279644 | R13: =IF($S13>=2,(MAX(G13:J13)-MIN(G13:J13))*$F13,"—") -> 329.5 | S13: =COUNT(G13:J13) -> 4 | T13: =IF($S13<=1,IF($S13=1,"Single quote","—"),"Like-for-like") -> Like-for-like | U13: =IF(COUNT(W13:Z13)<2,"",IF(MAX(W13:Z13)=MIN(W13:Z13),"OK","Qty differs")) -> OK | W13: =IF(COUNTIFS('Quote Lines'!$P$3:$P$805,$A13&"|"&G$6&"|1",'Quote Lines'!$M$3:$M$805,"Y")=0,"",SUMIFS('Quote Lines'!$L$3:$L$805,'Quote Lines'!$P$3:$P$805,$A13&"|"&G$6&"|1",'Quote Lines'!$M$3:$M$805,"Y")) -> 2 | X13: =IF(COUNTIFS('Quote Lines'!$P$3:$P$805,$A13&"|"&H$6&"|1",'Quote Lines'!$M$3:$M$805,"Y")=0,"",SUMIFS('Quote Lines'!$L$3:$L$805,'Quote Lines'!$P$3:$P$805,$A13&"|"&H$6&"|1",'Quote Lines'!$M$3:$M$805,"Y")) -> 2 | Y13: =IF(COUNTIFS('Quote Lines'!$P$3:$P$805,$A13&"|"&I$6&"|1",'Quote Lines'!$M$3:$M$805,"Y")=0,"",SUMIFS('Quote Lines'!$L$3:$L$805,'Quote Lines'!$P$3:$P$805,$A13&"|"&I$6&"|1",'Quote Lines'!$M$3:$M$805,"Y")) -> 2 | Z13: =IF(COUNTIFS('Quote Lines'!$P$3:$P$805,$A13&"|"&J$6&"|1",'Quote Lines'!$M$3:$M$805,"Y")=0,"",SUMIFS('Quote Lines'!$L$3:$L$805,'Quote Lines'!$P$3:$P$805,$A13&"|"&J$6&"|1",'Quote Lines'!$M$3:$M$805,"Y")) -> 2 | AA13: =IF(ISNUMBER(G13),1+SUMPRODUCT(ISNUMBER($G13:$J13)*($G13:$J13<G13)),"") -> 1 | AB13: =IF(ISNUMBER(H13),1+SUMPRODUCT(ISNUMBER($G13:$J13)*($G13:$J13<H13)),"") -> 2 | AC13: =IF(ISNUMBER(I13),1+SUMPRODUCT(ISNUMBER($G13:$J13)*($G13:$J13<I13)),"") -> 3 | AD13: =IF(ISNUMBER(J13),1+SUMPRODUCT(ISNUMBER($G13:$J13)*($G13:$J13<J13)),"") -> 4 | AE13: =IF(NOT(ISNUMBER(G13)),0,IF($S13<2,5,IF(AA13=1,1,IF(G13=MAX($G13:$J13),4,IF(AA13=2,2,3))))) -> 1 | AF13: =IF(NOT(ISNUMBER(H13)),0,IF($S13<2,5,IF(AB13=1,1,IF(H13=MAX($G13:$J13),4,IF(AB13=2,2,3))))) -> 2 | AG13: =IF(NOT(ISNUMBER(I13)),0,IF($S13<2,5,IF(AC13=1,1,IF(I13=MAX($G13:$J13),4,IF(AC13=2,2,3))))) -> 3 | AH13: =IF(NOT(ISNUMBER(J13)),0,IF($S13<2,5,IF(AD13=1,1,IF(J13=MAX($G13:$J13),4,IF(AD13=2,2,3))))) -> 4 | AI13: =IF($S13>=2,IF(ISNUMBER(G13),G13*$F13,MIN($G13:$J13)*$F13),0) -> 2024 | AJ13: =IF($S13>=2,IF(ISNUMBER(H13),H13*$F13,MIN($G13:$J13)*$F13),0) -> 2114.74 | AK13: =IF($S13>=2,IF(ISNUMBER(I13),I13*$F13,MIN($G13:$J13)*$F13),0) -> 2296.1 | AL13: =IF($S13>=2,IF(ISNUMBER(J13),J13*$F13,MIN($G13:$J13)*$F13),0) -> 2353.5 | AM13: =IF($S13>=2,$R13+ROW()/1000000,"") -> 329.50001 | AN13: =IF($S13>=2,MAX(G13:J13),"") -> 1176.75 | AO13: =IF($S13>=2,INDEX($G$6:$J$6,MATCH(MAX(G13:J13),G13:J13,0)),"") -> Scholzen | AP13: =IF($S13>=2,MIN(G13:J13)*$F13,0) -> 2024 | AQ13: =IF($S13>=2,INDEX($G$6:$J$6,MATCH(MIN(G13:J13),G13:J13,0)),"") -> Ferguson
A14: R007 | B14: Item 5 | C14: DI fittings | D14: 10" x 8" flanged tee | E14: EA | F14: 2 | G14: =IF(COUNTIF('Quote Lines'!$P$3:$P$805,$A14&"|"&G$6&"|1")=0,"—",SUMIFS('Quote Lines'!$O$3:$O$805,'Quote Lines'!$P$3:$P$805,$A14&"|"&G$6&"|1")/SUMIFS('Quote Lines'!$L$3:$L$805,'Quote Lines'!$P$3:$P$805,$A14&"|"&G$6&"|1")) -> 870.11 | H14: =IF(COUNTIF('Quote Lines'!$P$3:$P$805,$A14&"|"&H$6&"|1")=0,"—",SUMIFS('Quote Lines'!$O$3:$O$805,'Quote Lines'!$P$3:$P$805,$A14&"|"&H$6&"|1")/SUMIFS('Quote Lines'!$L$3:$L$805,'Quote Lines'!$P$3:$P$805,$A14&"|"&H$6&"|1")) -> 909.11 | I14: =IF(COUNTIF('Quote Lines'!$P$3:$P$805,$A14&"|"&I$6&"|1")=0,"—",SUMIFS('Quote Lines'!$O$3:$O$805,'Quote Lines'!$P$3:$P$805,$A14&"|"&I$6&"|1")/SUMIFS('Quote Lines'!$L$3:$L$805,'Quote Lines'!$P$3:$P$805,$A14&"|"&I$6&"|1")) -> 987.075 | J14: =IF(COUNTIF('Quote Lines'!$P$3:$P$805,$A14&"|"&J$6&"|1")=0,"—",SUMIFS('Quote Lines'!$O$3:$O$805,'Quote Lines'!$P$3:$P$805,$A14&"|"&J$6&"|1")/SUMIFS('Quote Lines'!$L$3:$L$805,'Quote Lines'!$P$3:$P$805,$A14&"|"&J$6&"|1")) -> 1011.75 | K14: =IF(ISNUMBER(G14),G14*$F14,"—") -> 1740.22 | L14: =IF(ISNUMBER(H14),H14*$F14,"—") -> 1818.22 | M14: =IF(ISNUMBER(I14),I14*$F14,"—") -> 1974.15 | N14: =IF(ISNUMBER(J14),J14*$F14,"—") -> 2023.5 | O14: =IF($S14=0,"—",MIN(G14:J14)) -> 870.11 | P14: =IF($S14=0,"—",IF(COUNTIF(G14:J14,O14)>1,"Tie",INDEX($G$6:$J$6,MATCH(O14,G14:J14,0)))) -> Ferguson | Q14: =IF($S14>=2,MAX(G14:J14)/MIN(G14:J14)-1,"—") -> 0.16278402 | R14: =IF($S14>=2,(MAX(G14:J14)-MIN(G14:J14))*$F14,"—") -> 283.28 | S14: =COUNT(G14:J14) -> 4 | T14: =IF($S14<=1,IF($S14=1,"Single quote","—"),"Like-for-like") -> Like-for-like | U14: =IF(COUNT(W14:Z14)<2,"",IF(MAX(W14:Z14)=MIN(W14:Z14),"OK","Qty differs")) -> OK | W14: =IF(COUNTIFS('Quote Lines'!$P$3:$P$805,$A14&"|"&G$6&"|1",'Quote Lines'!$M$3:$M$805,"Y")=0,"",SUMIFS('Quote Lines'!$L$3:$L$805,'Quote Lines'!$P$3:$P$805,$A14&"|"&G$6&"|1",'Quote Lines'!$M$3:$M$805,"Y")) -> 2 | X14: =IF(COUNTIFS('Quote Lines'!$P$3:$P$805,$A14&"|"&H$6&"|1",'Quote Lines'!$M$3:$M$805,"Y")=0,"",SUMIFS('Quote Lines'!$L$3:$L$805,'Quote Lines'!$P$3:$P$805,$A14&"|"&H$6&"|1",'Quote Lines'!$M$3:$M$805,"Y")) -> 2 | Y14: =IF(COUNTIFS('Quote Lines'!$P$3:$P$805,$A14&"|"&I$6&"|1",'Quote Lines'!$M$3:$M$805,"Y")=0,"",SUMIFS('Quote Lines'!$L$3:$L$805,'Quote Lines'!$P$3:$P$805,$A14&"|"&I$6&"|1",'Quote Lines'!$M$3:$M$805,"Y")) -> 2 | Z14: =IF(COUNTIFS('Quote Lines'!$P$3:$P$805,$A14&"|"&J$6&"|1",'Quote Lines'!$M$3:$M$805,"Y")=0,"",SUMIFS('Quote Lines'!$L$3:$L$805,'Quote Lines'!$P$3:$P$805,$A14&"|"&J$6&"|1",'Quote Lines'!$M$3:$M$805,"Y")) -> 2 | AA14: =IF(ISNUMBER(G14),1+SUMPRODUCT(ISNUMBER($G14:$J14)*($G14:$J14<G14)),"") -> 1 | AB14: =IF(ISNUMBER(H14),1+SUMPRODUCT(ISNUMBER($G14:$J14)*($G14:$J14<H14)),"") -> 2 | AC14: =IF(ISNUMBER(I14),1+SUMPRODUCT(ISNUMBER($G14:$J14)*($G14:$J14<I14)),"") -> 3 | AD14: =IF(ISNUMBER(J14),1+SUMPRODUCT(ISNUMBER($G14:$J14)*($G14:$J14<J14)),"") -> 4 | AE14: =IF(NOT(ISNUMBER(G14)),0,IF($S14<2,5,IF(AA14=1,1,IF(G14=MAX($G14:$J14),4,IF(AA14=2,2,3))))) -> 1 | AF14: =IF(NOT(ISNUMBER(H14)),0,IF($S14<2,5,IF(AB14=1,1,IF(H14=MAX($G14:$J14),4,IF(AB14=2,2,3))))) -> 2 | AG14: =IF(NOT(ISNUMBER(I14)),0,IF($S14<2,5,IF(AC14=1,1,IF(I14=MAX($G14:$J14),4,IF(AC14=2,2,3))))) -> 3 | AH14: =IF(NOT(ISNUMBER(J14)),0,IF($S14<2,5,IF(AD14=1,1,IF(J14=MAX($G14:$J14),4,IF(AD14=2,2,3))))) -> 4 | AI14: =IF($S14>=2,IF(ISNUMBER(G14),G14*$F14,MIN($G14:$J14)*$F14),0) -> 1740.22 | AJ14: =IF($S14>=2,IF(ISNUMBER(H14),H14*$F14,MIN($G14:$J14)*$F14),0) -> 1818.22 | AK14: =IF($S14>=2,IF(ISNUMBER(I14),I14*$F14,MIN($G14:$J14)*$F14),0) -> 1974.15 | AL14: =IF($S14>=2,IF(ISNUMBER(J14),J14*$F14,MIN($G14:$J14)*$F14),0) -> 2023.5 | AM14: =IF($S14>=2,$R14+ROW()/1000000,"") -> 283.28001 | AN14: =IF($S14>=2,MAX(G14:J14),"") -> 1011.75 | AO14: =IF($S14>=2,INDEX($G$6:$J$6,MATCH(MAX(G14:J14),G14:J14,0)),"") -> Scholzen | AP14: =IF($S14>=2,MIN(G14:J14)*$F14,0) -> 1740.22 | AQ14: =IF($S14>=2,INDEX($G$6:$J$6,MATCH(MIN(G14:J14),G14:J14,0)),"") -> Ferguson
A15: R008 | B15: Item 5 | C15: DI fittings | D15: 8" flanged 90° elbow | E15: EA | F15: 2 | G15: =IF(COUNTIF('Quote Lines'!$P$3:$P$805,$A15&"|"&G$6&"|1")=0,"—",SUMIFS('Quote Lines'!$O$3:$O$805,'Quote Lines'!$P$3:$P$805,$A15&"|"&G$6&"|1")/SUMIFS('Quote Lines'!$L$3:$L$805,'Quote Lines'!$P$3:$P$805,$A15&"|"&G$6&"|1")) -> 446.99 | H15: =IF(COUNTIF('Quote Lines'!$P$3:$P$805,$A15&"|"&H$6&"|1")=0,"—",SUMIFS('Quote Lines'!$O$3:$O$805,'Quote Lines'!$P$3:$P$805,$A15&"|"&H$6&"|1")/SUMIFS('Quote Lines'!$L$3:$L$805,'Quote Lines'!$P$3:$P$805,$A15&"|"&H$6&"|1")) -> 467.02 | I15: =IF(COUNTIF('Quote Lines'!$P$3:$P$805,$A15&"|"&I$6&"|1")=0,"—",SUMIFS('Quote Lines'!$O$3:$O$805,'Quote Lines'!$P$3:$P$805,$A15&"|"&I$6&"|1")/SUMIFS('Quote Lines'!$L$3:$L$805,'Quote Lines'!$P$3:$P$805,$A15&"|"&I$6&"|1")) -> 507.075 | J15: =IF(COUNTIF('Quote Lines'!$P$3:$P$805,$A15&"|"&J$6&"|1")=0,"—",SUMIFS('Quote Lines'!$O$3:$O$805,'Quote Lines'!$P$3:$P$805,$A15&"|"&J$6&"|1")/SUMIFS('Quote Lines'!$L$3:$L$805,'Quote Lines'!$P$3:$P$805,$A15&"|"&J$6&"|1")) -> 519.75 | K15: =IF(ISNUMBER(G15),G15*$F15,"—") -> 893.98 | L15: =IF(ISNUMBER(H15),H15*$F15,"—") -> 934.04 | M15: =IF(ISNUMBER(I15),I15*$F15,"—") -> 1014.15 | N15: =IF(ISNUMBER(J15),J15*$F15,"—") -> 1039.5 | O15: =IF($S15=0,"—",MIN(G15:J15)) -> 446.99 | P15: =IF($S15=0,"—",IF(COUNTIF(G15:J15,O15)>1,"Tie",INDEX($G$6:$J$6,MATCH(O15,G15:J15,0)))) -> Ferguson | Q15: =IF($S15>=2,MAX(G15:J15)/MIN(G15:J15)-1,"—") -> 0.16277769 | R15: =IF($S15>=2,(MAX(G15:J15)-MIN(G15:J15))*$F15,"—") -> 145.52 | S15: =COUNT(G15:J15) -> 4 | T15: =IF($S15<=1,IF($S15=1,"Single quote","—"),"Like-for-like") -> Like-for-like | U15: =IF(COUNT(W15:Z15)<2,"",IF(MAX(W15:Z15)=MIN(W15:Z15),"OK","Qty differs")) -> OK | W15: =IF(COUNTIFS('Quote Lines'!$P$3:$P$805,$A15&"|"&G$6&"|1",'Quote Lines'!$M$3:$M$805,"Y")=0,"",SUMIFS('Quote Lines'!$L$3:$L$805,'Quote Lines'!$P$3:$P$805,$A15&"|"&G$6&"|1",'Quote Lines'!$M$3:$M$805,"Y")) -> 2 | X15: =IF(COUNTIFS('Quote Lines'!$P$3:$P$805,$A15&"|"&H$6&"|1",'Quote Lines'!$M$3:$M$805,"Y")=0,"",SUMIFS('Quote Lines'!$L$3:$L$805,'Quote Lines'!$P$3:$P$805,$A15&"|"&H$6&"|1",'Quote Lines'!$M$3:$M$805,"Y")) -> 2 | Y15: =IF(COUNTIFS('Quote Lines'!$P$3:$P$805,$A15&"|"&I$6&"|1",'Quote Lines'!$M$3:$M$805,"Y")=0,"",SUMIFS('Quote Lines'!$L$3:$L$805,'Quote Lines'!$P$3:$P$805,$A15&"|"&I$6&"|1",'Quote Lines'!$M$3:$M$805,"Y")) -> 2 | Z15: =IF(COUNTIFS('Quote Lines'!$P$3:$P$805,$A15&"|"&J$6&"|1",'Quote Lines'!$M$3:$M$805,"Y")=0,"",SUMIFS('Quote Lines'!$L$3:$L$805,'Quote Lines'!$P$3:$P$805,$A15&"|"&J$6&"|1",'Quote Lines'!$M$3:$M$805,"Y")) -> 2 | AA15: =IF(ISNUMBER(G15),1+SUMPRODUCT(ISNUMBER($G15:$J15)*($G15:$J15<G15)),"") -> 1 | AB15: =IF(ISNUMBER(H15),1+SUMPRODUCT(ISNUMBER($G15:$J15)*($G15:$J15<H15)),"") -> 2 | AC15: =IF(ISNUMBER(I15),1+SUMPRODUCT(ISNUMBER($G15:$J15)*($G15:$J15<I15)),"") -> 3 | AD15: =IF(ISNUMBER(J15),1+SUMPRODUCT(ISNUMBER($G15:$J15)*($G15:$J15<J15)),"") -> 4 | AE15: =IF(NOT(ISNUMBER(G15)),0,IF($S15<2,5,IF(AA15=1,1,IF(G15=MAX($G15:$J15),4,IF(AA15=2,2,3))))) -> 1 | AF15: =IF(NOT(ISNUMBER(H15)),0,IF($S15<2,5,IF(AB15=1,1,IF(H15=MAX($G15:$J15),4,IF(AB15=2,2,3))))) -> 2 | AG15: =IF(NOT(ISNUMBER(I15)),0,IF($S15<2,5,IF(AC15=1,1,IF(I15=MAX($G15:$J15),4,IF(AC15=2,2,3))))) -> 3 | AH15: =IF(NOT(ISNUMBER(J15)),0,IF($S15<2,5,IF(AD15=1,1,IF(J15=MAX($G15:$J15),4,IF(AD15=2,2,3))))) -> 4 | AI15: =IF($S15>=2,IF(ISNUMBER(G15),G15*$F15,MIN($G15:$J15)*$F15),0) -> 893.98 | AJ15: =IF($S15>=2,IF(ISNUMBER(H15),H15*$F15,MIN($G15:$J15)*$F15),0) -> 934.04 | AK15: =IF($S15>=2,IF(ISNUMBER(I15),I15*$F15,MIN($G15:$J15)*$F15),0) -> 1014.15 | AL15: =IF($S15>=2,IF(ISNUMBER(J15),J15*$F15,MIN($G15:$J15)*$F15),0) -> 1039.5 | AM15: =IF($S15>=2,$R15+ROW()/1000000,"") -> 145.52002 | AN15: =IF($S15>=2,MAX(G15:J15),"") -> 519.75 | AO15: =IF($S15>=2,INDEX($G$6:$J$6,MATCH(MAX(G15:J15),G15:J15,0)),"") -> Scholzen | AP15: =IF($S15>=2,MIN(G15:J15)*$F15,0) -> 893.98 | AQ15: =IF($S15>=2,INDEX($G$6:$J$6,MATCH(MIN(G15:J15),G15:J15,0)),"") -> Ferguson
A16: R009 | B16: Item 5 | C16: DI fittings | D16: 12" MJ x flange 45° bend | E16: EA | F16: 1 | G16: =IF(COUNTIF('Quote Lines'!$P$3:$P$805,$A16&"|"&G$6&"|1")=0,"—",SUMIFS('Quote Lines'!$O$3:$O$805,'Quote Lines'!$P$3:$P$805,$A16&"|"&G$6&"|1")/SUMIFS('Quote Lines'!$L$3:$L$805,'Quote Lines'!$P$3:$P$805,$A16&"|"&G$6&"|1")) -> 728.21 | H16: — | I16: — | J16: — | K16: =IF(ISNUMBER(G16),G16*$F16,"—") -> 728.21 | L16: =IF(ISNUMBER(H16),H16*$F16,"—") -> — | M16: =IF(ISNUMBER(I16),I16*$F16,"—") -> — | N16: =IF(ISNUMBER(J16),J16*$F16,"—") -> — | O16: =IF($S16=0,"—",MIN(G16:J16)) -> 728.21 | P16: =IF($S16=0,"—",IF(COUNTIF(G16:J16,O16)>1,"Tie",INDEX($G$6:$J$6,MATCH(O16,G16:J16,0)))) -> Ferguson | Q16: =IF($S16>=2,MAX(G16:J16)/MIN(G16:J16)-1,"—") -> — | R16: =IF($S16>=2,(MAX(G16:J16)-MIN(G16:J16))*$F16,"—") -> — | S16: =COUNT(G16:J16) -> 1 | T16: =IF($S16<=1,IF($S16=1,"Single quote","—"),"Like-for-like") -> Single quote | U16: =IF(COUNT(W16:Z16)<2,"",IF(MAX(W16:Z16)=MIN(W16:Z16),"OK","Qty differs")) | V16: Only Ferguson priced the MJ x flange end configuration. | W16: =IF(COUNTIFS('Quote Lines'!$P$3:$P$805,$A16&"|"&G$6&"|1",'Quote Lines'!$M$3:$M$805,"Y")=0,"",SUMIFS('Quote Lines'!$L$3:$L$805,'Quote Lines'!$P$3:$P$805,$A16&"|"&G$6&"|1",'Quote Lines'!$M$3:$M$805,"Y")) -> 1 | AA16: =IF(ISNUMBER(G16),1+SUMPRODUCT(ISNUMBER($G16:$J16)*($G16:$J16<G16)),"") -> 1 | AB16: =IF(ISNUMBER(H16),1+SUMPRODUCT(ISNUMBER($G16:$J16)*($G16:$J16<H16)),"") | AC16: =IF(ISNUMBER(I16),1+SUMPRODUCT(ISNUMBER($G16:$J16)*($G16:$J16<I16)),"") | AD16: =IF(ISNUMBER(J16),1+SUMPRODUCT(ISNUMBER($G16:$J16)*($G16:$J16<J16)),"") | AE16: =IF(NOT(ISNUMBER(G16)),0,IF($S16<2,5,IF(AA16=1,1,IF(G16=MAX($G16:$J16),4,IF(AA16=2,2,3))))) -> 5 | AF16: =IF(NOT(ISNUMBER(H16)),0,IF($S16<2,5,IF(AB16=1,1,IF(H16=MAX($G16:$J16),4,IF(AB16=2,2,3))))) -> 0 | AG16: =IF(NOT(ISNUMBER(I16)),0,IF($S16<2,5,IF(AC16=1,1,IF(I16=MAX($G16:$J16),4,IF(AC16=2,2,3))))) -> 0 | AH16: =IF(NOT(ISNUMBER(J16)),0,IF($S16<2,5,IF(AD16=1,1,IF(J16=MAX($G16:$J16),4,IF(AD16=2,2,3))))) -> 0 | AI16: =IF($S16>=2,IF(ISNUMBER(G16),G16*$F16,MIN($G16:$J16)*$F16),0) -> 0 | AJ16: =IF($S16>=2,IF(ISNUMBER(H16),H16*$F16,MIN($G16:$J16)*$F16),0) -> 0 | AK16: =IF($S16>=2,IF(ISNUMBER(I16),I16*$F16,MIN($G16:$J16)*$F16),0) -> 0 | AL16: =IF($S16>=2,IF(ISNUMBER(J16),J16*$F16,MIN($G16:$J16)*$F16),0) -> 0 | AM16: =IF($S16>=2,$R16+ROW()/1000000,"") | AN16: =IF($S16>=2,MAX(G16:J16),"") | AO16: =IF($S16>=2,INDEX($G$6:$J$6,MATCH(MAX(G16:J16),G16:J16,0)),"") | AP16: =IF($S16>=2,MIN(G16:J16)*$F16,0) -> 0 | AQ16: =IF($S16>=2,INDEX($G$6:$J$6,MATCH(MIN(G16:J16),G16:J16,0)),"")
A17: R010 | B17: Item 5 | C17: DI fittings | D17: 12" MJ x flange 22-1/2° bend | E17: EA | F17: 1 | G17: =IF(COUNTIF('Quote Lines'!$P$3:$P$805,$A17&"|"&G$6&"|1")=0,"—",SUMIFS('Quote Lines'!$O$3:$O$805,'Quote Lines'!$P$3:$P$805,$A17&"|"&G$6&"|1")/SUMIFS('Quote Lines'!$L$3:$L$805,'Quote Lines'!$P$3:$P$805,$A17&"|"&G$6&"|1")) -> 636.61 | H17: =IF(COUNTIF('Quote Lines'!$P$3:$P$805,$A17&"|"&H$6&"|1")=0,"—",SUMIFS('Quote Lines'!$O$3:$O$805,'Quote Lines'!$P$3:$P$805,$A17&"|"&H$6&"|1")/SUMIFS('Quote Lines'!$L$3:$L$805,'Quote Lines'!$P$3:$P$805,$A17&"|"&H$6&"|1")) -> 665.15 | I17: — | J17: — | K17: =IF(ISNUMBER(G17),G17*$F17,"—") -> 636.61 | L17: =IF(ISNUMBER(H17),H17*$F17,"—") -> 665.15 | M17: =IF(ISNUMBER(I17),I17*$F17,"—") -> — | N17: =IF(ISNUMBER(J17),J17*$F17,"—") -> — | O17: =IF($S17=0,"—",MIN(G17:J17)) -> 636.61 | P17: =IF($S17=0,"—",IF(COUNTIF(G17:J17,O17)>1,"Tie",INDEX($G$6:$J$6,MATCH(O17,G17:J17,0)))) -> Ferguson | Q17: =IF($S17>=2,MAX(G17:J17)/MIN(G17:J17)-1,"—") -> 0.044831215 | R17: =IF($S17>=2,(MAX(G17:J17)-MIN(G17:J17))*$F17,"—") -> 28.54 | S17: =COUNT(G17:J17) -> 2 | T17: =IF($S17<=1,IF($S17=1,"Single quote","—"),"Like-for-like") -> Like-for-like | U17: =IF(COUNT(W17:Z17)<2,"",IF(MAX(W17:Z17)=MIN(W17:Z17),"OK","Qty differs")) -> OK | W17: =IF(COUNTIFS('Quote Lines'!$P$3:$P$805,$A17&"|"&G$6&"|1",'Quote Lines'!$M$3:$M$805,"Y")=0,"",SUMIFS('Quote Lines'!$L$3:$L$805,'Quote Lines'!$P$3:$P$805,$A17&"|"&G$6&"|1",'Quote Lines'!$M$3:$M$805,"Y")) -> 1 | X17: =IF(COUNTIFS('Quote Lines'!$P$3:$P$805,$A17&"|"&H$6&"|1",'Quote Lines'!$M$3:$M$805,"Y")=0,"",SUMIFS('Quote Lines'!$L$3:$L$805,'Quote Lines'!$P$3:$P$805,$A17&"|"&H$6&"|1",'Quote Lines'!$M$3:$M$805,"Y")) -> 1 | AA17: =IF(ISNUMBER(G17),1+SUMPRODUCT(ISNUMBER($G17:$J17)*($G17:$J17<G17)),"") -> 1 | AB17: =IF(ISNUMBER(H17),1+SUMPRODUCT(ISNUMBER($G17:$J17)*($G17:$J17<H17)),"") -> 2 | AC17: =IF(ISNUMBER(I17),1+SUMPRODUCT(ISNUMBER($G17:$J17)*($G17:$J17<I17)),"") | AD17: =IF(ISNUMBER(J17),1+SUMPRODUCT(ISNUMBER($G17:$J17)*($G17:$J17<J17)),"") | AE17: =IF(NOT(ISNUMBER(G17)),0,IF($S17<2,5,IF(AA17=1,1,IF(G17=MAX($G17:$J17),4,IF(AA17=2,2,3))))) -> 1 | AF17: =IF(NOT(ISNUMBER(H17)),0,IF($S17<2,5,IF(AB17=1,1,IF(H17=MAX($G17:$J17),4,IF(AB17=2,2,3))))) -> 4 | AG17: =IF(NOT(ISNUMBER(I17)),0,IF($S17<2,5,IF(AC17=1,1,IF(I17=MAX($G17:$J17),4,IF(AC17=2,2,3))))) -> 0 | AH17: =IF(NOT(ISNUMBER(J17)),0,IF($S17<2,5,IF(AD17=1,1,IF(J17=MAX($G17:$J17),4,IF(AD17=2,2,3))))) -> 0 | AI17: =IF($S17>=2,IF(ISNUMBER(G17),G17*$F17,MIN($G17:$J17)*$F17),0) -> 636.61 | AJ17: =IF($S17>=2,IF(ISNUMBER(H17),H17*$F17,MIN($G17:$J17)*$F17),0) -> 665.15 | AK17: =IF($S17>=2,IF(ISNUMBER(I17),I17*$F17,MIN($G17:$J17)*$F17),0) -> 636.61 | AL17: =IF($S17>=2,IF(ISNUMBER(J17),J17*$F17,MIN($G17:$J17)*$F17),0) -> 636.61 | AM17: =IF($S17>=2,$R17+ROW()/1000000,"") -> 28.540017 | AN17: =IF($S17>=2,MAX(G17:J17),"") -> 665.15 | AO17: =IF($S17>=2,INDEX($G$6:$J$6,MATCH(MAX(G17:J17),G17:J17,0)),"") -> HD Fowler | AP17: =IF($S17>=2,MIN(G17:J17)*$F17,0) -> 636.61 | AQ17: =IF($S17>=2,INDEX($G$6:$J$6,MATCH(MIN(G17:J17),G17:J17,0)),"") -> Ferguson
A18: R011 | B18: Item 5 | C18: DI fittings | D18: 12" MJ 45° bend (MJ x MJ) | E18: EA | F18: 1 | G18: — | H18: =IF(COUNTIF('Quote Lines'!$P$3:$P$805,$A18&"|"&H$6&"|1")=0,"—",SUMIFS('Quote Lines'!$O$3:$O$805,'Quote Lines'!$P$3:$P$805,$A18&"|"&H$6&"|1")/SUMIFS('Quote Lines'!$L$3:$L$805,'Quote Lines'!$P$3:$P$805,$A18&"|"&H$6&"|1")) -> 418.5 | I18: — | J18: =IF(COUNTIF('Quote Lines'!$P$3:$P$805,$A18&"|"&J$6&"|1")=0,"—",SUMIFS('Quote Lines'!$O$3:$O$805,'Quote Lines'!$P$3:$P$805,$A18&"|"&J$6&"|1")/SUMIFS('Quote Lines'!$L$3:$L$805,'Quote Lines'!$P$3:$P$805,$A18&"|"&J$6&"|1")) -> 465.75 | K18: =IF(ISNUMBER(G18),G18*$F18,"—") -> — | L18: =IF(ISNUMBER(H18),H18*$F18,"—") -> 418.5 | M18: =IF(ISNUMBER(I18),I18*$F18,"—") -> — | N18: =IF(ISNUMBER(J18),J18*$F18,"—") -> 465.75 | O18: =IF($S18=0,"—",MIN(G18:J18)) -> 418.5 | P18: =IF($S18=0,"—",IF(COUNTIF(G18:J18,O18)>1,"Tie",INDEX($G$6:$J$6,MATCH(O18,G18:J18,0)))) -> HD Fowler | Q18: =IF($S18>=2,MAX(G18:J18)/MIN(G18:J18)-1,"—") -> 0.11290323 | R18: =IF($S18>=2,(MAX(G18:J18)-MIN(G18:J18))*$F18,"—") -> 47.25 | S18: =COUNT(G18:J18) -> 2 | T18: =IF($S18<=1,IF($S18=1,"Single quote","—"),"Like-for-like") -> Like-for-like | U18: =IF(COUNT(W18:Z18)<2,"",IF(MAX(W18:Z18)=MIN(W18:Z18),"OK","Qty differs")) -> OK | X18: =IF(COUNTIFS('Quote Lines'!$P$3:$P$805,$A18&"|"&H$6&"|1",'Quote Lines'!$M$3:$M$805,"Y")=0,"",SUMIFS('Quote Lines'!$L$3:$L$805,'Quote Lines'!$P$3:$P$805,$A18&"|"&H$6&"|1",'Quote Lines'!$M$3:$M$805,"Y")) -> 1 | Z18: =IF(COUNTIFS('Quote Lines'!$P$3:$P$805,$A18&"|"&J$6&"|1",'Quote Lines'!$M$3:$M$805,"Y")=0,"",SUMIFS('Quote Lines'!$L$3:$L$805,'Quote Lines'!$P$3:$P$805,$A18&"|"&J$6&"|1",'Quote Lines'!$M$3:$M$805,"Y")) -> 1 | AA18: =IF(ISNUMBER(G18),1+SUMPRODUCT(ISNUMBER($G18:$J18)*($G18:$J18<G18)),"") | AB18: =IF(ISNUMBER(H18),1+SUMPRODUCT(ISNUMBER($G18:$J18)*($G18:$J18<H18)),"") -> 1 | AC18: =IF(ISNUMBER(I18),1+SUMPRODUCT(ISNUMBER($G18:$J18)*($G18:$J18<I18)),"") | AD18: =IF(ISNUMBER(J18),1+SUMPRODUCT(ISNUMBER($G18:$J18)*($G18:$J18<J18)),"") -> 2 | AE18: =IF(NOT(ISNUMBER(G18)),0,IF($S18<2,5,IF(AA18=1,1,IF(G18=MAX($G18:$J18),4,IF(AA18=2,2,3))))) -> 0 | AF18: =IF(NOT(ISNUMBER(H18)),0,IF($S18<2,5,IF(AB18=1,1,IF(H18=MAX($G18:$J18),4,IF(AB18=2,2,3))))) -> 1 | AG18: =IF(NOT(ISNUMBER(I18)),0,IF($S18<2,5,IF(AC18=1,1,IF(I18=MAX($G18:$J18),4,IF(AC18=2,2,3))))) -> 0 | AH18: =IF(NOT(ISNUMBER(J18)),0,IF($S18<2,5,IF(AD18=1,1,IF(J18=MAX($G18:$J18),4,IF(AD18=2,2,3))))) -> 4 | AI18: =IF($S18>=2,IF(ISNUMBER(G18),G18*$F18,MIN($G18:$J18)*$F18),0) -> 418.5 | AJ18: =IF($S18>=2,IF(ISNUMBER(H18),H18*$F18,MIN($G18:$J18)*$F18),0) -> 418.5 | AK18: =IF($S18>=2,IF(ISNUMBER(I18),I18*$F18,MIN($G18:$J18)*$F18),0) -> 418.5 | AL18: =IF($S18>=2,IF(ISNUMBER(J18),J18*$F18,MIN($G18:$J18)*$F18),0) -> 465.75 | AM18: =IF($S18>=2,$R18+ROW()/1000000,"") -> 47.250018 | AN18: =IF($S18>=2,MAX(G18:J18),"") -> 465.75 | AO18: =IF($S18>=2,INDEX($G$6:$J$6,MATCH(MAX(G18:J18),G18:J18,0)),"") -> Scholzen | AP18: =IF($S18>=2,MIN(G18:J18)*$F18,0) -> 418.5 | AQ18: =IF($S18>=2,INDEX($G$6:$J$6,MATCH(MIN(G18:J18),G18:J18,0)),"") -> HD Fowler
A19: R012 | B19: Item 5 | C19: DI fittings | D19: 12" MJ 22-1/2° bend (MJ x MJ) | E19: EA | F19: 1 | G19: — | H19: — | I19: — | J19: =IF(COUNTIF('Quote Lines'!$P$3:$P$805,$A19&"|"&J$6&"|1")=0,"—",SUMIFS('Quote Lines'!$O$3:$O$805,'Quote Lines'!$P$3:$P$805,$A19&"|"&J$6&"|1")/SUMIFS('Quote Lines'!$L$3:$L$805,'Quote Lines'!$P$3:$P$805,$A19&"|"&J$6&"|1")) -> 406.5 | K19: =IF(ISNUMBER(G19),G19*$F19,"—") -> — | L19: =IF(ISNUMBER(H19),H19*$F19,"—") -> — | M19: =IF(ISNUMBER(I19),I19*$F19,"—") -> — | N19: =IF(ISNUMBER(J19),J19*$F19,"—") -> 406.5 | O19: =IF($S19=0,"—",MIN(G19:J19)) -> 406.5 | P19: =IF($S19=0,"—",IF(COUNTIF(G19:J19,O19)>1,"Tie",INDEX($G$6:$J$6,MATCH(O19,G19:J19,0)))) -> Scholzen | Q19: =IF($S19>=2,MAX(G19:J19)/MIN(G19:J19)-1,"—") -> — | R19: =IF($S19>=2,(MAX(G19:J19)-MIN(G19:J19))*$F19,"—") -> — | S19: =COUNT(G19:J19) -> 1 | T19: =IF($S19<=1,IF($S19=1,"Single quote","—"),"Like-for-like") -> Single quote | U19: =IF(COUNT(W19:Z19)<2,"",IF(MAX(W19:Z19)=MIN(W19:Z19),"OK","Qty differs")) | Z19: =IF(COUNTIFS('Quote Lines'!$P$3:$P$805,$A19&"|"&J$6&"|1",'Quote Lines'!$M$3:$M$805,"Y")=0,"",SUMIFS('Quote Lines'!$L$3:$L$805,'Quote Lines'!$P$3:$P$805,$A19&"|"&J$6&"|1",'Quote Lines'!$M$3:$M$805,"Y")) -> 1 | AA19: =IF(ISNUMBER(G19),1+SUMPRODUCT(ISNUMBER($G19:$J19)*($G19:$J19<G19)),"") | AB19: =IF(ISNUMBER(H19),1+SUMPRODUCT(ISNUMBER($G19:$J19)*($G19:$J19<H19)),"") | AC19: =IF(ISNUMBER(I19),1+SUMPRODUCT(ISNUMBER($G19:$J19)*($G19:$J19<I19)),"") | AD19: =IF(ISNUMBER(J19),1+SUMPRODUCT(ISNUMBER($G19:$J19)*($G19:$J19<J19)),"") -> 1 | AE19: =IF(NOT(ISNUMBER(G19)),0,IF($S19<2,5,IF(AA19=1,1,IF(G19=MAX($G19:$J19),4,IF(AA19=2,2,3))))) -> 0 | AF19: =IF(NOT(ISNUMBER(H19)),0,IF($S19<2,5,IF(AB19=1,1,IF(H19=MAX($G19:$J19),4,IF(AB19=2,2,3))))) -> 0 | AG19: =IF(NOT(ISNUMBER(I19)),0,IF($S19<2,5,IF(AC19=1,1,IF(I19=MAX($G19:$J19),4,IF(AC19=2,2,3))))) -> 0 | AH19: =IF(NOT(ISNUMBER(J19)),0,IF($S19<2,5,IF(AD19=1,1,IF(J19=MAX($G19:$J19),4,IF(AD19=2,2,3))))) -> 5 | AI19: =IF($S19>=2,IF(ISNUMBER(G19),G19*$F19,MIN($G19:$J19)*$F19),0) -> 0 | AJ19: =IF($S19>=2,IF(ISNUMBER(H19),H19*$F19,MIN($G19:$J19)*$F19),0) -> 0 | AK19: =IF($S19>=2,IF(ISNUMBER(I19),I19*$F19,MIN($G19:$J19)*$F19),0) -> 0 | AL19: =IF($S19>=2,IF(ISNUMBER(J19),J19*$F19,MIN($G19:$J19)*$F19),0) -> 0 | AM19: =IF($S19>=2,$R19+ROW()/1000000,"") | AN19: =IF($S19>=2,MAX(G19:J19),"") | AO19: =IF($S19>=2,INDEX($G$6:$J$6,MATCH(MAX(G19:J19),G19:J19,0)),"") | AP19: =IF($S19>=2,MIN(G19:J19)*$F19,0) -> 0 | AQ19: =IF($S19>=2,INDEX($G$6:$J$6,MATCH(MIN(G19:J19),G19:J19,0)),"")
A20: R013 | B20: Item 5 | C20: DI fittings | D20: 12" MJ x flange adapter | E20: EA | F20: 2 | G20: =IF(COUNTIF('Quote Lines'!$P$3:$P$805,$A20&"|"&G$6&"|1")=0,"—",SUMIFS('Quote Lines'!$O$3:$O$805,'Quote Lines'!$P$3:$P$805,$A20&"|"&G$6&"|1")/SUMIFS('Quote Lines'!$L$3:$L$805,'Quote Lines'!$P$3:$P$805,$A20&"|"&G$6&"|1")) -> 419.9 | H20: — | I20: — | J20: =IF(COUNTIF('Quote Lines'!$P$3:$P$805,$A20&"|"&J$6&"|1")=0,"—",SUMIFS('Quote Lines'!$O$3:$O$805,'Quote Lines'!$P$3:$P$805,$A20&"|"&J$6&"|1")/SUMIFS('Quote Lines'!$L$3:$L$805,'Quote Lines'!$P$3:$P$805,$A20&"|"&J$6&"|1")) -> 488.25 | K20: =IF(ISNUMBER(G20),G20*$F20,"—") -> 839.8 | L20: =IF(ISNUMBER(H20),H20*$F20,"—") -> — | M20: =IF(ISNUMBER(I20),I20*$F20,"—") -> — | N20: =IF(ISNUMBER(J20),J20*$F20,"—") -> 976.5 | O20: =IF($S20=0,"—",MIN(G20:J20)) -> 419.9 | P20: =IF($S20=0,"—",IF(COUNTIF(G20:J20,O20)>1,"Tie",INDEX($G$6:$J$6,MATCH(O20,G20:J20,0)))) -> Ferguson | Q20: =IF($S20>=2,MAX(G20:J20)/MIN(G20:J20)-1,"—") -> 0.16277685 | R20: =IF($S20>=2,(MAX(G20:J20)-MIN(G20:J20))*$F20,"—") -> 136.7 | S20: =COUNT(G20:J20) -> 2 | T20: =IF($S20<=1,IF($S20=1,"Single quote","—"),"Like-for-like") -> Like-for-like | U20: =IF(COUNT(W20:Z20)<2,"",IF(MAX(W20:Z20)=MIN(W20:Z20),"OK","Qty differs")) -> Qty differs | W20: =IF(COUNTIFS('Quote Lines'!$P$3:$P$805,$A20&"|"&G$6&"|1",'Quote Lines'!$M$3:$M$805,"Y")=0,"",SUMIFS('Quote Lines'!$L$3:$L$805,'Quote Lines'!$P$3:$P$805,$A20&"|"&G$6&"|1",'Quote Lines'!$M$3:$M$805,"Y")) -> 1 | Z20: =IF(COUNTIFS('Quote Lines'!$P$3:$P$805,$A20&"|"&J$6&"|1",'Quote Lines'!$M$3:$M$805,"Y")=0,"",SUMIFS('Quote Lines'!$L$3:$L$805,'Quote Lines'!$P$3:$P$805,$A20&"|"&J$6&"|1",'Quote Lines'!$M$3:$M$805,"Y")) -> 2 | AA20: =IF(ISNUMBER(G20),1+SUMPRODUCT(ISNUMBER($G20:$J20)*($G20:$J20<G20)),"") -> 1 | AB20: =IF(ISNUMBER(H20),1+SUMPRODUCT(ISNUMBER($G20:$J20)*($G20:$J20<H20)),"") | AC20: =IF(ISNUMBER(I20),1+SUMPRODUCT(ISNUMBER($G20:$J20)*($G20:$J20<I20)),"") | AD20: =IF(ISNUMBER(J20),1+SUMPRODUCT(ISNUMBER($G20:$J20)*($G20:$J20<J20)),"") -> 2 | AE20: =IF(NOT(ISNUMBER(G20)),0,IF($S20<2,5,IF(AA20=1,1,IF(G20=MAX($G20:$J20),4,IF(AA20=2,2,3))))) -> 1 | AF20: =IF(NOT(ISNUMBER(H20)),0,IF($S20<2,5,IF(AB20=1,1,IF(H20=MAX($G20:$J20),4,IF(AB20=2,2,3))))) -> 0 | AG20: =IF(NOT(ISNUMBER(I20)),0,IF($S20<2,5,IF(AC20=1,1,IF(I20=MAX($G20:$J20),4,IF(AC20=2,2,3))))) -> 0 | AH20: =IF(NOT(ISNUMBER(J20)),0,IF($S20<2,5,IF(AD20=1,1,IF(J20=MAX($G20:$J20),4,IF(AD20=2,2,3))))) -> 4 | AI20: =IF($S20>=2,IF(ISNUMBER(G20),G20*$F20,MIN($G20:$J20)*$F20),0) -> 839.8 | AJ20: =IF($S20>=2,IF(ISNUMBER(H20),H20*$F20,MIN($G20:$J20)*$F20),0) -> 839.8 | AK20: =IF($S20>=2,IF(ISNUMBER(I20),I20*$F20,MIN($G20:$J20)*$F20),0) -> 839.8 | AL20: =IF($S20>=2,IF(ISNUMBER(J20),J20*$F20,MIN($G20:$J20)*$F20),0) -> 976.5 | AM20: =IF($S20>=2,$R20+ROW()/1000000,"") -> 136.70002 | AN20: =IF($S20>=2,MAX(G20:J20),"") -> 488.25 | AO20: =IF($S20>=2,INDEX($G$6:$J$6,MATCH(MAX(G20:J20),G20:J20,0)),"") -> Scholzen | AP20: =IF($S20>=2,MIN(G20:J20)*$F20,0) -> 839.8 | AQ20: =IF($S20>=2,INDEX($G$6:$J$6,MATCH(MIN(G20:J20),G20:J20,0)),"") -> Ferguson
A21: R014 | B21: Item 5 | C21: DI fittings | D21: 12" MJ long sleeve | E21: EA | F21: 2 | G21: =IF(COUNTIF('Quote Lines'!$P$3:$P$805,$A21&"|"&G$6&"|1")=0,"—",SUMIFS('Quote Lines'!$O$3:$O$805,'Quote Lines'!$P$3:$P$805,$A21&"|"&G$6&"|1")/SUMIFS('Quote Lines'!$L$3:$L$805,'Quote Lines'!$P$3:$P$805,$A21&"|"&G$6&"|1")) -> 368.94 | H21: =IF(COUNTIF('Quote Lines'!$P$3:$P$805,$A21&"|"&H$6&"|1")=0,"—",SUMIFS('Quote Lines'!$O$3:$O$805,'Quote Lines'!$P$3:$P$805,$A21&"|"&H$6&"|1")/SUMIFS('Quote Lines'!$L$3:$L$805,'Quote Lines'!$P$3:$P$805,$A21&"|"&H$6&"|1")) -> 385.48 | I21: =IF(COUNTIF('Quote Lines'!$P$3:$P$805,$A21&"|"&I$6&"|1")=0,"—",SUMIFS('Quote Lines'!$O$3:$O$805,'Quote Lines'!$P$3:$P$805,$A21&"|"&I$6&"|1")/SUMIFS('Quote Lines'!$L$3:$L$805,'Quote Lines'!$P$3:$P$805,$A21&"|"&I$6&"|1")) -> 418.54 | J21: =IF(COUNTIF('Quote Lines'!$P$3:$P$805,$A21&"|"&J$6&"|1")=0,"—",SUMIFS('Quote Lines'!$O$3:$O$805,'Quote Lines'!$P$3:$P$805,$A21&"|"&J$6&"|1")/SUMIFS('Quote Lines'!$L$3:$L$805,'Quote Lines'!$P$3:$P$805,$A21&"|"&J$6&"|1")) -> 429 | K21: =IF(ISNUMBER(G21),G21*$F21,"—") -> 737.88 | L21: =IF(ISNUMBER(H21),H21*$F21,"—") -> 770.96 | M21: =IF(ISNUMBER(I21),I21*$F21,"—") -> 837.08 | N21: =IF(ISNUMBER(J21),J21*$F21,"—") -> 858 | O21: =IF($S21=0,"—",MIN(G21:J21)) -> 368.94 | P21: =IF($S21=0,"—",IF(COUNTIF(G21:J21,O21)>1,"Tie",INDEX($G$6:$J$6,MATCH(O21,G21:J21,0)))) -> Ferguson | Q21: =IF($S21>=2,MAX(G21:J21)/MIN(G21:J21)-1,"—") -> 0.1627907 | R21: =IF($S21>=2,(MAX(G21:J21)-MIN(G21:J21))*$F21,"—") -> 120.12 | S21: =COUNT(G21:J21) -> 4 | T21: =IF($S21<=1,IF($S21=1,"Single quote","—"),"Like-for-like") -> Like-for-like | U21: =IF(COUNT(W21:Z21)<2,"",IF(MAX(W21:Z21)=MIN(W21:Z21),"OK","Qty differs")) -> Qty differs | W21: =IF(COUNTIFS('Quote Lines'!$P$3:$P$805,$A21&"|"&G$6&"|1",'Quote Lines'!$M$3:$M$805,"Y")=0,"",SUMIFS('Quote Lines'!$L$3:$L$805,'Quote Lines'!$P$3:$P$805,$A21&"|"&G$6&"|1",'Quote Lines'!$M$3:$M$805,"Y")) -> 3 | X21: =IF(COUNTIFS('Quote Lines'!$P$3:$P$805,$A21&"|"&H$6&"|1",'Quote Lines'!$M$3:$M$805,"Y")=0,"",SUMIFS('Quote Lines'!$L$3:$L$805,'Quote Lines'!$P$3:$P$805,$A21&"|"&H$6&"|1",'Quote Lines'!$M$3:$M$805,"Y")) -> 2 | Y21: =IF(COUNTIFS('Quote Lines'!$P$3:$P$805,$A21&"|"&I$6&"|1",'Quote Lines'!$M$3:$M$805,"Y")=0,"",SUMIFS('Quote Lines'!$L$3:$L$805,'Quote Lines'!$P$3:$P$805,$A21&"|"&I$6&"|1",'Quote Lines'!$M$3:$M$805,"Y")) -> 1 | Z21: =IF(COUNTIFS('Quote Lines'!$P$3:$P$805,$A21&"|"&J$6&"|1",'Quote Lines'!$M$3:$M$805,"Y")=0,"",SUMIFS('Quote Lines'!$L$3:$L$805,'Quote Lines'!$P$3:$P$805,$A21&"|"&J$6&"|1",'Quote Lines'!$M$3:$M$805,"Y")) -> 2 | AA21: =IF(ISNUMBER(G21),1+SUMPRODUCT(ISNUMBER($G21:$J21)*($G21:$J21<G21)),"") -> 1 | AB21: =IF(ISNUMBER(H21),1+SUMPRODUCT(ISNUMBER($G21:$J21)*($G21:$J21<H21)),"") -> 2 | AC21: =IF(ISNUMBER(I21),1+SUMPRODUCT(ISNUMBER($G21:$J21)*($G21:$J21<I21)),"") -> 3 | AD21: =IF(ISNUMBER(J21),1+SUMPRODUCT(ISNUMBER($G21:$J21)*($G21:$J21<J21)),"") -> 4 | AE21: =IF(NOT(ISNUMBER(G21)),0,IF($S21<2,5,IF(AA21=1,1,IF(G21=MAX($G21:$J21),4,IF(AA21=2,2,3))))) -> 1 | AF21: =IF(NOT(ISNUMBER(H21)),0,IF($S21<2,5,IF(AB21=1,1,IF(H21=MAX($G21:$J21),4,IF(AB21=2,2,3))))) -> 2 | AG21: =IF(NOT(ISNUMBER(I21)),0,IF($S21<2,5,IF(AC21=1,1,IF(I21=MAX($G21:$J21),4,IF(AC21=2,2,3))))) -> 3 | AH21: =IF(NOT(ISNUMBER(J21)),0,IF($S21<2,5,IF(AD21=1,1,IF(J21=MAX($G21:$J21),4,IF(AD21=2,2,3))))) -> 4 | AI21: =IF($S21>=2,IF(ISNUMBER(G21),G21*$F21,MIN($G21:$J21)*$F21),0) -> 737.88 | AJ21: =IF($S21>=2,IF(ISNUMBER(H21),H21*$F21,MIN($G21:$J21)*$F21),0) -> 770.96 | AK21: =IF($S21>=2,IF(ISNUMBER(I21),I21*$F21,MIN($G21:$J21)*$F21),0) -> 837.08 | AL21: =IF($S21>=2,IF(ISNUMBER(J21),J21*$F21,MIN($G21:$J21)*$F21),0) -> 858 | AM21: =IF($S21>=2,$R21+ROW()/1000000,"") -> 120.12002 | AN21: =IF($S21>=2,MAX(G21:J21),"") -> 429 | AO21: =IF($S21>=2,INDEX($G$6:$J$6,MATCH(MAX(G21:J21),G21:J21,0)),"") -> Scholzen | AP21: =IF($S21>=2,MIN(G21:J21)*$F21,0) -> 737.88 | AQ21: =IF($S21>=2,INDEX($G$6:$J$6,MATCH(MIN(G21:J21),G21:J21,0)),"") -> Ferguson
A22: R015 | B22: Item 5 | C22: DI fittings | D22: 12" MJ short sleeve (7-1/2") | E22: EA | F22: 2 | G22: =IF(COUNTIF('Quote Lines'!$P$3:$P$805,$A22&"|"&G$6&"|1")=0,"—",SUMIFS('Quote Lines'!$O$3:$O$805,'Quote Lines'!$P$3:$P$805,$A22&"|"&G$6&"|1")/SUMIFS('Quote Lines'!$L$3:$L$805,'Quote Lines'!$P$3:$P$805,$A22&"|"&G$6&"|1")) -> 279.93 | H22: — | I22: — | J22: — | K22: =IF(ISNUMBER(G22),G22*$F22,"—") -> 559.86 | L22: =IF(ISNUMBER(H22),H22*$F22,"—") -> — | M22: =IF(ISNUMBER(I22),I22*$F22,"—") -> — | N22: =IF(ISNUMBER(J22),J22*$F22,"—") -> — | O22: =IF($S22=0,"—",MIN(G22:J22)) -> 279.93 | P22: =IF($S22=0,"—",IF(COUNTIF(G22:J22,O22)>1,"Tie",INDEX($G$6:$J$6,MATCH(O22,G22:J22,0)))) -> Ferguson | Q22: =IF($S22>=2,MAX(G22:J22)/MIN(G22:J22)-1,"—") -> — | R22: =IF($S22>=2,(MAX(G22:J22)-MIN(G22:J22))*$F22,"—") -> — | S22: =COUNT(G22:J22) -> 1 | T22: =IF($S22<=1,IF($S22=1,"Single quote","—"),"Like-for-like") -> Single quote | U22: =IF(COUNT(W22:Z22)<2,"",IF(MAX(W22:Z22)=MIN(W22:Z22),"OK","Qty differs")) | W22: =IF(COUNTIFS('Quote Lines'!$P$3:$P$805,$A22&"|"&G$6&"|1",'Quote Lines'!$M$3:$M$805,"Y")=0,"",SUMIFS('Quote Lines'!$L$3:$L$805,'Quote Lines'!$P$3:$P$805,$A22&"|"&G$6&"|1",'Quote Lines'!$M$3:$M$805,"Y")) -> 2 | AA22: =IF(ISNUMBER(G22),1+SUMPRODUCT(ISNUMBER($G22:$J22)*($G22:$J22<G22)),"") -> 1 | AB22: =IF(ISNUMBER(H22),1+SUMPRODUCT(ISNUMBER($G22:$J22)*($G22:$J22<H22)),"") | AC22: =IF(ISNUMBER(I22),1+SUMPRODUCT(ISNUMBER($G22:$J22)*($G22:$J22<I22)),"") | AD22: =IF(ISNUMBER(J22),1+SUMPRODUCT(ISNUMBER($G22:$J22)*($G22:$J22<J22)),"") | AE22: =IF(NOT(ISNUMBER(G22)),0,IF($S22<2,5,IF(AA22=1,1,IF(G22=MAX($G22:$J22),4,IF(AA22=2,2,3))))) -> 5 | AF22: =IF(NOT(ISNUMBER(H22)),0,IF($S22<2,5,IF(AB22=1,1,IF(H22=MAX($G22:$J22),4,IF(AB22=2,2,3))))) -> 0 | AG22: =IF(NOT(ISNUMBER(I22)),0,IF($S22<2,5,IF(AC22=1,1,IF(I22=MAX($G22:$J22),4,IF(AC22=2,2,3))))) -> 0 | AH22: =IF(NOT(ISNUMBER(J22)),0,IF($S22<2,5,IF(AD22=1,1,IF(J22=MAX($G22:$J22),4,IF(AD22=2,2,3))))) -> 0 | AI22: =IF($S22>=2,IF(ISNUMBER(G22),G22*$F22,MIN($G22:$J22)*$F22),0) -> 0 | AJ22: =IF($S22>=2,IF(ISNUMBER(H22),H22*$F22,MIN($G22:$J22)*$F22),0) -> 0 | AK22: =IF($S22>=2,IF(ISNUMBER(I22),I22*$F22,MIN($G22:$J22)*$F22),0) -> 0 | AL22: =IF($S22>=2,IF(ISNUMBER(J22),J22*$F22,MIN($G22:$J22)*$F22),0) -> 0 | AM22: =IF($S22>=2,$R22+ROW()/1000000,"") | AN22: =IF($S22>=2,MAX(G22:J22),"") | AO22: =IF($S22>=2,INDEX($G$6:$J$6,MATCH(MAX(G22:J22),G22:J22,0)),"") | AP22: =IF($S22>=2,MIN(G22:J22)*$F22,0) -> 0 | AQ22: =IF($S22>=2,INDEX($G$6:$J$6,MATCH(MIN(G22:J22),G22:J22,0)),"")
A23: R016 | B23: Item 5 | C23: DI fittings | D23: 16" MJ sleeve | E23: EA | F23: 1 | G23: — | H23: — | I23: — | J23: =IF(COUNTIF('Quote Lines'!$P$3:$P$805,$A23&"|"&J$6&"|1")=0,"—",SUMIFS('Quote Lines'!$O$3:$O$805,'Quote Lines'!$P$3:$P$805,$A23&"|"&J$6&"|1")/SUMIFS('Quote Lines'!$L$3:$L$805,'Quote Lines'!$P$3:$P$805,$A23&"|"&J$6&"|1")) -> 784.77 | K23: =IF(ISNUMBER(G23),G23*$F23,"—") -> — | L23: =IF(ISNUMBER(H23),H23*$F23,"—") -> — | M23: =IF(ISNUMBER(I23),I23*$F23,"—") -> — | N23: =IF(ISNUMBER(J23),J23*$F23,"—") -> 784.77 | O23: =IF($S23=0,"—",MIN(G23:J23)) -> 784.77 | P23: =IF($S23=0,"—",IF(COUNTIF(G23:J23,O23)>1,"Tie",INDEX($G$6:$J$6,MATCH(O23,G23:J23,0)))) -> Scholzen | Q23: =IF($S23>=2,MAX(G23:J23)/MIN(G23:J23)-1,"—") -> — | R23: =IF($S23>=2,(MAX(G23:J23)-MIN(G23:J23))*$F23,"—") -> — | S23: =COUNT(G23:J23) -> 1 | T23: =IF($S23<=1,IF($S23=1,"Single quote","—"),"Like-for-like") -> Single quote | U23: =IF(COUNT(W23:Z23)<2,"",IF(MAX(W23:Z23)=MIN(W23:Z23),"OK","Qty differs")) | Z23: =IF(COUNTIFS('Quote Lines'!$P$3:$P$805,$A23&"|"&J$6&"|1",'Quote Lines'!$M$3:$M$805,"Y")=0,"",SUMIFS('Quote Lines'!$L$3:$L$805,'Quote Lines'!$P$3:$P$805,$A23&"|"&J$6&"|1",'Quote Lines'!$M$3:$M$805,"Y")) -> 1 | AA23: =IF(ISNUMBER(G23),1+SUMPRODUCT(ISNUMBER($G23:$J23)*($G23:$J23<G23)),"") | AB23: =IF(ISNUMBER(H23),1+SUMPRODUCT(ISNUMBER($G23:$J23)*($G23:$J23<H23)),"") | AC23: =IF(ISNUMBER(I23),1+SUMPRODUCT(ISNUMBER($G23:$J23)*($G23:$J23<I23)),"") | AD23: =IF(ISNUMBER(J23),1+SUMPRODUCT(ISNUMBER($G23:$J23)*($G23:$J23<J23)),"") -> 1 | AE23: =IF(NOT(ISNUMBER(G23)),0,IF($S23<2,5,IF(AA23=1,1,IF(G23=MAX($G23:$J23),4,IF(AA23=2,2,3))))) -> 0 | AF23: =IF(NOT(ISNUMBER(H23)),0,IF($S23<2,5,IF(AB23=1,1,IF(H23=MAX($G23:$J23),4,IF(AB23=2,2,3))))) -> 0 | AG23: =IF(NOT(ISNUMBER(I23)),0,IF($S23<2,5,IF(AC23=1,1,IF(I23=MAX($G23:$J23),4,IF(AC23=2,2,3))))) -> 0 | AH23: =IF(NOT(ISNUMBER(J23)),0,IF($S23<2,5,IF(AD23=1,1,IF(J23=MAX($G23:$J23),4,IF(AD23=2,2,3))))) -> 5 | AI23: =IF($S23>=2,IF(ISNUMBER(G23),G23*$F23,MIN($G23:$J23)*$F23),0) -> 0 | AJ23: =IF($S23>=2,IF(ISNUMBER(H23),H23*$F23,MIN($G23:$J23)*$F23),0) -> 0 | AK23: =IF($S23>=2,IF(ISNUMBER(I23),I23*$F23,MIN($G23:$J23)*$F23),0) -> 0 | AL23: =IF($S23>=2,IF(ISNUMBER(J23),J23*$F23,MIN($G23:$J23)*$F23),0) -> 0 | AM23: =IF($S23>=2,$R23+ROW()/1000000,"") | AN23: =IF($S23>=2,MAX(G23:J23),"") | AO23: =IF($S23>=2,INDEX($G$6:$J$6,MATCH(MAX(G23:J23),G23:J23,0)),"") | AP23: =IF($S23>=2,MIN(G23:J23)*$F23,0) -> 0 | AQ23: =IF($S23>=2,INDEX($G$6:$J$6,MATCH(MIN(G23:J23),G23:J23,0)),"")
A24: R017 | B24: Item 5 | C24: DI fittings | D24: 4" MJ sleeve | E24: EA | F24: 1 | G24: =IF(COUNTIF('Quote Lines'!$P$3:$P$805,$A24&"|"&G$6&"|1")=0,"—",SUMIFS('Quote Lines'!$O$3:$O$805,'Quote Lines'!$P$3:$P$805,$A24&"|"&G$6&"|1")/SUMIFS('Quote Lines'!$L$3:$L$805,'Quote Lines'!$P$3:$P$805,$A24&"|"&G$6&"|1")) -> 85.78 | H24: — | I24: — | J24: =IF(COUNTIF('Quote Lines'!$P$3:$P$805,$A24&"|"&J$6&"|1")=0,"—",SUMIFS('Quote Lines'!$O$3:$O$805,'Quote Lines'!$P$3:$P$805,$A24&"|"&J$6&"|1")/SUMIFS('Quote Lines'!$L$3:$L$805,'Quote Lines'!$P$3:$P$805,$A24&"|"&J$6&"|1")) -> 99.75 | K24: =IF(ISNUMBER(G24),G24*$F24,"—") -> 85.78 | L24: =IF(ISNUMBER(H24),H24*$F24,"—") -> — | M24: =IF(ISNUMBER(I24),I24*$F24,"—") -> — | N24: =IF(ISNUMBER(J24),J24*$F24,"—") -> 99.75 | O24: =IF($S24=0,"—",MIN(G24:J24)) -> 85.78 | P24: =IF($S24=0,"—",IF(COUNTIF(G24:J24,O24)>1,"Tie",INDEX($G$6:$J$6,MATCH(O24,G24:J24,0)))) -> Ferguson | Q24: =IF($S24>=2,MAX(G24:J24)/MIN(G24:J24)-1,"—") -> 0.16285848 | R24: =IF($S24>=2,(MAX(G24:J24)-MIN(G24:J24))*$F24,"—") -> 13.97 | S24: =COUNT(G24:J24) -> 2 | T24: =IF($S24<=1,IF($S24=1,"Single quote","—"),"Like-for-like") -> Like-for-like | U24: =IF(COUNT(W24:Z24)<2,"",IF(MAX(W24:Z24)=MIN(W24:Z24),"OK","Qty differs")) -> OK | V24: Ferguson: 4x12 long sleeve. | W24: =IF(COUNTIFS('Quote Lines'!$P$3:$P$805,$A24&"|"&G$6&"|1",'Quote Lines'!$M$3:$M$805,"Y")=0,"",SUMIFS('Quote Lines'!$L$3:$L$805,'Quote Lines'!$P$3:$P$805,$A24&"|"&G$6&"|1",'Quote Lines'!$M$3:$M$805,"Y")) -> 1 | Z24: =IF(COUNTIFS('Quote Lines'!$P$3:$P$805,$A24&"|"&J$6&"|1",'Quote Lines'!$M$3:$M$805,"Y")=0,"",SUMIFS('Quote Lines'!$L$3:$L$805,'Quote Lines'!$P$3:$P$805,$A24&"|"&J$6&"|1",'Quote Lines'!$M$3:$M$805,"Y")) -> 1 | AA24: =IF(ISNUMBER(G24),1+SUMPRODUCT(ISNUMBER($G24:$J24)*($G24:$J24<G24)),"") -> 1 | AB24: =IF(ISNUMBER(H24),1+SUMPRODUCT(ISNUMBER($G24:$J24)*($G24:$J24<H24)),"") | AC24: =IF(ISNUMBER(I24),1+SUMPRODUCT(ISNUMBER($G24:$J24)*($G24:$J24<I24)),"") | AD24: =IF(ISNUMBER(J24),1+SUMPRODUCT(ISNUMBER($G24:$J24)*($G24:$J24<J24)),"") -> 2 | AE24: =IF(NOT(ISNUMBER(G24)),0,IF($S24<2,5,IF(AA24=1,1,IF(G24=MAX($G24:$J24),4,IF(AA24=2,2,3))))) -> 1 | AF24: =IF(NOT(ISNUMBER(H24)),0,IF($S24<2,5,IF(AB24=1,1,IF(H24=MAX($G24:$J24),4,IF(AB24=2,2,3))))) -> 0 | AG24: =IF(NOT(ISNUMBER(I24)),0,IF($S24<2,5,IF(AC24=1,1,IF(I24=MAX($G24:$J24),4,IF(AC24=2,2,3))))) -> 0 | AH24: =IF(NOT(ISNUMBER(J24)),0,IF($S24<2,5,IF(AD24=1,1,IF(J24=MAX($G24:$J24),4,IF(AD24=2,2,3))))) -> 4 | AI24: =IF($S24>=2,IF(ISNUMBER(G24),G24*$F24,MIN($G24:$J24)*$F24),0) -> 85.78 | AJ24: =IF($S24>=2,IF(ISNUMBER(H24),H24*$F24,MIN($G24:$J24)*$F24),0) -> 85.78 | AK24: =IF($S24>=2,IF(ISNUMBER(I24),I24*$F24,MIN($G24:$J24)*$F24),0) -> 85.78 | AL24: =IF($S24>=2,IF(ISNUMBER(J24),J24*$F24,MIN($G24:$J24)*$F24),0) -> 99.75 | AM24: =IF($S24>=2,$R24+ROW()/1000000,"") -> 13.970024 | AN24: =IF($S24>=2,MAX(G24:J24),"") -> 99.75 | AO24: =IF($S24>=2,INDEX($G$6:$J$6,MATCH(MAX(G24:J24),G24:J24,0)),"") -> Scholzen | AP24: =IF($S24>=2,MIN(G24:J24)*$F24,0) -> 85.78 | AQ24: =IF($S24>=2,INDEX($G$6:$J$6,MATCH(MIN(G24:J24),G24:J24,0)),"") -> Ferguson
A25: R018 | B25: Item 5 | C25: DI fittings | D25: 4" MJ x flange adapter | E25: EA | F25: 1 | G25: — | H25: — | I25: =IF(COUNTIF('Quote Lines'!$P$3:$P$805,$A25&"|"&I$6&"|1")=0,"—",SUMIFS('Quote Lines'!$O$3:$O$805,'Quote Lines'!$P$3:$P$805,$A25&"|"&I$6&"|1")/SUMIFS('Quote Lines'!$L$3:$L$805,'Quote Lines'!$P$3:$P$805,$A25&"|"&I$6&"|1")) -> 103.9 | J25: — | K25: =IF(ISNUMBER(G25),G25*$F25,"—") -> — | L25: =IF(ISNUMBER(H25),H25*$F25,"—") -> — | M25: =IF(ISNUMBER(I25),I25*$F25,"—") -> 103.9 | N25: =IF(ISNUMBER(J25),J25*$F25,"—") -> — | O25: =IF($S25=0,"—",MIN(G25:J25)) -> 103.9 | P25: =IF($S25=0,"—",IF(COUNTIF(G25:J25,O25)>1,"Tie",INDEX($G$6:$J$6,MATCH(O25,G25:J25,0)))) -> Mountainland | Q25: =IF($S25>=2,MAX(G25:J25)/MIN(G25:J25)-1,"—") -> — | R25: =IF($S25>=2,(MAX(G25:J25)-MIN(G25:J25))*$F25,"—") -> — | S25: =COUNT(G25:J25) -> 1 | T25: =IF($S25<=1,IF($S25=1,"Single quote","—"),"Like-for-like") -> Single quote | U25: =IF(COUNT(W25:Z25)<2,"",IF(MAX(W25:Z25)=MIN(W25:Z25),"OK","Qty differs")) | Y25: =IF(COUNTIFS('Quote Lines'!$P$3:$P$805,$A25&"|"&I$6&"|1",'Quote Lines'!$M$3:$M$805,"Y")=0,"",SUMIFS('Quote Lines'!$L$3:$L$805,'Quote Lines'!$P$3:$P$805,$A25&"|"&I$6&"|1",'Quote Lines'!$M$3:$M$805,"Y")) -> 1 | AA25: =IF(ISNUMBER(G25),1+SUMPRODUCT(ISNUMBER($G25:$J25)*($G25:$J25<G25)),"") | AB25: =IF(ISNUMBER(H25),1+SUMPRODUCT(ISNUMBER($G25:$J25)*($G25:$J25<H25)),"") | AC25: =IF(ISNUMBER(I25),1+SUMPRODUCT(ISNUMBER($G25:$J25)*($G25:$J25<I25)),"") -> 1 | AD25: =IF(ISNUMBER(J25),1+SUMPRODUCT(ISNUMBER($G25:$J25)*($G25:$J25<J25)),"") | AE25: =IF(NOT(ISNUMBER(G25)),0,IF($S25<2,5,IF(AA25=1,1,IF(G25=MAX($G25:$J25),4,IF(AA25=2,2,3))))) -> 0 | AF25: =IF(NOT(ISNUMBER(H25)),0,IF($S25<2,5,IF(AB25=1,1,IF(H25=MAX($G25:$J25),4,IF(AB25=2,2,3))))) -> 0 | AG25: =IF(NOT(ISNUMBER(I25)),0,IF($S25<2,5,IF(AC25=1,1,IF(I25=MAX($G25:$J25),4,IF(AC25=2,2,3))))) -> 5 | AH25: =IF(NOT(ISNUMBER(J25)),0,IF($S25<2,5,IF(AD25=1,1,IF(J25=MAX($G25:$J25),4,IF(AD25=2,2,3))))) -> 0 | AI25: =IF($S25>=2,IF(ISNUMBER(G25),G25*$F25,MIN($G25:$J25)*$F25),0) -> 0 | AJ25: =IF($S25>=2,IF(ISNUMBER(H25),H25*$F25,MIN($G25:$J25)*$F25),0) -> 0 | AK25: =IF($S25>=2,IF(ISNUMBER(I25),I25*$F25,MIN($G25:$J25)*$F25),0) -> 0 | AL25: =IF($S25>=2,IF(ISNUMBER(J25),J25*$F25,MIN($G25:$J25)*$F25),0) -> 0 | AM25: =IF($S25>=2,$R25+ROW()/1000000,"") | AN25: =IF($S25>=2,MAX(G25:J25),"") | AO25: =IF($S25>=2,INDEX($G$6:$J$6,MATCH(MAX(G25:J25),G25:J25,0)),"") | AP25: =IF($S25>=2,MIN(G25:J25)*$F25,0) -> 0 | AQ25: =IF($S25>=2,INDEX($G$6:$J$6,MATCH(MIN(G25:J25),G25:J25,0)),"")
A26: R019 | B26: Item 5 | C26: DI fittings | D26: 10" x 2" tapped blind flange (2" IP tap) | E26: EA | F26: 2 | G26: =IF(COUNTIF('Quote Lines'!$P$3:$P$805,$A26&"|"&G$6&"|1")=0,"—",SUMIFS('Quote Lines'!$O$3:$O$805,'Quote Lines'!$P$3:$P$805,$A26&"|"&G$6&"|1")/SUMIFS('Quote Lines'!$L$3:$L$805,'Quote Lines'!$P$3:$P$805,$A26&"|"&G$6&"|1")) -> 347.01 | H26: =IF(COUNTIF('Quote Lines'!$P$3:$P$805,$A26&"|"&H$6&"|1")=0,"—",SUMIFS('Quote Lines'!$O$3:$O$805,'Quote Lines'!$P$3:$P$805,$A26&"|"&H$6&"|1")/SUMIFS('Quote Lines'!$L$3:$L$805,'Quote Lines'!$P$3:$P$805,$A26&"|"&H$6&"|1")) -> 362.57 | I26: =IF(COUNTIF('Quote Lines'!$P$3:$P$805,$A26&"|"&I$6&"|1")=0,"—",SUMIFS('Quote Lines'!$O$3:$O$805,'Quote Lines'!$P$3:$P$805,$A26&"|"&I$6&"|1")/SUMIFS('Quote Lines'!$L$3:$L$805,'Quote Lines'!$P$3:$P$805,$A26&"|"&I$6&"|1")) -> 393.66 | J26: — | K26: =IF(ISNUMBER(G26),G26*$F26,"—") -> 694.02 | L26: =IF(ISNUMBER(H26),H26*$F26,"—") -> 725.14 | M26: =IF(ISNUMBER(I26),I26*$F26,"—") -> 787.32 | N26: =IF(ISNUMBER(J26),J26*$F26,"—") -> — | O26: =IF($S26=0,"—",MIN(G26:J26)) -> 347.01 | P26: =IF($S26=0,"—",IF(COUNTIF(G26:J26,O26)>1,"Tie",INDEX($G$6:$J$6,MATCH(O26,G26:J26,0)))) -> Ferguson | Q26: =IF($S26>=2,MAX(G26:J26)/MIN(G26:J26)-1,"—") -> 0.13443417 | R26: =IF($S26>=2,(MAX(G26:J26)-MIN(G26:J26))*$F26,"—") -> 93.3 | S26: =COUNT(G26:J26) -> 3 | T26: =IF($S26<=1,IF($S26=1,"Single quote","—"),"Like-for-like") -> Like-for-like | U26: =IF(COUNT(W26:Z26)<2,"",IF(MAX(W26:Z26)=MIN(W26:Z26),"OK","Qty differs")) -> OK | W26: =IF(COUNTIFS('Quote Lines'!$P$3:$P$805,$A26&"|"&G$6&"|1",'Quote Lines'!$M$3:$M$805,"Y")=0,"",SUMIFS('Quote Lines'!$L$3:$L$805,'Quote Lines'!$P$3:$P$805,$A26&"|"&G$6&"|1",'Quote Lines'!$M$3:$M$805,"Y")) -> 2 | X26: =IF(COUNTIFS('Quote Lines'!$P$3:$P$805,$A26&"|"&H$6&"|1",'Quote Lines'!$M$3:$M$805,"Y")=0,"",SUMIFS('Quote Lines'!$L$3:$L$805,'Quote Lines'!$P$3:$P$805,$A26&"|"&H$6&"|1",'Quote Lines'!$M$3:$M$805,"Y")) -> 2 | Y26: =IF(COUNTIFS('Quote Lines'!$P$3:$P$805,$A26&"|"&I$6&"|1",'Quote Lines'!$M$3:$M$805,"Y")=0,"",SUMIFS('Quote Lines'!$L$3:$L$805,'Quote Lines'!$P$3:$P$805,$A26&"|"&I$6&"|1",'Quote Lines'!$M$3:$M$805,"Y")) -> 2 | AA26: =IF(ISNUMBER(G26),1+SUMPRODUCT(ISNUMBER($G26:$J26)*($G26:$J26<G26)),"") -> 1 | AB26: =IF(ISNUMBER(H26),1+SUMPRODUCT(ISNUMBER($G26:$J26)*($G26:$J26<H26)),"") -> 2 | AC26: =IF(ISNUMBER(I26),1+SUMPRODUCT(ISNUMBER($G26:$J26)*($G26:$J26<I26)),"") -> 3 | AD26: =IF(ISNUMBER(J26),1+SUMPRODUCT(ISNUMBER($G26:$J26)*($G26:$J26<J26)),"") | AE26: =IF(NOT(ISNUMBER(G26)),0,IF($S26<2,5,IF(AA26=1,1,IF(G26=MAX($G26:$J26),4,IF(AA26=2,2,3))))) -> 1 | AF26: =IF(NOT(ISNUMBER(H26)),0,IF($S26<2,5,IF(AB26=1,1,IF(H26=MAX($G26:$J26),4,IF(AB26=2,2,3))))) -> 2 | AG26: =IF(NOT(ISNUMBER(I26)),0,IF($S26<2,5,IF(AC26=1,1,IF(I26=MAX($G26:$J26),4,IF(AC26=2,2,3))))) -> 4 | AH26: =IF(NOT(ISNUMBER(J26)),0,IF($S26<2,5,IF(AD26=1,1,IF(J26=MAX($G26:$J26),4,IF(AD26=2,2,3))))) -> 0 | AI26: =IF($S26>=2,IF(ISNUMBER(G26),G26*$F26,MIN($G26:$J26)*$F26),0) -> 694.02 | AJ26: =IF($S26>=2,IF(ISNUMBER(H26),H26*$F26,MIN($G26:$J26)*$F26),0) -> 725.14 | AK26: =IF($S26>=2,IF(ISNUMBER(I26),I26*$F26,MIN($G26:$J26)*$F26),0) -> 787.32 | AL26: =IF($S26>=2,IF(ISNUMBER(J26),J26*$F26,MIN($G26:$J26)*$F26),0) -> 694.02 | AM26: =IF($S26>=2,$R26+ROW()/1000000,"") -> 93.300026 | AN26: =IF($S26>=2,MAX(G26:J26),"") -> 393.66 | AO26: =IF($S26>=2,INDEX($G$6:$J$6,MATCH(MAX(G26:J26),G26:J26,0)),"") -> Mountainland | AP26: =IF($S26>=2,MIN(G26:J26)*$F26,0) -> 694.02 | AQ26: =IF($S26>=2,INDEX($G$6:$J$6,MATCH(MIN(G26:J26),G26:J26,0)),"") -> Ferguson
A27: R020 | B27: Item 5 | C27: PVC / DI pipe | D27: 4" DI pipe (CL350 / CL51, TJ) | E27: FT | F27: 20 | G27: =IF(COUNTIF('Quote Lines'!$P$3:$P$805,$A27&"|"&G$6&"|1")=0,"—",SUMIFS('Quote Lines'!$O$3:$O$805,'Quote Lines'!$P$3:$P$805,$A27&"|"&G$6&"|1")/SUMIFS('Quote Lines'!$L$3:$L$805,'Quote Lines'!$P$3:$P$805,$A27&"|"&G$6&"|1")) -> 40.33 | H27: =IF(COUNTIF('Quote Lines'!$P$3:$P$805,$A27&"|"&H$6&"|1")=0,"—",SUMIFS('Quote Lines'!$O$3:$O$805,'Quote Lines'!$P$3:$P$805,$A27&"|"&H$6&"|1")/SUMIFS('Quote Lines'!$L$3:$L$805,'Quote Lines'!$P$3:$P$805,$A27&"|"&H$6&"|1")) -> 39.489863 | I27: — | J27: =IF(COUNTIF('Quote Lines'!$P$3:$P$805,$A27&"|"&J$6&"|1")=0,"—",SUMIFS('Quote Lines'!$O$3:$O$805,'Quote Lines'!$P$3:$P$805,$A27&"|"&J$6&"|1")/SUMIFS('Quote Lines'!$L$3:$L$805,'Quote Lines'!$P$3:$P$805,$A27&"|"&J$6&"|1")) -> 43.37 | K27: =IF(ISNUMBER(G27),G27*$F27,"—") -> 806.6 | L27: =IF(ISNUMBER(H27),H27*$F27,"—") -> 789.79726 | M27: =IF(ISNUMBER(I27),I27*$F27,"—") -> — | N27: =IF(ISNUMBER(J27),J27*$F27,"—") -> 867.4 | O27: =IF($S27=0,"—",MIN(G27:J27)) -> 39.489863 | P27: =IF($S27=0,"—",IF(COUNTIF(G27:J27,O27)>1,"Tie",INDEX($G$6:$J$6,MATCH(O27,G27:J27,0)))) -> HD Fowler | Q27: =IF($S27>=2,MAX(G27:J27)/MIN(G27:J27)-1,"—") -> 0.098256532 | R27: =IF($S27>=2,(MAX(G27:J27)-MIN(G27:J27))*$F27,"—") -> 77.60274 | S27: =COUNT(G27:J27) -> 3 | T27: =IF($S27<=1,IF($S27=1,"Single quote","—"),"Alt spec – verify") -> Alt spec – verify | U27: =IF(COUNT(W27:Z27)<2,"",IF(MAX(W27:Z27)=MIN(W27:Z27),"OK","Qty differs")) -> Qty differs | V27: Ferguson CL350 double-cement-lined FASTITE; H & S CL51 TJ. | W27: =IF(COUNTIFS('Quote Lines'!$P$3:$P$805,$A27&"|"&G$6&"|1",'Quote Lines'!$M$3:$M$805,"Y")=0,"",SUMIFS('Quote Lines'!$L$3:$L$805,'Quote Lines'!$P$3:$P$805,$A27&"|"&G$6&"|1",'Quote Lines'!$M$3:$M$805,"Y")) -> 20 | X27: =IF(COUNTIFS('Quote Lines'!$P$3:$P$805,$A27&"|"&H$6&"|1",'Quote Lines'!$M$3:$M$805,"Y")=0,"",SUMIFS('Quote Lines'!$L$3:$L$805,'Quote Lines'!$P$3:$P$805,$A27&"|"&H$6&"|1",'Quote Lines'!$M$3:$M$805,"Y")) -> 18.25 | Z27: =IF(COUNTIFS('Quote Lines'!$P$3:$P$805,$A27&"|"&J$6&"|1",'Quote Lines'!$M$3:$M$805,"Y")=0,"",SUMIFS('Quote Lines'!$L$3:$L$805,'Quote Lines'!$P$3:$P$805,$A27&"|"&J$6&"|1",'Quote Lines'!$M$3:$M$805,"Y")) -> 20 | AA27: =IF(ISNUMBER(G27),1+SUMPRODUCT(ISNUMBER($G27:$J27)*($G27:$J27<G27)),"") -> 2 | AB27: =IF(ISNUMBER(H27),1+SUMPRODUCT(ISNUMBER($G27:$J27)*($G27:$J27<H27)),"") -> 1 | AC27: =IF(ISNUMBER(I27),1+SUMPRODUCT(ISNUMBER($G27:$J27)*($G27:$J27<I27)),"") | AD27: =IF(ISNUMBER(J27),1+SUMPRODUCT(ISNUMBER($G27:$J27)*($G27:$J27<J27)),"") -> 3 | AE27: =IF(NOT(ISNUMBER(G27)),0,IF($S27<2,5,IF(AA27=1,1,IF(G27=MAX($G27:$J27),4,IF(AA27=2,2,3))))) -> 2 | AF27: =IF(NOT(ISNUMBER(H27)),0,IF($S27<2,5,IF(AB27=1,1,IF(H27=MAX($G27:$J27),4,IF(AB27=2,2,3))))) -> 1 | AG27: =IF(NOT(ISNUMBER(I27)),0,IF($S27<2,5,IF(AC27=1,1,IF(I27=MAX($G27:$J27),4,IF(AC27=2,2,3))))) -> 0 | AH27: =IF(NOT(ISNUMBER(J27)),0,IF($S27<2,5,IF(AD27=1,1,IF(J27=MAX($G27:$J27),4,IF(AD27=2,2,3))))) -> 4 | AI27: =IF($S27>=2,IF(ISNUMBER(G27),G27*$F27,MIN($G27:$J27)*$F27),0) -> 806.6 | AJ27: =IF($S27>=2,IF(ISNUMBER(H27),H27*$F27,MIN($G27:$J27)*$F27),0) -> 789.79726 | AK27: =IF($S27>=2,IF(ISNUMBER(I27),I27*$F27,MIN($G27:$J27)*$F27),0) -> 789.79726 | AL27: =IF($S27>=2,IF(ISNUMBER(J27),J27*$F27,MIN($G27:$J27)*$F27),0) -> 867.4 | AM27: =IF($S27>=2,$R27+ROW()/1000000,"") -> 77.602767 | AN27: =IF($S27>=2,MAX(G27:J27),"") -> 43.37 | AO27: =IF($S27>=2,INDEX($G$6:$J$6,MATCH(MAX(G27:J27),G27:J27,0)),"") -> Scholzen | AP27: =IF($S27>=2,MIN(G27:J27)*$F27,0) -> 789.79726 | AQ27: =IF($S27>=2,INDEX($G$6:$J$6,MATCH(MIN(G27:J27),G27:J27,0)),"") -> HD Fowler
A28: R021 | B28: Item 5 | C28: PVC / DI pipe | D28: 12" CL51 DI pipe (TJ) | E28: FT | F28: 19 | G28: — | H28: — | I28: — | J28: =IF(COUNTIF('Quote Lines'!$P$3:$P$805,$A28&"|"&J$6&"|1")=0,"—",SUMIFS('Quote Lines'!$O$3:$O$805,'Quote Lines'!$P$3:$P$805,$A28&"|"&J$6&"|1")/SUMIFS('Quote Lines'!$L$3:$L$805,'Quote Lines'!$P$3:$P$805,$A28&"|"&J$6&"|1")) -> 71.67 | K28: =IF(ISNUMBER(G28),G28*$F28,"—") -> — | L28: =IF(ISNUMBER(H28),H28*$F28,"—") -> — | M28: =IF(ISNUMBER(I28),I28*$F28,"—") -> — | N28: =IF(ISNUMBER(J28),J28*$F28,"—") -> 1361.73 | O28: =IF($S28=0,"—",MIN(G28:J28)) -> 71.67 | P28: =IF($S28=0,"—",IF(COUNTIF(G28:J28,O28)>1,"Tie",INDEX($G$6:$J$6,MATCH(O28,G28:J28,0)))) -> Scholzen | Q28: =IF($S28>=2,MAX(G28:J28)/MIN(G28:J28)-1,"—") -> — | R28: =IF($S28>=2,(MAX(G28:J28)-MIN(G28:J28))*$F28,"—") -> — | S28: =COUNT(G28:J28) -> 1 | T28: =IF($S28<=1,IF($S28=1,"Single quote","—"),"Like-for-like") -> Single quote | U28: =IF(COUNT(W28:Z28)<2,"",IF(MAX(W28:Z28)=MIN(W28:Z28),"OK","Qty differs")) | Z28: =IF(COUNTIFS('Quote Lines'!$P$3:$P$805,$A28&"|"&J$6&"|1",'Quote Lines'!$M$3:$M$805,"Y")=0,"",SUMIFS('Quote Lines'!$L$3:$L$805,'Quote Lines'!$P$3:$P$805,$A28&"|"&J$6&"|1",'Quote Lines'!$M$3:$M$805,"Y")) -> 19 | AA28: =IF(ISNUMBER(G28),1+SUMPRODUCT(ISNUMBER($G28:$J28)*($G28:$J28<G28)),"") | AB28: =IF(ISNUMBER(H28),1+SUMPRODUCT(ISNUMBER($G28:$J28)*($G28:$J28<H28)),"") | AC28: =IF(ISNUMBER(I28),1+SUMPRODUCT(ISNUMBER($G28:$J28)*($G28:$J28<I28)),"") | AD28: =IF(ISNUMBER(J28),1+SUMPRODUCT(ISNUMBER($G28:$J28)*($G28:$J28<J28)),"") -> 1 | AE28: =IF(NOT(ISNUMBER(G28)),0,IF($S28<2,5,IF(AA28=1,1,IF(G28=MAX($G28:$J28),4,IF(AA28=2,2,3))))) -> 0 | AF28: =IF(NOT(ISNUMBER(H28)),0,IF($S28<2,5,IF(AB28=1,1,IF(H28=MAX($G28:$J28),4,IF(AB28=2,2,3))))) -> 0 | AG28: =IF(NOT(ISNUMBER(I28)),0,IF($S28<2,5,IF(AC28=1,1,IF(I28=MAX($G28:$J28),4,IF(AC28=2,2,3))))) -> 0 | AH28: =IF(NOT(ISNUMBER(J28)),0,IF($S28<2,5,IF(AD28=1,1,IF(J28=MAX($G28:$J28),4,IF(AD28=2,2,3))))) -> 5 | AI28: =IF($S28>=2,IF(ISNUMBER(G28),G28*$F28,MIN($G28:$J28)*$F28),0) -> 0 | AJ28: =IF($S28>=2,IF(ISNUMBER(H28),H28*$F28,MIN($G28:$J28)*$F28),0) -> 0 | AK28: =IF($S28>=2,IF(ISNUMBER(I28),I28*$F28,MIN($G28:$J28)*$F28),0) -> 0 | AL28: =IF($S28>=2,IF(ISNUMBER(J28),J28*$F28,MIN($G28:$J28)*$F28),0) -> 0 | AM28: =IF($S28>=2,$R28+ROW()/1000000,"") | AN28: =IF($S28>=2,MAX(G28:J28),"") | AO28: =IF($S28>=2,INDEX($G$6:$J$6,MATCH(MAX(G28:J28),G28:J28,0)),"") | AP28: =IF($S28>=2,MIN(G28:J28)*$F28,0) -> 0 | AQ28: =IF($S28>=2,INDEX($G$6:$J$6,MATCH(MIN(G28:J28),G28:J28,0)),"")
A29: R022 | B29: Item 5 | C29: DI spools | D29: 16" x 15'-0" flange x PE DI spool | E29: EA | F29: 1 | G29: =IF(COUNTIF('Quote Lines'!$P$3:$P$805,$A29&"|"&G$6&"|1")=0,"—",SUMIFS('Quote Lines'!$O$3:$O$805,'Quote Lines'!$P$3:$P$805,$A29&"|"&G$6&"|1")/SUMIFS('Quote Lines'!$L$3:$L$805,'Quote Lines'!$P$3:$P$805,$A29&"|"&G$6&"|1")) -> 6622.86 | H29: =IF(COUNTIF('Quote Lines'!$P$3:$P$805,$A29&"|"&H$6&"|1")=0,"—",SUMIFS('Quote Lines'!$O$3:$O$805,'Quote Lines'!$P$3:$P$805,$A29&"|"&H$6&"|1")/SUMIFS('Quote Lines'!$L$3:$L$805,'Quote Lines'!$P$3:$P$805,$A29&"|"&H$6&"|1")) -> 4510.99 | I29: =IF(COUNTIF('Quote Lines'!$P$3:$P$805,$A29&"|"&I$6&"|1")=0,"—",SUMIFS('Quote Lines'!$O$3:$O$805,'Quote Lines'!$P$3:$P$805,$A29&"|"&I$6&"|1")/SUMIFS('Quote Lines'!$L$3:$L$805,'Quote Lines'!$P$3:$P$805,$A29&"|"&I$6&"|1")) -> 5606.63 | J29: — | K29: =IF(ISNUMBER(G29),G29*$F29,"—") -> 6622.86 | L29: =IF(ISNUMBER(H29),H29*$F29,"—") -> 4510.99 | M29: =IF(ISNUMBER(I29),I29*$F29,"—") -> 5606.63 | N29: =IF(ISNUMBER(J29),J29*$F29,"—") -> — | O29: =IF($S29=0,"—",MIN(G29:J29)) -> 4510.99 | P29: =IF($S29=0,"—",IF(COUNTIF(G29:J29,O29)>1,"Tie",INDEX($G$6:$J$6,MATCH(O29,G29:J29,0)))) -> HD Fowler | Q29: =IF($S29>=2,MAX(G29:J29)/MIN(G29:J29)-1,"—") -> 0.46816109 | R29: =IF($S29>=2,(MAX(G29:J29)-MIN(G29:J29))*$F29,"—") -> 2111.87 | S29: =COUNT(G29:J29) -> 3 | T29: =IF($S29<=1,IF($S29=1,"Single quote","—"),"Like-for-like") -> Like-for-like | U29: =IF(COUNT(W29:Z29)<2,"",IF(MAX(W29:Z29)=MIN(W29:Z29),"OK","Qty differs")) -> OK | W29: =IF(COUNTIFS('Quote Lines'!$P$3:$P$805,$A29&"|"&G$6&"|1",'Quote Lines'!$M$3:$M$805,"Y")=0,"",SUMIFS('Quote Lines'!$L$3:$L$805,'Quote Lines'!$P$3:$P$805,$A29&"|"&G$6&"|1",'Quote Lines'!$M$3:$M$805,"Y")) -> 1 | X29: =IF(COUNTIFS('Quote Lines'!$P$3:$P$805,$A29&"|"&H$6&"|1",'Quote Lines'!$M$3:$M$805,"Y")=0,"",SUMIFS('Quote Lines'!$L$3:$L$805,'Quote Lines'!$P$3:$P$805,$A29&"|"&H$6&"|1",'Quote Lines'!$M$3:$M$805,"Y")) -> 1 | Y29: =IF(COUNTIFS('Quote Lines'!$P$3:$P$805,$A29&"|"&I$6&"|1",'Quote Lines'!$M$3:$M$805,"Y")=0,"",SUMIFS('Quote Lines'!$L$3:$L$805,'Quote Lines'!$P$3:$P$805,$A29&"|"&I$6&"|1",'Quote Lines'!$M$3:$M$805,"Y")) -> 1 | AA29: =IF(ISNUMBER(G29),1+SUMPRODUCT(ISNUMBER($G29:$J29)*($G29:$J29<G29)),"") -> 3 | AB29: =IF(ISNUMBER(H29),1+SUMPRODUCT(ISNUMBER($G29:$J29)*($G29:$J29<H29)),"") -> 1 | AC29: =IF(ISNUMBER(I29),1+SUMPRODUCT(ISNUMBER($G29:$J29)*($G29:$J29<I29)),"") -> 2 | AD29: =IF(ISNUMBER(J29),1+SUMPRODUCT(ISNUMBER($G29:$J29)*($G29:$J29<J29)),"") | AE29: =IF(NOT(ISNUMBER(G29)),0,IF($S29<2,5,IF(AA29=1,1,IF(G29=MAX($G29:$J29),4,IF(AA29=2,2,3))))) -> 4 | AF29: =IF(NOT(ISNUMBER(H29)),0,IF($S29<2,5,IF(AB29=1,1,IF(H29=MAX($G29:$J29),4,IF(AB29=2,2,3))))) -> 1 | AG29: =IF(NOT(ISNUMBER(I29)),0,IF($S29<2,5,IF(AC29=1,1,IF(I29=MAX($G29:$J29),4,IF(AC29=2,2,3))))) -> 2 | AH29: =IF(NOT(ISNUMBER(J29)),0,IF($S29<2,5,IF(AD29=1,1,IF(J29=MAX($G29:$J29),4,IF(AD29=2,2,3))))) -> 0 | AI29: =IF($S29>=2,IF(ISNUMBER(G29),G29*$F29,MIN($G29:$J29)*$F29),0) -> 6622.86 | AJ29: =IF($S29>=2,IF(ISNUMBER(H29),H29*$F29,MIN($G29:$J29)*$F29),0) -> 4510.99 | AK29: =IF($S29>=2,IF(ISNUMBER(I29),I29*$F29,MIN($G29:$J29)*$F29),0) -> 5606.63 | AL29: =IF($S29>=2,IF(ISNUMBER(J29),J29*$F29,MIN($G29:$J29)*$F29),0) -> 4510.99 | AM29: =IF($S29>=2,$R29+ROW()/1000000,"") -> 2111.87 | AN29: =IF($S29>=2,MAX(G29:J29),"") -> 6622.86 | AO29: =IF($S29>=2,INDEX($G$6:$J$6,MATCH(MAX(G29:J29),G29:J29,0)),"") -> Ferguson | AP29: =IF($S29>=2,MIN(G29:J29)*$F29,0) -> 4510.99 | AQ29: =IF($S29>=2,INDEX($G$6:$J$6,MATCH(MIN(G29:J29),G29:J29,0)),"") -> HD Fowler
A30: R023 | B30: Item 5 | C30: DI spools | D30: 16" x 10'-0" flange x PE DI spool | E30: EA | F30: 1 | G30: =IF(COUNTIF('Quote Lines'!$P$3:$P$805,$A30&"|"&G$6&"|1")=0,"—",SUMIFS('Quote Lines'!$O$3:$O$805,'Quote Lines'!$P$3:$P$805,$A30&"|"&G$6&"|1")/SUMIFS('Quote Lines'!$L$3:$L$805,'Quote Lines'!$P$3:$P$805,$A30&"|"&G$6&"|1")) -> 3346.08 | H30: — | I30: — | J30: =IF(COUNTIF('Quote Lines'!$P$3:$P$805,$A30&"|"&J$6&"|1")=0,"—",SUMIFS('Quote Lines'!$O$3:$O$805,'Quote Lines'!$P$3:$P$805,$A30&"|"&J$6&"|1")/SUMIFS('Quote Lines'!$L$3:$L$805,'Quote Lines'!$P$3:$P$805,$A30&"|"&J$6&"|1")) -> 3911 | K30: =IF(ISNUMBER(G30),G30*$F30,"—") -> 3346.08 | L30: =IF(ISNUMBER(H30),H30*$F30,"—") -> — | M30: =IF(ISNUMBER(I30),I30*$F30,"—") -> — | N30: =IF(ISNUMBER(J30),J30*$F30,"—") -> 3911 | O30: =IF($S30=0,"—",MIN(G30:J30)) -> 3346.08 | P30: =IF($S30=0,"—",IF(COUNTIF(G30:J30,O30)>1,"Tie",INDEX($G$6:$J$6,MATCH(O30,G30:J30,0)))) -> Ferguson | Q30: =IF($S30>=2,MAX(G30:J30)/MIN(G30:J30)-1,"—") -> 0.16883039 | R30: =IF($S30>=2,(MAX(G30:J30)-MIN(G30:J30))*$F30,"—") -> 564.92 | S30: =COUNT(G30:J30) -> 2 | T30: =IF($S30<=1,IF($S30=1,"Single quote","—"),"Like-for-like") -> Like-for-like | U30: =IF(COUNT(W30:Z30)<2,"",IF(MAX(W30:Z30)=MIN(W30:Z30),"OK","Qty differs")) -> OK | W30: =IF(COUNTIFS('Quote Lines'!$P$3:$P$805,$A30&"|"&G$6&"|1",'Quote Lines'!$M$3:$M$805,"Y")=0,"",SUMIFS('Quote Lines'!$L$3:$L$805,'Quote Lines'!$P$3:$P$805,$A30&"|"&G$6&"|1",'Quote Lines'!$M$3:$M$805,"Y")) -> 1 | Z30: =IF(COUNTIFS('Quote Lines'!$P$3:$P$805,$A30&"|"&J$6&"|1",'Quote Lines'!$M$3:$M$805,"Y")=0,"",SUMIFS('Quote Lines'!$L$3:$L$805,'Quote Lines'!$P$3:$P$805,$A30&"|"&J$6&"|1",'Quote Lines'!$M$3:$M$805,"Y")) -> 1 | AA30: =IF(ISNUMBER(G30),1+SUMPRODUCT(ISNUMBER($G30:$J30)*($G30:$J30<G30)),"") -> 1 | AB30: =IF(ISNUMBER(H30),1+SUMPRODUCT(ISNUMBER($G30:$J30)*($G30:$J30<H30)),"") | AC30: =IF(ISNUMBER(I30),1+SUMPRODUCT(ISNUMBER($G30:$J30)*($G30:$J30<I30)),"") | AD30: =IF(ISNUMBER(J30),1+SUMPRODUCT(ISNUMBER($G30:$J30)*($G30:$J30<J30)),"") -> 2 | AE30: =IF(NOT(ISNUMBER(G30)),0,IF($S30<2,5,IF(AA30=1,1,IF(G30=MAX($G30:$J30),4,IF(AA30=2,2,3))))) -> 1 | AF30: =IF(NOT(ISNUMBER(H30)),0,IF($S30<2,5,IF(AB30=1,1,IF(H30=MAX($G30:$J30),4,IF(AB30=2,2,3))))) -> 0 | AG30: =IF(NOT(ISNUMBER(I30)),0,IF($S30<2,5,IF(AC30=1,1,IF(I30=MAX($G30:$J30),4,IF(AC30=2,2,3))))) -> 0 | AH30: =IF(NOT(ISNUMBER(J30)),0,IF($S30<2,5,IF(AD30=1,1,IF(J30=MAX($G30:$J30),4,IF(AD30=2,2,3))))) -> 4 | AI30: =IF($S30>=2,IF(ISNUMBER(G30),G30*$F30,MIN($G30:$J30)*$F30),0) -> 3346.08 | AJ30: =IF($S30>=2,IF(ISNUMBER(H30),H30*$F30,MIN($G30:$J30)*$F30),0) -> 3346.08 | AK30: =IF($S30>=2,IF(ISNUMBER(I30),I30*$F30,MIN($G30:$J30)*$F30),0) -> 3346.08 | AL30: =IF($S30>=2,IF(ISNUMBER(J30),J30*$F30,MIN($G30:$J30)*$F30),0) -> 3911 | AM30: =IF($S30>=2,$R30+ROW()/1000000,"") -> 564.92003 | AN30: =IF($S30>=2,MAX(G30:J30),"") -> 3911 | AO30: =IF($S30>=2,INDEX($G$6:$J$6,MATCH(MAX(G30:J30),G30:J30,0)),"") -> Scholzen | AP30: =IF($S30>=2,MIN(G30:J30)*$F30,0) -> 3346.08 | AQ30: =IF($S30>=2,INDEX($G$6:$J$6,MATCH(MIN(G30:J30),G30:J30,0)),"") -> Ferguson
A31: R024 | B31: Item 5 | C31: DI spools | D31: 16" x 9'-0" flange x PE DI spool | E31: EA | F31: 1 | G31: — | H31: — | I31: =IF(COUNTIF('Quote Lines'!$P$3:$P$805,$A31&"|"&I$6&"|1")=0,"—",SUMIFS('Quote Lines'!$O$3:$O$805,'Quote Lines'!$P$3:$P$805,$A31&"|"&I$6&"|1")/SUMIFS('Quote Lines'!$L$3:$L$805,'Quote Lines'!$P$3:$P$805,$A31&"|"&I$6&"|1")) -> 3696.36 | J31: — | K31: =IF(ISNUMBER(G31),G31*$F31,"—") -> — | L31: =IF(ISNUMBER(H31),H31*$F31,"—") -> — | M31: =IF(ISNUMBER(I31),I31*$F31,"—") -> 3696.36 | N31: =IF(ISNUMBER(J31),J31*$F31,"—") -> — | O31: =IF($S31=0,"—",MIN(G31:J31)) -> 3696.36 | P31: =IF($S31=0,"—",IF(COUNTIF(G31:J31,O31)>1,"Tie",INDEX($G$6:$J$6,MATCH(O31,G31:J31,0)))) -> Mountainland | Q31: =IF($S31>=2,MAX(G31:J31)/MIN(G31:J31)-1,"—") -> — | R31: =IF($S31>=2,(MAX(G31:J31)-MIN(G31:J31))*$F31,"—") -> — | S31: =COUNT(G31:J31) -> 1 | T31: =IF($S31<=1,IF($S31=1,"Single quote","—"),"Like-for-like") -> Single quote | U31: =IF(COUNT(W31:Z31)<2,"",IF(MAX(W31:Z31)=MIN(W31:Z31),"OK","Qty differs")) | Y31: =IF(COUNTIFS('Quote Lines'!$P$3:$P$805,$A31&"|"&I$6&"|1",'Quote Lines'!$M$3:$M$805,"Y")=0,"",SUMIFS('Quote Lines'!$L$3:$L$805,'Quote Lines'!$P$3:$P$805,$A31&"|"&I$6&"|1",'Quote Lines'!$M$3:$M$805,"Y")) -> 1 | AA31: =IF(ISNUMBER(G31),1+SUMPRODUCT(ISNUMBER($G31:$J31)*($G31:$J31<G31)),"") | AB31: =IF(ISNUMBER(H31),1+SUMPRODUCT(ISNUMBER($G31:$J31)*($G31:$J31<H31)),"") | AC31: =IF(ISNUMBER(I31),1+SUMPRODUCT(ISNUMBER($G31:$J31)*($G31:$J31<I31)),"") -> 1 | AD31: =IF(ISNUMBER(J31),1+SUMPRODUCT(ISNUMBER($G31:$J31)*($G31:$J31<J31)),"") | AE31: =IF(NOT(ISNUMBER(G31)),0,IF($S31<2,5,IF(AA31=1,1,IF(G31=MAX($G31:$J31),4,IF(AA31=2,2,3))))) -> 0 | AF31: =IF(NOT(ISNUMBER(H31)),0,IF($S31<2,5,IF(AB31=1,1,IF(H31=MAX($G31:$J31),4,IF(AB31=2,2,3))))) -> 0 | AG31: =IF(NOT(ISNUMBER(I31)),0,IF($S31<2,5,IF(AC31=1,1,IF(I31=MAX($G31:$J31),4,IF(AC31=2,2,3))))) -> 5 | AH31: =IF(NOT(ISNUMBER(J31)),0,IF($S31<2,5,IF(AD31=1,1,IF(J31=MAX($G31:$J31),4,IF(AD31=2,2,3))))) -> 0 | AI31: =IF($S31>=2,IF(ISNUMBER(G31),G31*$F31,MIN($G31:$J31)*$F31),0) -> 0 | AJ31: =IF($S31>=2,IF(ISNUMBER(H31),H31*$F31,MIN($G31:$J31)*$F31),0) -> 0 | AK31: =IF($S31>=2,IF(ISNUMBER(I31),I31*$F31,MIN($G31:$J31)*$F31),0) -> 0 | AL31: =IF($S31>=2,IF(ISNUMBER(J31),J31*$F31,MIN($G31:$J31)*$F31),0) -> 0 | AM31: =IF($S31>=2,$R31+ROW()/1000000,"") | AN31: =IF($S31>=2,MAX(G31:J31),"") | AO31: =IF($S31>=2,INDEX($G$6:$J$6,MATCH(MAX(G31:J31),G31:J31,0)),"") | AP31: =IF($S31>=2,MIN(G31:J31)*$F31,0) -> 0 | AQ31: =IF($S31>=2,INDEX($G$6:$J$6,MATCH(MIN(G31:J31),G31:J31,0)),"")
A32: R025 | B32: Item 5 | C32: DI spools | D32: 16" x 10'-6" flange x flange DI spool | E32: EA | F32: 1 | G32: — | H32: =IF(COUNTIF('Quote Lines'!$P$3:$P$805,$A32&"|"&H$6&"|1")=0,"—",SUMIFS('Quote Lines'!$O$3:$O$805,'Quote Lines'!$P$3:$P$805,$A32&"|"&H$6&"|1")/SUMIFS('Quote Lines'!$L$3:$L$805,'Quote Lines'!$P$3:$P$805,$A32&"|"&H$6&"|1")) -> 4005.49 | I32: — | J32: =IF(COUNTIF('Quote Lines'!$P$3:$P$805,$A32&"|"&J$6&"|1")=0,"—",SUMIFS('Quote Lines'!$O$3:$O$805,'Quote Lines'!$P$3:$P$805,$A32&"|"&J$6&"|1")/SUMIFS('Quote Lines'!$L$3:$L$805,'Quote Lines'!$P$3:$P$805,$A32&"|"&J$6&"|1")) -> 4848 | K32: =IF(ISNUMBER(G32),G32*$F32,"—") -> — | L32: =IF(ISNUMBER(H32),H32*$F32,"—") -> 4005.49 | M32: =IF(ISNUMBER(I32),I32*$F32,"—") -> — | N32: =IF(ISNUMBER(J32),J32*$F32,"—") -> 4848 | O32: =IF($S32=0,"—",MIN(G32:J32)) -> 4005.49 | P32: =IF($S32=0,"—",IF(COUNTIF(G32:J32,O32)>1,"Tie",INDEX($G$6:$J$6,MATCH(O32,G32:J32,0)))) -> HD Fowler | Q32: =IF($S32>=2,MAX(G32:J32)/MIN(G32:J32)-1,"—") -> 0.21033881 | R32: =IF($S32>=2,(MAX(G32:J32)-MIN(G32:J32))*$F32,"—") -> 842.51 | S32: =COUNT(G32:J32) -> 2 | T32: =IF($S32<=1,IF($S32=1,"Single quote","—"),"Like-for-like") -> Like-for-like | U32: =IF(COUNT(W32:Z32)<2,"",IF(MAX(W32:Z32)=MIN(W32:Z32),"OK","Qty differs")) -> OK | X32: =IF(COUNTIFS('Quote Lines'!$P$3:$P$805,$A32&"|"&H$6&"|1",'Quote Lines'!$M$3:$M$805,"Y")=0,"",SUMIFS('Quote Lines'!$L$3:$L$805,'Quote Lines'!$P$3:$P$805,$A32&"|"&H$6&"|1",'Quote Lines'!$M$3:$M$805,"Y")) -> 1 | Z32: =IF(COUNTIFS('Quote Lines'!$P$3:$P$805,$A32&"|"&J$6&"|1",'Quote Lines'!$M$3:$M$805,"Y")=0,"",SUMIFS('Quote Lines'!$L$3:$L$805,'Quote Lines'!$P$3:$P$805,$A32&"|"&J$6&"|1",'Quote Lines'!$M$3:$M$805,"Y")) -> 1 | AA32: =IF(ISNUMBER(G32),1+SUMPRODUCT(ISNUMBER($G32:$J32)*($G32:$J32<G32)),"") | AB32: =IF(ISNUMBER(H32),1+SUMPRODUCT(ISNUMBER($G32:$J32)*($G32:$J32<H32)),"") -> 1 | AC32: =IF(ISNUMBER(I32),1+SUMPRODUCT(ISNUMBER($G32:$J32)*($G32:$J32<I32)),"") | AD32: =IF(ISNUMBER(J32),1+SUMPRODUCT(ISNUMBER($G32:$J32)*($G32:$J32<J32)),"") -> 2 | AE32: =IF(NOT(ISNUMBER(G32)),0,IF($S32<2,5,IF(AA32=1,1,IF(G32=MAX($G32:$J32),4,IF(AA32=2,2,3))))) -> 0 | AF32: =IF(NOT(ISNUMBER(H32)),0,IF($S32<2,5,IF(AB32=1,1,IF(H32=MAX($G32:$J32),4,IF(AB32=2,2,3))))) -> 1 | AG32: =IF(NOT(ISNUMBER(I32)),0,IF($S32<2,5,IF(AC32=1,1,IF(I32=MAX($G32:$J32),4,IF(AC32=2,2,3))))) -> 0 | AH32: =IF(NOT(ISNUMBER(J32)),0,IF($S32<2,5,IF(AD32=1,1,IF(J32=MAX($G32:$J32),4,IF(AD32=2,2,3))))) -> 4 | AI32: =IF($S32>=2,IF(ISNUMBER(G32),G32*$F32,MIN($G32:$J32)*$F32),0) -> 4005.49 | AJ32: =IF($S32>=2,IF(ISNUMBER(H32),H32*$F32,MIN($G32:$J32)*$F32),0) -> 4005.49 | AK32: =IF($S32>=2,IF(ISNUMBER(I32),I32*$F32,MIN($G32:$J32)*$F32),0) -> 4005.49 | AL32: =IF($S32>=2,IF(ISNUMBER(J32),J32*$F32,MIN($G32:$J32)*$F32),0) -> 4848 | AM32: =IF($S32>=2,$R32+ROW()/1000000,"") -> 842.51003 | AN32: =IF($S32>=2,MAX(G32:J32),"") -> 4848 | AO32: =IF($S32>=2,INDEX($G$6:$J$6,MATCH(MAX(G32:J32),G32:J32,0)),"") -> Scholzen | AP32: =IF($S32>=2,MIN(G32:J32)*$F32,0) -> 4005.49 | AQ32: =IF($S32>=2,INDEX($G$6:$J$6,MATCH(MIN(G32:J32),G32:J32,0)),"") -> HD Fowler
A33: R026 | B33: Item 5 | C33: DI spools | D33: 16" x 5'-0" flange x flange DI spool | E33: EA | F33: 1 | G33: — | H33: — | I33: =IF(COUNTIF('Quote Lines'!$P$3:$P$805,$A33&"|"&I$6&"|1")=0,"—",SUMIFS('Quote Lines'!$O$3:$O$805,'Quote Lines'!$P$3:$P$805,$A33&"|"&I$6&"|1")/SUMIFS('Quote Lines'!$L$3:$L$805,'Quote Lines'!$P$3:$P$805,$A33&"|"&I$6&"|1")) -> 3214.93 | J33: — | K33: =IF(ISNUMBER(G33),G33*$F33,"—") -> — | L33: =IF(ISNUMBER(H33),H33*$F33,"—") -> — | M33: =IF(ISNUMBER(I33),I33*$F33,"—") -> 3214.93 | N33: =IF(ISNUMBER(J33),J33*$F33,"—") -> — | O33: =IF($S33=0,"—",MIN(G33:J33)) -> 3214.93 | P33: =IF($S33=0,"—",IF(COUNTIF(G33:J33,O33)>1,"Tie",INDEX($G$6:$J$6,MATCH(O33,G33:J33,0)))) -> Mountainland | Q33: =IF($S33>=2,MAX(G33:J33)/MIN(G33:J33)-1,"—") -> — | R33: =IF($S33>=2,(MAX(G33:J33)-MIN(G33:J33))*$F33,"—") -> — | S33: =COUNT(G33:J33) -> 1 | T33: =IF($S33<=1,IF($S33=1,"Single quote","—"),"Like-for-like") -> Single quote | U33: =IF(COUNT(W33:Z33)<2,"",IF(MAX(W33:Z33)=MIN(W33:Z33),"OK","Qty differs")) | Y33: =IF(COUNTIFS('Quote Lines'!$P$3:$P$805,$A33&"|"&I$6&"|1",'Quote Lines'!$M$3:$M$805,"Y")=0,"",SUMIFS('Quote Lines'!$L$3:$L$805,'Quote Lines'!$P$3:$P$805,$A33&"|"&I$6&"|1",'Quote Lines'!$M$3:$M$805,"Y")) -> 1 | AA33: =IF(ISNUMBER(G33),1+SUMPRODUCT(ISNUMBER($G33:$J33)*($G33:$J33<G33)),"") | AB33: =IF(ISNUMBER(H33),1+SUMPRODUCT(ISNUMBER($G33:$J33)*($G33:$J33<H33)),"") | AC33: =IF(ISNUMBER(I33),1+SUMPRODUCT(ISNUMBER($G33:$J33)*($G33:$J33<I33)),"") -> 1 | AD33: =IF(ISNUMBER(J33),1+SUMPRODUCT(ISNUMBER($G33:$J33)*($G33:$J33<J33)),"") | AE33: =IF(NOT(ISNUMBER(G33)),0,IF($S33<2,5,IF(AA33=1,1,IF(G33=MAX($G33:$J33),4,IF(AA33=2,2,3))))) -> 0 | AF33: =IF(NOT(ISNUMBER(H33)),0,IF($S33<2,5,IF(AB33=1,1,IF(H33=MAX($G33:$J33),4,IF(AB33=2,2,3))))) -> 0 | AG33: =IF(NOT(ISNUMBER(I33)),0,IF($S33<2,5,IF(AC33=1,1,IF(I33=MAX($G33:$J33),4,IF(AC33=2,2,3))))) -> 5 | AH33: =IF(NOT(ISNUMBER(J33)),0,IF($S33<2,5,IF(AD33=1,1,IF(J33=MAX($G33:$J33),4,IF(AD33=2,2,3))))) -> 0 | AI33: =IF($S33>=2,IF(ISNUMBER(G33),G33*$F33,MIN($G33:$J33)*$F33),0) -> 0 | AJ33: =IF($S33>=2,IF(ISNUMBER(H33),H33*$F33,MIN($G33:$J33)*$F33),0) -> 0 | AK33: =IF($S33>=2,IF(ISNUMBER(I33),I33*$F33,MIN($G33:$J33)*$F33),0) -> 0 | AL33: =IF($S33>=2,IF(ISNUMBER(J33),J33*$F33,MIN($G33:$J33)*$F33),0) -> 0 | AM33: =IF($S33>=2,$R33+ROW()/1000000,"") | AN33: =IF($S33>=2,MAX(G33:J33),"") | AO33: =IF($S33>=2,INDEX($G$6:$J$6,MATCH(MAX(G33:J33),G33:J33,0)),"") | AP33: =IF($S33>=2,MIN(G33:J33)*$F33,0) -> 0 | AQ33: =IF($S33>=2,INDEX($G$6:$J$6,MATCH(MIN(G33:J33),G33:J33,0)),"")
A34: R027 | B34: Item 5 | C34: DI spools | D34: 16" x 4'-0" flange x flange DI spool | E34: EA | F34: 2 | G34: — | H34: =IF(COUNTIF('Quote Lines'!$P$3:$P$805,$A34&"|"&H$6&"|1")=0,"—",SUMIFS('Quote Lines'!$O$3:$O$805,'Quote Lines'!$P$3:$P$805,$A34&"|"&H$6&"|1")/SUMIFS('Quote Lines'!$L$3:$L$805,'Quote Lines'!$P$3:$P$805,$A34&"|"&H$6&"|1")) -> 2341.76 | I34: =IF(COUNTIF('Quote Lines'!$P$3:$P$805,$A34&"|"&I$6&"|1")=0,"—",SUMIFS('Quote Lines'!$O$3:$O$805,'Quote Lines'!$P$3:$P$805,$A34&"|"&I$6&"|1")/SUMIFS('Quote Lines'!$L$3:$L$805,'Quote Lines'!$P$3:$P$805,$A34&"|"&I$6&"|1")) -> 2908.55 | J34: — | K34: =IF(ISNUMBER(G34),G34*$F34,"—") -> — | L34: =IF(ISNUMBER(H34),H34*$F34,"—") -> 4683.52 | M34: =IF(ISNUMBER(I34),I34*$F34,"—") -> 5817.1 | N34: =IF(ISNUMBER(J34),J34*$F34,"—") -> — | O34: =IF($S34=0,"—",MIN(G34:J34)) -> 2341.76 | P34: =IF($S34=0,"—",IF(COUNTIF(G34:J34,O34)>1,"Tie",INDEX($G$6:$J$6,MATCH(O34,G34:J34,0)))) -> HD Fowler | Q34: =IF($S34>=2,MAX(G34:J34)/MIN(G34:J34)-1,"—") -> 0.2420359 | R34: =IF($S34>=2,(MAX(G34:J34)-MIN(G34:J34))*$F34,"—") -> 1133.58 | S34: =COUNT(G34:J34) -> 2 | T34: =IF($S34<=1,IF($S34=1,"Single quote","—"),"Like-for-like") -> Like-for-like | U34: =IF(COUNT(W34:Z34)<2,"",IF(MAX(W34:Z34)=MIN(W34:Z34),"OK","Qty differs")) -> Qty differs | X34: =IF(COUNTIFS('Quote Lines'!$P$3:$P$805,$A34&"|"&H$6&"|1",'Quote Lines'!$M$3:$M$805,"Y")=0,"",SUMIFS('Quote Lines'!$L$3:$L$805,'Quote Lines'!$P$3:$P$805,$A34&"|"&H$6&"|1",'Quote Lines'!$M$3:$M$805,"Y")) -> 2 | Y34: =IF(COUNTIFS('Quote Lines'!$P$3:$P$805,$A34&"|"&I$6&"|1",'Quote Lines'!$M$3:$M$805,"Y")=0,"",SUMIFS('Quote Lines'!$L$3:$L$805,'Quote Lines'!$P$3:$P$805,$A34&"|"&I$6&"|1",'Quote Lines'!$M$3:$M$805,"Y")) -> 1 | AA34: =IF(ISNUMBER(G34),1+SUMPRODUCT(ISNUMBER($G34:$J34)*($G34:$J34<G34)),"") | AB34: =IF(ISNUMBER(H34),1+SUMPRODUCT(ISNUMBER($G34:$J34)*($G34:$J34<H34)),"") -> 1 | AC34: =IF(ISNUMBER(I34),1+SUMPRODUCT(ISNUMBER($G34:$J34)*($G34:$J34<I34)),"") -> 2 | AD34: =IF(ISNUMBER(J34),1+SUMPRODUCT(ISNUMBER($G34:$J34)*($G34:$J34<J34)),"") | AE34: =IF(NOT(ISNUMBER(G34)),0,IF($S34<2,5,IF(AA34=1,1,IF(G34=MAX($G34:$J34),4,IF(AA34=2,2,3))))) -> 0 | AF34: =IF(NOT(ISNUMBER(H34)),0,IF($S34<2,5,IF(AB34=1,1,IF(H34=MAX($G34:$J34),4,IF(AB34=2,2,3))))) -> 1 | AG34: =IF(NOT(ISNUMBER(I34)),0,IF($S34<2,5,IF(AC34=1,1,IF(I34=MAX($G34:$J34),4,IF(AC34=2,2,3))))) -> 4 | AH34: =IF(NOT(ISNUMBER(J34)),0,IF($S34<2,5,IF(AD34=1,1,IF(J34=MAX($G34:$J34),4,IF(AD34=2,2,3))))) -> 0 | AI34: =IF($S34>=2,IF(ISNUMBER(G34),G34*$F34,MIN($G34:$J34)*$F34),0) -> 4683.52 | AJ34: =IF($S34>=2,IF(ISNUMBER(H34),H34*$F34,MIN($G34:$J34)*$F34),0) -> 4683.52 | AK34: =IF($S34>=2,IF(ISNUMBER(I34),I34*$F34,MIN($G34:$J34)*$F34),0) -> 5817.1 | AL34: =IF($S34>=2,IF(ISNUMBER(J34),J34*$F34,MIN($G34:$J34)*$F34),0) -> 4683.52 | AM34: =IF($S34>=2,$R34+ROW()/1000000,"") -> 1133.58 | AN34: =IF($S34>=2,MAX(G34:J34),"") -> 2908.55 | AO34: =IF($S34>=2,INDEX($G$6:$J$6,MATCH(MAX(G34:J34),G34:J34,0)),"") -> Mountainland | AP34: =IF($S34>=2,MIN(G34:J34)*$F34,0) -> 4683.52 | AQ34: =IF($S34>=2,INDEX($G$6:$J$6,MATCH(MIN(G34:J34),G34:J34,0)),"") -> HD Fowler
A35: R028 | B35: Item 5 | C35: DI spools | D35: 16" x 3'-6" flange x flange DI spool | E35: EA | F35: 2 | G35: =IF(COUNTIF('Quote Lines'!$P$3:$P$805,$A35&"|"&G$6&"|1")=0,"—",SUMIFS('Quote Lines'!$O$3:$O$805,'Quote Lines'!$P$3:$P$805,$A35&"|"&G$6&"|1")/SUMIFS('Quote Lines'!$L$3:$L$805,'Quote Lines'!$P$3:$P$805,$A35&"|"&G$6&"|1")) -> 2746.33 | H35: — | I35: — | J35: — | K35: =IF(ISNUMBER(G35),G35*$F35,"—") -> 5492.66 | L35: =IF(ISNUMBER(H35),H35*$F35,"—") -> — | M35: =IF(ISNUMBER(I35),I35*$F35,"—") -> — | N35: =IF(ISNUMBER(J35),J35*$F35,"—") -> — | O35: =IF($S35=0,"—",MIN(G35:J35)) -> 2746.33 | P35: =IF($S35=0,"—",IF(COUNTIF(G35:J35,O35)>1,"Tie",INDEX($G$6:$J$6,MATCH(O35,G35:J35,0)))) -> Ferguson | Q35: =IF($S35>=2,MAX(G35:J35)/MIN(G35:J35)-1,"—") -> — | R35: =IF($S35>=2,(MAX(G35:J35)-MIN(G35:J35))*$F35,"—") -> — | S35: =COUNT(G35:J35) -> 1 | T35: =IF($S35<=1,IF($S35=1,"Single quote","—"),"Like-for-like") -> Single quote | U35: =IF(COUNT(W35:Z35)<2,"",IF(MAX(W35:Z35)=MIN(W35:Z35),"OK","Qty differs")) | W35: =IF(COUNTIFS('Quote Lines'!$P$3:$P$805,$A35&"|"&G$6&"|1",'Quote Lines'!$M$3:$M$805,"Y")=0,"",SUMIFS('Quote Lines'!$L$3:$L$805,'Quote Lines'!$P$3:$P$805,$A35&"|"&G$6&"|1",'Quote Lines'!$M$3:$M$805,"Y")) -> 2 | AA35: =IF(ISNUMBER(G35),1+SUMPRODUCT(ISNUMBER($G35:$J35)*($G35:$J35<G35)),"") -> 1 | AB35: =IF(ISNUMBER(H35),1+SUMPRODUCT(ISNUMBER($G35:$J35)*($G35:$J35<H35)),"") | AC35: =IF(ISNUMBER(I35),1+SUMPRODUCT(ISNUMBER($G35:$J35)*($G35:$J35<I35)),"") | AD35: =IF(ISNUMBER(J35),1+SUMPRODUCT(ISNUMBER($G35:$J35)*($G35:$J35<J35)),"") | AE35: =IF(NOT(ISNUMBER(G35)),0,IF($S35<2,5,IF(AA35=1,1,IF(G35=MAX($G35:$J35),4,IF(AA35=2,2,3))))) -> 5 | AF35: =IF(NOT(ISNUMBER(H35)),0,IF($S35<2,5,IF(AB35=1,1,IF(H35=MAX($G35:$J35),4,IF(AB35=2,2,3))))) -> 0 | AG35: =IF(NOT(ISNUMBER(I35)),0,IF($S35<2,5,IF(AC35=1,1,IF(I35=MAX($G35:$J35),4,IF(AC35=2,2,3))))) -> 0 | AH35: =IF(NOT(ISNUMBER(J35)),0,IF($S35<2,5,IF(AD35=1,1,IF(J35=MAX($G35:$J35),4,IF(AD35=2,2,3))))) -> 0 | AI35: =IF($S35>=2,IF(ISNUMBER(G35),G35*$F35,MIN($G35:$J35)*$F35),0) -> 0 | AJ35: =IF($S35>=2,IF(ISNUMBER(H35),H35*$F35,MIN($G35:$J35)*$F35),0) -> 0 | AK35: =IF($S35>=2,IF(ISNUMBER(I35),I35*$F35,MIN($G35:$J35)*$F35),0) -> 0 | AL35: =IF($S35>=2,IF(ISNUMBER(J35),J35*$F35,MIN($G35:$J35)*$F35),0) -> 0 | AM35: =IF($S35>=2,$R35+ROW()/1000000,"") | AN35: =IF($S35>=2,MAX(G35:J35),"") | AO35: =IF($S35>=2,INDEX($G$6:$J$6,MATCH(MAX(G35:J35),G35:J35,0)),"") | AP35: =IF($S35>=2,MIN(G35:J35)*$F35,0) -> 0 | AQ35: =IF($S35>=2,INDEX($G$6:$J$6,MATCH(MIN(G35:J35),G35:J35,0)),"")
A36: R029 | B36: Item 5 | C36: DI spools | D36: 10" x 4'-6" flange x flange DI spool | E36: EA | F36: 2 | G36: =IF(COUNTIF('Quote Lines'!$P$3:$P$805,$A36&"|"&G$6&"|1")=0,"—",SUMIFS('Quote Lines'!$O$3:$O$805,'Quote Lines'!$P$3:$P$805,$A36&"|"&G$6&"|1")/SUMIFS('Quote Lines'!$L$3:$L$805,'Quote Lines'!$P$3:$P$805,$A36&"|"&G$6&"|1")) -> 1566.1 | H36: =IF(COUNTIF('Quote Lines'!$P$3:$P$805,$A36&"|"&H$6&"|1")=0,"—",SUMIFS('Quote Lines'!$O$3:$O$805,'Quote Lines'!$P$3:$P$805,$A36&"|"&H$6&"|1")/SUMIFS('Quote Lines'!$L$3:$L$805,'Quote Lines'!$P$3:$P$805,$A36&"|"&H$6&"|1")) -> 1162.64 | I36: — | J36: =IF(COUNTIF('Quote Lines'!$P$3:$P$805,$A36&"|"&J$6&"|1")=0,"—",SUMIFS('Quote Lines'!$O$3:$O$805,'Quote Lines'!$P$3:$P$805,$A36&"|"&J$6&"|1")/SUMIFS('Quote Lines'!$L$3:$L$805,'Quote Lines'!$P$3:$P$805,$A36&"|"&J$6&"|1")) -> 1412 | K36: =IF(ISNUMBER(G36),G36*$F36,"—") -> 3132.2 | L36: =IF(ISNUMBER(H36),H36*$F36,"—") -> 2325.28 | M36: =IF(ISNUMBER(I36),I36*$F36,"—") -> — | N36: =IF(ISNUMBER(J36),J36*$F36,"—") -> 2824 | O36: =IF($S36=0,"—",MIN(G36:J36)) -> 1162.64 | P36: =IF($S36=0,"—",IF(COUNTIF(G36:J36,O36)>1,"Tie",INDEX($G$6:$J$6,MATCH(O36,G36:J36,0)))) -> HD Fowler | Q36: =IF($S36>=2,MAX(G36:J36)/MIN(G36:J36)-1,"—") -> 0.34702057 | R36: =IF($S36>=2,(MAX(G36:J36)-MIN(G36:J36))*$F36,"—") -> 806.92 | S36: =COUNT(G36:J36) -> 3 | T36: =IF($S36<=1,IF($S36=1,"Single quote","—"),"Like-for-like") -> Like-for-like | U36: =IF(COUNT(W36:Z36)<2,"",IF(MAX(W36:Z36)=MIN(W36:Z36),"OK","Qty differs")) -> Qty differs | W36: =IF(COUNTIFS('Quote Lines'!$P$3:$P$805,$A36&"|"&G$6&"|1",'Quote Lines'!$M$3:$M$805,"Y")=0,"",SUMIFS('Quote Lines'!$L$3:$L$805,'Quote Lines'!$P$3:$P$805,$A36&"|"&G$6&"|1",'Quote Lines'!$M$3:$M$805,"Y")) -> 2 | X36: =IF(COUNTIFS('Quote Lines'!$P$3:$P$805,$A36&"|"&H$6&"|1",'Quote Lines'!$M$3:$M$805,"Y")=0,"",SUMIFS('Quote Lines'!$L$3:$L$805,'Quote Lines'!$P$3:$P$805,$A36&"|"&H$6&"|1",'Quote Lines'!$M$3:$M$805,"Y")) -> 2 | Z36: =IF(COUNTIFS('Quote Lines'!$P$3:$P$805,$A36&"|"&J$6&"|1",'Quote Lines'!$M$3:$M$805,"Y")=0,"",SUMIFS('Quote Lines'!$L$3:$L$805,'Quote Lines'!$P$3:$P$805,$A36&"|"&J$6&"|1",'Quote Lines'!$M$3:$M$805,"Y")) -> 1 | AA36: =IF(ISNUMBER(G36),1+SUMPRODUCT(ISNUMBER($G36:$J36)*($G36:$J36<G36)),"") -> 3 | AB36: =IF(ISNUMBER(H36),1+SUMPRODUCT(ISNUMBER($G36:$J36)*($G36:$J36<H36)),"") -> 1 | AC36: =IF(ISNUMBER(I36),1+SUMPRODUCT(ISNUMBER($G36:$J36)*($G36:$J36<I36)),"") | AD36: =IF(ISNUMBER(J36),1+SUMPRODUCT(ISNUMBER($G36:$J36)*($G36:$J36<J36)),"") -> 2 | AE36: =IF(NOT(ISNUMBER(G36)),0,IF($S36<2,5,IF(AA36=1,1,IF(G36=MAX($G36:$J36),4,IF(AA36=2,2,3))))) -> 4 | AF36: =IF(NOT(ISNUMBER(H36)),0,IF($S36<2,5,IF(AB36=1,1,IF(H36=MAX($G36:$J36),4,IF(AB36=2,2,3))))) -> 1 | AG36: =IF(NOT(ISNUMBER(I36)),0,IF($S36<2,5,IF(AC36=1,1,IF(I36=MAX($G36:$J36),4,IF(AC36=2,2,3))))) -> 0 | AH36: =IF(NOT(ISNUMBER(J36)),0,IF($S36<2,5,IF(AD36=1,1,IF(J36=MAX($G36:$J36),4,IF(AD36=2,2,3))))) -> 2 | AI36: =IF($S36>=2,IF(ISNUMBER(G36),G36*$F36,MIN($G36:$J36)*$F36),0) -> 3132.2 | AJ36: =IF($S36>=2,IF(ISNUMBER(H36),H36*$F36,MIN($G36:$J36)*$F36),0) -> 2325.28 | AK36: =IF($S36>=2,IF(ISNUMBER(I36),I36*$F36,MIN($G36:$J36)*$F36),0) -> 2325.28 | AL36: =IF($S36>=2,IF(ISNUMBER(J36),J36*$F36,MIN($G36:$J36)*$F36),0) -> 2824 | AM36: =IF($S36>=2,$R36+ROW()/1000000,"") -> 806.92004 | AN36: =IF($S36>=2,MAX(G36:J36),"") -> 1566.1 | AO36: =IF($S36>=2,INDEX($G$6:$J$6,MATCH(MAX(G36:J36),G36:J36,0)),"") -> Ferguson | AP36: =IF($S36>=2,MIN(G36:J36)*$F36,0) -> 2325.28 | AQ36: =IF($S36>=2,INDEX($G$6:$J$6,MATCH(MIN(G36:J36),G36:J36,0)),"") -> HD Fowler
A37: R030 | B37: Item 5 | C37: DI spools | D37: 10" x 2'-0" flange x flange DI spool | E37: EA | F37: 2 | G37: =IF(COUNTIF('Quote Lines'!$P$3:$P$805,$A37&"|"&G$6&"|1")=0,"—",SUMIFS('Quote Lines'!$O$3:$O$805,'Quote Lines'!$P$3:$P$805,$A37&"|"&G$6&"|1")/SUMIFS('Quote Lines'!$L$3:$L$805,'Quote Lines'!$P$3:$P$805,$A37&"|"&G$6&"|1")) -> 1007.84 | H37: =IF(COUNTIF('Quote Lines'!$P$3:$P$805,$A37&"|"&H$6&"|1")=0,"—",SUMIFS('Quote Lines'!$O$3:$O$805,'Quote Lines'!$P$3:$P$805,$A37&"|"&H$6&"|1")/SUMIFS('Quote Lines'!$L$3:$L$805,'Quote Lines'!$P$3:$P$805,$A37&"|"&H$6&"|1")) -> 817.58 | I37: — | J37: — | K37: =IF(ISNUMBER(G37),G37*$F37,"—") -> 2015.68 | L37: =IF(ISNUMBER(H37),H37*$F37,"—") -> 1635.16 | M37: =IF(ISNUMBER(I37),I37*$F37,"—") -> — | N37: =IF(ISNUMBER(J37),J37*$F37,"—") -> — | O37: =IF($S37=0,"—",MIN(G37:J37)) -> 817.58 | P37: =IF($S37=0,"—",IF(COUNTIF(G37:J37,O37)>1,"Tie",INDEX($G$6:$J$6,MATCH(O37,G37:J37,0)))) -> HD Fowler | Q37: =IF($S37>=2,MAX(G37:J37)/MIN(G37:J37)-1,"—") -> 0.23271117 | R37: =IF($S37>=2,(MAX(G37:J37)-MIN(G37:J37))*$F37,"—") -> 380.52 | S37: =COUNT(G37:J37) -> 2 | T37: =IF($S37<=1,IF($S37=1,"Single quote","—"),"Like-for-like") -> Like-for-like | U37: =IF(COUNT(W37:Z37)<2,"",IF(MAX(W37:Z37)=MIN(W37:Z37),"OK","Qty differs")) -> OK | W37: =IF(COUNTIFS('Quote Lines'!$P$3:$P$805,$A37&"|"&G$6&"|1",'Quote Lines'!$M$3:$M$805,"Y")=0,"",SUMIFS('Quote Lines'!$L$3:$L$805,'Quote Lines'!$P$3:$P$805,$A37&"|"&G$6&"|1",'Quote Lines'!$M$3:$M$805,"Y")) -> 2 | X37: =IF(COUNTIFS('Quote Lines'!$P$3:$P$805,$A37&"|"&H$6&"|1",'Quote Lines'!$M$3:$M$805,"Y")=0,"",SUMIFS('Quote Lines'!$L$3:$L$805,'Quote Lines'!$P$3:$P$805,$A37&"|"&H$6&"|1",'Quote Lines'!$M$3:$M$805,"Y")) -> 2 | AA37: =IF(ISNUMBER(G37),1+SUMPRODUCT(ISNUMBER($G37:$J37)*($G37:$J37<G37)),"") -> 2 | AB37: =IF(ISNUMBER(H37),1+SUMPRODUCT(ISNUMBER($G37:$J37)*($G37:$J37<H37)),"") -> 1 | AC37: =IF(ISNUMBER(I37),1+SUMPRODUCT(ISNUMBER($G37:$J37)*($G37:$J37<I37)),"") | AD37: =IF(ISNUMBER(J37),1+SUMPRODUCT(ISNUMBER($G37:$J37)*($G37:$J37<J37)),"") | AE37: =IF(NOT(ISNUMBER(G37)),0,IF($S37<2,5,IF(AA37=1,1,IF(G37=MAX($G37:$J37),4,IF(AA37=2,2,3))))) -> 4 | AF37: =IF(NOT(ISNUMBER(H37)),0,IF($S37<2,5,IF(AB37=1,1,IF(H37=MAX($G37:$J37),4,IF(AB37=2,2,3))))) -> 1 | AG37: =IF(NOT(ISNUMBER(I37)),0,IF($S37<2,5,IF(AC37=1,1,IF(I37=MAX($G37:$J37),4,IF(AC37=2,2,3))))) -> 0 | AH37: =IF(NOT(ISNUMBER(J37)),0,IF($S37<2,5,IF(AD37=1,1,IF(J37=MAX($G37:$J37),4,IF(AD37=2,2,3))))) -> 0 | AI37: =IF($S37>=2,IF(ISNUMBER(G37),G37*$F37,MIN($G37:$J37)*$F37),0) -> 2015.68 | AJ37: =IF($S37>=2,IF(ISNUMBER(H37),H37*$F37,MIN($G37:$J37)*$F37),0) -> 1635.16 | AK37: =IF($S37>=2,IF(ISNUMBER(I37),I37*$F37,MIN($G37:$J37)*$F37),0) -> 1635.16 | AL37: =IF($S37>=2,IF(ISNUMBER(J37),J37*$F37,MIN($G37:$J37)*$F37),0) -> 1635.16 | AM37: =IF($S37>=2,$R37+ROW()/1000000,"") -> 380.52004 | AN37: =IF($S37>=2,MAX(G37:J37),"") -> 1007.84 | AO37: =IF($S37>=2,INDEX($G$6:$J$6,MATCH(MAX(G37:J37),G37:J37,0)),"") -> Ferguson | AP37: =IF($S37>=2,MIN(G37:J37)*$F37,0) -> 1635.16 | AQ37: =IF($S37>=2,INDEX($G$6:$J$6,MATCH(MIN(G37:J37),G37:J37,0)),"") -> HD Fowler
A38: R031 | B38: Item 5 | C38: DI spools | D38: 10" x 2'-10" flange x flange DI spool | E38: EA | F38: 2 | G38: — | H38: — | I38: — | J38: =IF(COUNTIF('Quote Lines'!$P$3:$P$805,$A38&"|"&J$6&"|1")=0,"—",SUMIFS('Quote Lines'!$O$3:$O$805,'Quote Lines'!$P$3:$P$805,$A38&"|"&J$6&"|1")/SUMIFS('Quote Lines'!$L$3:$L$805,'Quote Lines'!$P$3:$P$805,$A38&"|"&J$6&"|1")) -> 1160 | K38: =IF(ISNUMBER(G38),G38*$F38,"—") -> — | L38: =IF(ISNUMBER(H38),H38*$F38,"—") -> — | M38: =IF(ISNUMBER(I38),I38*$F38,"—") -> — | N38: =IF(ISNUMBER(J38),J38*$F38,"—") -> 2320 | O38: =IF($S38=0,"—",MIN(G38:J38)) -> 1160 | P38: =IF($S38=0,"—",IF(COUNTIF(G38:J38,O38)>1,"Tie",INDEX($G$6:$J$6,MATCH(O38,G38:J38,0)))) -> Scholzen | Q38: =IF($S38>=2,MAX(G38:J38)/MIN(G38:J38)-1,"—") -> — | R38: =IF($S38>=2,(MAX(G38:J38)-MIN(G38:J38))*$F38,"—") -> — | S38: =COUNT(G38:J38) -> 1 | T38: =IF($S38<=1,IF($S38=1,"Single quote","—"),"Like-for-like") -> Single quote | U38: =IF(COUNT(W38:Z38)<2,"",IF(MAX(W38:Z38)=MIN(W38:Z38),"OK","Qty differs")) | Z38: =IF(COUNTIFS('Quote Lines'!$P$3:$P$805,$A38&"|"&J$6&"|1",'Quote Lines'!$M$3:$M$805,"Y")=0,"",SUMIFS('Quote Lines'!$L$3:$L$805,'Quote Lines'!$P$3:$P$805,$A38&"|"&J$6&"|1",'Quote Lines'!$M$3:$M$805,"Y")) -> 2 | AA38: =IF(ISNUMBER(G38),1+SUMPRODUCT(ISNUMBER($G38:$J38)*($G38:$J38<G38)),"") | AB38: =IF(ISNUMBER(H38),1+SUMPRODUCT(ISNUMBER($G38:$J38)*($G38:$J38<H38)),"") | AC38: =IF(ISNUMBER(I38),1+SUMPRODUCT(ISNUMBER($G38:$J38)*($G38:$J38<I38)),"") | AD38: =IF(ISNUMBER(J38),1+SUMPRODUCT(ISNUMBER($G38:$J38)*($G38:$J38<J38)),"") -> 1 | AE38: =IF(NOT(ISNUMBER(G38)),0,IF($S38<2,5,IF(AA38=1,1,IF(G38=MAX($G38:$J38),4,IF(AA38=2,2,3))))) -> 0 | AF38: =IF(NOT(ISNUMBER(H38)),0,IF($S38<2,5,IF(AB38=1,1,IF(H38=MAX($G38:$J38),4,IF(AB38=2,2,3))))) -> 0 | AG38: =IF(NOT(ISNUMBER(I38)),0,IF($S38<2,5,IF(AC38=1,1,IF(I38=MAX($G38:$J38),4,IF(AC38=2,2,3))))) -> 0 | AH38: =IF(NOT(ISNUMBER(J38)),0,IF($S38<2,5,IF(AD38=1,1,IF(J38=MAX($G38:$J38),4,IF(AD38=2,2,3))))) -> 5 | AI38: =IF($S38>=2,IF(ISNUMBER(G38),G38*$F38,MIN($G38:$J38)*$F38),0) -> 0 | AJ38: =IF($S38>=2,IF(ISNUMBER(H38),H38*$F38,MIN($G38:$J38)*$F38),0) -> 0 | AK38: =IF($S38>=2,IF(ISNUMBER(I38),I38*$F38,MIN($G38:$J38)*$F38),0) -> 0 | AL38: =IF($S38>=2,IF(ISNUMBER(J38),J38*$F38,MIN($G38:$J38)*$F38),0) -> 0 | AM38: =IF($S38>=2,$R38+ROW()/1000000,"") | AN38: =IF($S38>=2,MAX(G38:J38),"") | AO38: =IF($S38>=2,INDEX($G$6:$J$6,MATCH(MAX(G38:J38),G38:J38,0)),"") | AP38: =IF($S38>=2,MIN(G38:J38)*$F38,0) -> 0 | AQ38: =IF($S38>=2,INDEX($G$6:$J$6,MATCH(MIN(G38:J38),G38:J38,0)),"")
A39: R032 | B39: Item 5 | C39: DI spools | D39: 10" x 1'-0" flange x flange DI spool | E39: EA | F39: 2 | G39: — | H39: — | I39: =IF(COUNTIF('Quote Lines'!$P$3:$P$805,$A39&"|"&I$6&"|1")=0,"—",SUMIFS('Quote Lines'!$O$3:$O$805,'Quote Lines'!$P$3:$P$805,$A39&"|"&I$6&"|1")/SUMIFS('Quote Lines'!$L$3:$L$805,'Quote Lines'!$P$3:$P$805,$A39&"|"&I$6&"|1")) -> 845.975 | J39: — | K39: =IF(ISNUMBER(G39),G39*$F39,"—") -> — | L39: =IF(ISNUMBER(H39),H39*$F39,"—") -> — | M39: =IF(ISNUMBER(I39),I39*$F39,"—") -> 1691.95 | N39: =IF(ISNUMBER(J39),J39*$F39,"—") -> — | O39: =IF($S39=0,"—",MIN(G39:J39)) -> 845.975 | P39: =IF($S39=0,"—",IF(COUNTIF(G39:J39,O39)>1,"Tie",INDEX($G$6:$J$6,MATCH(O39,G39:J39,0)))) -> Mountainland | Q39: =IF($S39>=2,MAX(G39:J39)/MIN(G39:J39)-1,"—") -> — | R39: =IF($S39>=2,(MAX(G39:J39)-MIN(G39:J39))*$F39,"—") -> — | S39: =COUNT(G39:J39) -> 1 | T39: =IF($S39<=1,IF($S39=1,"Single quote","—"),"Like-for-like") -> Single quote | U39: =IF(COUNT(W39:Z39)<2,"",IF(MAX(W39:Z39)=MIN(W39:Z39),"OK","Qty differs")) | Y39: =IF(COUNTIFS('Quote Lines'!$P$3:$P$805,$A39&"|"&I$6&"|1",'Quote Lines'!$M$3:$M$805,"Y")=0,"",SUMIFS('Quote Lines'!$L$3:$L$805,'Quote Lines'!$P$3:$P$805,$A39&"|"&I$6&"|1",'Quote Lines'!$M$3:$M$805,"Y")) -> 2 | AA39: =IF(ISNUMBER(G39),1+SUMPRODUCT(ISNUMBER($G39:$J39)*($G39:$J39<G39)),"") | AB39: =IF(ISNUMBER(H39),1+SUMPRODUCT(ISNUMBER($G39:$J39)*($G39:$J39<H39)),"") | AC39: =IF(ISNUMBER(I39),1+SUMPRODUCT(ISNUMBER($G39:$J39)*($G39:$J39<I39)),"") -> 1 | AD39: =IF(ISNUMBER(J39),1+SUMPRODUCT(ISNUMBER($G39:$J39)*($G39:$J39<J39)),"") | AE39: =IF(NOT(ISNUMBER(G39)),0,IF($S39<2,5,IF(AA39=1,1,IF(G39=MAX($G39:$J39),4,IF(AA39=2,2,3))))) -> 0 | AF39: =IF(NOT(ISNUMBER(H39)),0,IF($S39<2,5,IF(AB39=1,1,IF(H39=MAX($G39:$J39),4,IF(AB39=2,2,3))))) -> 0 | AG39: =IF(NOT(ISNUMBER(I39)),0,IF($S39<2,5,IF(AC39=1,1,IF(I39=MAX($G39:$J39),4,IF(AC39=2,2,3))))) -> 5 | AH39: =IF(NOT(ISNUMBER(J39)),0,IF($S39<2,5,IF(AD39=1,1,IF(J39=MAX($G39:$J39),4,IF(AD39=2,2,3))))) -> 0 | AI39: =IF($S39>=2,IF(ISNUMBER(G39),G39*$F39,MIN($G39:$J39)*$F39),0) -> 0 | AJ39: =IF($S39>=2,IF(ISNUMBER(H39),H39*$F39,MIN($G39:$J39)*$F39),0) -> 0 | AK39: =IF($S39>=2,IF(ISNUMBER(I39),I39*$F39,MIN($G39:$J39)*$F39),0) -> 0 | AL39: =IF($S39>=2,IF(ISNUMBER(J39),J39*$F39,MIN($G39:$J39)*$F39),0) -> 0 | AM39: =IF($S39>=2,$R39+ROW()/1000000,"") | AN39: =IF($S39>=2,MAX(G39:J39),"") | AO39: =IF($S39>=2,INDEX($G$6:$J$6,MATCH(MAX(G39:J39),G39:J39,0)),"") | AP39: =IF($S39>=2,MIN(G39:J39)*$F39,0) -> 0 | AQ39: =IF($S39>=2,INDEX($G$6:$J$6,MATCH(MIN(G39:J39),G39:J39,0)),"")
A40: R033 | B40: Item 5 | C40: DI spools | D40: 10" x 3'-0" flange x flange DI spool | E40: EA | F40: 2 | G40: — | H40: — | I40: =IF(COUNTIF('Quote Lines'!$P$3:$P$805,$A40&"|"&I$6&"|1")=0,"—",SUMIFS('Quote Lines'!$O$3:$O$805,'Quote Lines'!$P$3:$P$805,$A40&"|"&I$6&"|1")/SUMIFS('Quote Lines'!$L$3:$L$805,'Quote Lines'!$P$3:$P$805,$A40&"|"&I$6&"|1")) -> 1190.935 | J40: — | K40: =IF(ISNUMBER(G40),G40*$F40,"—") -> — | L40: =IF(ISNUMBER(H40),H40*$F40,"—") -> — | M40: =IF(ISNUMBER(I40),I40*$F40,"—") -> 2381.87 | N40: =IF(ISNUMBER(J40),J40*$F40,"—") -> — | O40: =IF($S40=0,"—",MIN(G40:J40)) -> 1190.935 | P40: =IF($S40=0,"—",IF(COUNTIF(G40:J40,O40)>1,"Tie",INDEX($G$6:$J$6,MATCH(O40,G40:J40,0)))) -> Mountainland | Q40: =IF($S40>=2,MAX(G40:J40)/MIN(G40:J40)-1,"—") -> — | R40: =IF($S40>=2,(MAX(G40:J40)-MIN(G40:J40))*$F40,"—") -> — | S40: =COUNT(G40:J40) -> 1 | T40: =IF($S40<=1,IF($S40=1,"Single quote","—"),"Like-for-like") -> Single quote | U40: =IF(COUNT(W40:Z40)<2,"",IF(MAX(W40:Z40)=MIN(W40:Z40),"OK","Qty differs")) | Y40: =IF(COUNTIFS('Quote Lines'!$P$3:$P$805,$A40&"|"&I$6&"|1",'Quote Lines'!$M$3:$M$805,"Y")=0,"",SUMIFS('Quote Lines'!$L$3:$L$805,'Quote Lines'!$P$3:$P$805,$A40&"|"&I$6&"|1",'Quote Lines'!$M$3:$M$805,"Y")) -> 2 | AA40: =IF(ISNUMBER(G40),1+SUMPRODUCT(ISNUMBER($G40:$J40)*($G40:$J40<G40)),"") | AB40: =IF(ISNUMBER(H40),1+SUMPRODUCT(ISNUMBER($G40:$J40)*($G40:$J40<H40)),"") | AC40: =IF(ISNUMBER(I40),1+SUMPRODUCT(ISNUMBER($G40:$J40)*($G40:$J40<I40)),"") -> 1 | AD40: =IF(ISNUMBER(J40),1+SUMPRODUCT(ISNUMBER($G40:$J40)*($G40:$J40<J40)),"") | AE40: =IF(NOT(ISNUMBER(G40)),0,IF($S40<2,5,IF(AA40=1,1,IF(G40=MAX($G40:$J40),4,IF(AA40=2,2,3))))) -> 0 | AF40: =IF(NOT(ISNUMBER(H40)),0,IF($S40<2,5,IF(AB40=1,1,IF(H40=MAX($G40:$J40),4,IF(AB40=2,2,3))))) -> 0 | AG40: =IF(NOT(ISNUMBER(I40)),0,IF($S40<2,5,IF(AC40=1,1,IF(I40=MAX($G40:$J40),4,IF(AC40=2,2,3))))) -> 5 | AH40: =IF(NOT(ISNUMBER(J40)),0,IF($S40<2,5,IF(AD40=1,1,IF(J40=MAX($G40:$J40),4,IF(AD40=2,2,3))))) -> 0 | AI40: =IF($S40>=2,IF(ISNUMBER(G40),G40*$F40,MIN($G40:$J40)*$F40),0) -> 0 | AJ40: =IF($S40>=2,IF(ISNUMBER(H40),H40*$F40,MIN($G40:$J40)*$F40),0) -> 0 | AK40: =IF($S40>=2,IF(ISNUMBER(I40),I40*$F40,MIN($G40:$J40)*$F40),0) -> 0 | AL40: =IF($S40>=2,IF(ISNUMBER(J40),J40*$F40,MIN($G40:$J40)*$F40),0) -> 0 | AM40: =IF($S40>=2,$R40+ROW()/1000000,"") | AN40: =IF($S40>=2,MAX(G40:J40),"") | AO40: =IF($S40>=2,INDEX($G$6:$J$6,MATCH(MAX(G40:J40),G40:J40,0)),"") | AP40: =IF($S40>=2,MIN(G40:J40)*$F40,0) -> 0 | AQ40: =IF($S40>=2,INDEX($G$6:$J$6,MATCH(MIN(G40:J40),G40:J40,0)),"")
A41: R034 | B41: Item 5 | C41: DI spools | D41: 8" x 2'-6" flange x flange DI spool | E41: EA | F41: 1 | G41: =IF(COUNTIF('Quote Lines'!$P$3:$P$805,$A41&"|"&G$6&"|1")=0,"—",SUMIFS('Quote Lines'!$O$3:$O$805,'Quote Lines'!$P$3:$P$805,$A41&"|"&G$6&"|1")/SUMIFS('Quote Lines'!$L$3:$L$805,'Quote Lines'!$P$3:$P$805,$A41&"|"&G$6&"|1")) -> 881.22 | H41: — | I41: — | J41: =IF(COUNTIF('Quote Lines'!$P$3:$P$805,$A41&"|"&J$6&"|1")=0,"—",SUMIFS('Quote Lines'!$O$3:$O$805,'Quote Lines'!$P$3:$P$805,$A41&"|"&J$6&"|1")/SUMIFS('Quote Lines'!$L$3:$L$805,'Quote Lines'!$P$3:$P$805,$A41&"|"&J$6&"|1")) -> 835 | K41: =IF(ISNUMBER(G41),G41*$F41,"—") -> 881.22 | L41: =IF(ISNUMBER(H41),H41*$F41,"—") -> — | M41: =IF(ISNUMBER(I41),I41*$F41,"—") -> — | N41: =IF(ISNUMBER(J41),J41*$F41,"—") -> 835 | O41: =IF($S41=0,"—",MIN(G41:J41)) -> 835 | P41: =IF($S41=0,"—",IF(COUNTIF(G41:J41,O41)>1,"Tie",INDEX($G$6:$J$6,MATCH(O41,G41:J41,0)))) -> Scholzen | Q41: =IF($S41>=2,MAX(G41:J41)/MIN(G41:J41)-1,"—") -> 0.055353293 | R41: =IF($S41>=2,(MAX(G41:J41)-MIN(G41:J41))*$F41,"—") -> 46.22 | S41: =COUNT(G41:J41) -> 2 | T41: =IF($S41<=1,IF($S41=1,"Single quote","—"),"Like-for-like") -> Like-for-like | U41: =IF(COUNT(W41:Z41)<2,"",IF(MAX(W41:Z41)=MIN(W41:Z41),"OK","Qty differs")) -> OK | W41: =IF(COUNTIFS('Quote Lines'!$P$3:$P$805,$A41&"|"&G$6&"|1",'Quote Lines'!$M$3:$M$805,"Y")=0,"",SUMIFS('Quote Lines'!$L$3:$L$805,'Quote Lines'!$P$3:$P$805,$A41&"|"&G$6&"|1",'Quote Lines'!$M$3:$M$805,"Y")) -> 1 | Z41: =IF(COUNTIFS('Quote Lines'!$P$3:$P$805,$A41&"|"&J$6&"|1",'Quote Lines'!$M$3:$M$805,"Y")=0,"",SUMIFS('Quote Lines'!$L$3:$L$805,'Quote Lines'!$P$3:$P$805,$A41&"|"&J$6&"|1",'Quote Lines'!$M$3:$M$805,"Y")) -> 1 | AA41: =IF(ISNUMBER(G41),1+SUMPRODUCT(ISNUMBER($G41:$J41)*($G41:$J41<G41)),"") -> 2 | AB41: =IF(ISNUMBER(H41),1+SUMPRODUCT(ISNUMBER($G41:$J41)*($G41:$J41<H41)),"") | AC41: =IF(ISNUMBER(I41),1+SUMPRODUCT(ISNUMBER($G41:$J41)*($G41:$J41<I41)),"") | AD41: =IF(ISNUMBER(J41),1+SUMPRODUCT(ISNUMBER($G41:$J41)*($G41:$J41<J41)),"") -> 1 | AE41: =IF(NOT(ISNUMBER(G41)),0,IF($S41<2,5,IF(AA41=1,1,IF(G41=MAX($G41:$J41),4,IF(AA41=2,2,3))))) -> 4 | AF41: =IF(NOT(ISNUMBER(H41)),0,IF($S41<2,5,IF(AB41=1,1,IF(H41=MAX($G41:$J41),4,IF(AB41=2,2,3))))) -> 0 | AG41: =IF(NOT(ISNUMBER(I41)),0,IF($S41<2,5,IF(AC41=1,1,IF(I41=MAX($G41:$J41),4,IF(AC41=2,2,3))))) -> 0 | AH41: =IF(NOT(ISNUMBER(J41)),0,IF($S41<2,5,IF(AD41=1,1,IF(J41=MAX($G41:$J41),4,IF(AD41=2,2,3))))) -> 1 | AI41: =IF($S41>=2,IF(ISNUMBER(G41),G41*$F41,MIN($G41:$J41)*$F41),0) -> 881.22 | AJ41: =IF($S41>=2,IF(ISNUMBER(H41),H41*$F41,MIN($G41:$J41)*$F41),0) -> 835 | AK41: =IF($S41>=2,IF(ISNUMBER(I41),I41*$F41,MIN($G41:$J41)*$F41),0) -> 835 | AL41: =IF($S41>=2,IF(ISNUMBER(J41),J41*$F41,MIN($G41:$J41)*$F41),0) -> 835 | AM41: =IF($S41>=2,$R41+ROW()/1000000,"") -> 46.220041 | AN41: =IF($S41>=2,MAX(G41:J41),"") -> 881.22 | AO41: =IF($S41>=2,INDEX($G$6:$J$6,MATCH(MAX(G41:J41),G41:J41,0)),"") -> Ferguson | AP41: =IF($S41>=2,MIN(G41:J41)*$F41,0) -> 835 | AQ41: =IF($S41>=2,INDEX($G$6:$J$6,MATCH(MIN(G41:J41),G41:J41,0)),"") -> Scholzen
A42: R035 | B42: Item 5 | C42: DI spools | D42: 8" x 2'-0" flange x flange DI spool | E42: EA | F42: 1 | G42: — | H42: — | I42: =IF(COUNTIF('Quote Lines'!$P$3:$P$805,$A42&"|"&I$6&"|1")=0,"—",SUMIFS('Quote Lines'!$O$3:$O$805,'Quote Lines'!$P$3:$P$805,$A42&"|"&I$6&"|1")/SUMIFS('Quote Lines'!$L$3:$L$805,'Quote Lines'!$P$3:$P$805,$A42&"|"&I$6&"|1")) -> 791.56 | J42: — | K42: =IF(ISNUMBER(G42),G42*$F42,"—") -> — | L42: =IF(ISNUMBER(H42),H42*$F42,"—") -> — | M42: =IF(ISNUMBER(I42),I42*$F42,"—") -> 791.56 | N42: =IF(ISNUMBER(J42),J42*$F42,"—") -> — | O42: =IF($S42=0,"—",MIN(G42:J42)) -> 791.56 | P42: =IF($S42=0,"—",IF(COUNTIF(G42:J42,O42)>1,"Tie",INDEX($G$6:$J$6,MATCH(O42,G42:J42,0)))) -> Mountainland | Q42: =IF($S42>=2,MAX(G42:J42)/MIN(G42:J42)-1,"—") -> — | R42: =IF($S42>=2,(MAX(G42:J42)-MIN(G42:J42))*$F42,"—") -> — | S42: =COUNT(G42:J42) -> 1 | T42: =IF($S42<=1,IF($S42=1,"Single quote","—"),"Like-for-like") -> Single quote | U42: =IF(COUNT(W42:Z42)<2,"",IF(MAX(W42:Z42)=MIN(W42:Z42),"OK","Qty differs")) | Y42: =IF(COUNTIFS('Quote Lines'!$P$3:$P$805,$A42&"|"&I$6&"|1",'Quote Lines'!$M$3:$M$805,"Y")=0,"",SUMIFS('Quote Lines'!$L$3:$L$805,'Quote Lines'!$P$3:$P$805,$A42&"|"&I$6&"|1",'Quote Lines'!$M$3:$M$805,"Y")) -> 1 | AA42: =IF(ISNUMBER(G42),1+SUMPRODUCT(ISNUMBER($G42:$J42)*($G42:$J42<G42)),"") | AB42: =IF(ISNUMBER(H42),1+SUMPRODUCT(ISNUMBER($G42:$J42)*($G42:$J42<H42)),"") | AC42: =IF(ISNUMBER(I42),1+SUMPRODUCT(ISNUMBER($G42:$J42)*($G42:$J42<I42)),"") -> 1 | AD42: =IF(ISNUMBER(J42),1+SUMPRODUCT(ISNUMBER($G42:$J42)*($G42:$J42<J42)),"") | AE42: =IF(NOT(ISNUMBER(G42)),0,IF($S42<2,5,IF(AA42=1,1,IF(G42=MAX($G42:$J42),4,IF(AA42=2,2,3))))) -> 0 | AF42: =IF(NOT(ISNUMBER(H42)),0,IF($S42<2,5,IF(AB42=1,1,IF(H42=MAX($G42:$J42),4,IF(AB42=2,2,3))))) -> 0 | AG42: =IF(NOT(ISNUMBER(I42)),0,IF($S42<2,5,IF(AC42=1,1,IF(I42=MAX($G42:$J42),4,IF(AC42=2,2,3))))) -> 5 | AH42: =IF(NOT(ISNUMBER(J42)),0,IF($S42<2,5,IF(AD42=1,1,IF(J42=MAX($G42:$J42),4,IF(AD42=2,2,3))))) -> 0 | AI42: =IF($S42>=2,IF(ISNUMBER(G42),G42*$F42,MIN($G42:$J42)*$F42),0) -> 0 | AJ42: =IF($S42>=2,IF(ISNUMBER(H42),H42*$F42,MIN($G42:$J42)*$F42),0) -> 0 | AK42: =IF($S42>=2,IF(ISNUMBER(I42),I42*$F42,MIN($G42:$J42)*$F42),0) -> 0 | AL42: =IF($S42>=2,IF(ISNUMBER(J42),J42*$F42,MIN($G42:$J42)*$F42),0) -> 0 | AM42: =IF($S42>=2,$R42+ROW()/1000000,"") | AN42: =IF($S42>=2,MAX(G42:J42),"") | AO42: =IF($S42>=2,INDEX($G$6:$J$6,MATCH(MAX(G42:J42),G42:J42,0)),"") | AP42: =IF($S42>=2,MIN(G42:J42)*$F42,0) -> 0 | AQ42: =IF($S42>=2,INDEX($G$6:$J$6,MATCH(MIN(G42:J42),G42:J42,0)),"")
A43: R036 | B43: Item 5 | C43: DI spools | D43: 8" x 3'-0" flange x flange DI spool | E43: EA | F43: 1 | G43: — | H43: =IF(COUNTIF('Quote Lines'!$P$3:$P$805,$A43&"|"&H$6&"|1")=0,"—",SUMIFS('Quote Lines'!$O$3:$O$805,'Quote Lines'!$P$3:$P$805,$A43&"|"&H$6&"|1")/SUMIFS('Quote Lines'!$L$3:$L$805,'Quote Lines'!$P$3:$P$805,$A43&"|"&H$6&"|1")) -> 741.76 | I43: — | J43: — | K43: =IF(ISNUMBER(G43),G43*$F43,"—") -> — | L43: =IF(ISNUMBER(H43),H43*$F43,"—") -> 741.76 | M43: =IF(ISNUMBER(I43),I43*$F43,"—") -> — | N43: =IF(ISNUMBER(J43),J43*$F43,"—") -> — | O43: =IF($S43=0,"—",MIN(G43:J43)) -> 741.76 | P43: =IF($S43=0,"—",IF(COUNTIF(G43:J43,O43)>1,"Tie",INDEX($G$6:$J$6,MATCH(O43,G43:J43,0)))) -> HD Fowler | Q43: =IF($S43>=2,MAX(G43:J43)/MIN(G43:J43)-1,"—") -> — | R43: =IF($S43>=2,(MAX(G43:J43)-MIN(G43:J43))*$F43,"—") -> — | S43: =COUNT(G43:J43) -> 1 | T43: =IF($S43<=1,IF($S43=1,"Single quote","—"),"Like-for-like") -> Single quote | U43: =IF(COUNT(W43:Z43)<2,"",IF(MAX(W43:Z43)=MIN(W43:Z43),"OK","Qty differs")) | X43: =IF(COUNTIFS('Quote Lines'!$P$3:$P$805,$A43&"|"&H$6&"|1",'Quote Lines'!$M$3:$M$805,"Y")=0,"",SUMIFS('Quote Lines'!$L$3:$L$805,'Quote Lines'!$P$3:$P$805,$A43&"|"&H$6&"|1",'Quote Lines'!$M$3:$M$805,"Y")) -> 1 | AA43: =IF(ISNUMBER(G43),1+SUMPRODUCT(ISNUMBER($G43:$J43)*($G43:$J43<G43)),"") | AB43: =IF(ISNUMBER(H43),1+SUMPRODUCT(ISNUMBER($G43:$J43)*($G43:$J43<H43)),"") -> 1 | AC43: =IF(ISNUMBER(I43),1+SUMPRODUCT(ISNUMBER($G43:$J43)*($G43:$J43<I43)),"") | AD43: =IF(ISNUMBER(J43),1+SUMPRODUCT(ISNUMBER($G43:$J43)*($G43:$J43<J43)),"") | AE43: =IF(NOT(ISNUMBER(G43)),0,IF($S43<2,5,IF(AA43=1,1,IF(G43=MAX($G43:$J43),4,IF(AA43=2,2,3))))) -> 0 | AF43: =IF(NOT(ISNUMBER(H43)),0,IF($S43<2,5,IF(AB43=1,1,IF(H43=MAX($G43:$J43),4,IF(AB43=2,2,3))))) -> 5 | AG43: =IF(NOT(ISNUMBER(I43)),0,IF($S43<2,5,IF(AC43=1,1,IF(I43=MAX($G43:$J43),4,IF(AC43=2,2,3))))) -> 0 | AH43: =IF(NOT(ISNUMBER(J43)),0,IF($S43<2,5,IF(AD43=1,1,IF(J43=MAX($G43:$J43),4,IF(AD43=2,2,3))))) -> 0 | AI43: =IF($S43>=2,IF(ISNUMBER(G43),G43*$F43,MIN($G43:$J43)*$F43),0) -> 0 | AJ43: =IF($S43>=2,IF(ISNUMBER(H43),H43*$F43,MIN($G43:$J43)*$F43),0) -> 0 | AK43: =IF($S43>=2,IF(ISNUMBER(I43),I43*$F43,MIN($G43:$J43)*$F43),0) -> 0 | AL43: =IF($S43>=2,IF(ISNUMBER(J43),J43*$F43,MIN($G43:$J43)*$F43),0) -> 0 | AM43: =IF($S43>=2,$R43+ROW()/1000000,"") | AN43: =IF($S43>=2,MAX(G43:J43),"") | AO43: =IF($S43>=2,INDEX($G$6:$J$6,MATCH(MAX(G43:J43),G43:J43,0)),"") | AP43: =IF($S43>=2,MIN(G43:J43)*$F43,0) -> 0 | AQ43: =IF($S43>=2,INDEX($G$6:$J$6,MATCH(MIN(G43:J43),G43:J43,0)),"")
A44: R037 | B44: Item 5 | C44: DI spools | D44: 12" x 7'-0" flange x flange DI spool | E44: EA | F44: 1 | G44: — | H44: =IF(COUNTIF('Quote Lines'!$P$3:$P$805,$A44&"|"&H$6&"|1")=0,"—",SUMIFS('Quote Lines'!$O$3:$O$805,'Quote Lines'!$P$3:$P$805,$A44&"|"&H$6&"|1")/SUMIFS('Quote Lines'!$L$3:$L$805,'Quote Lines'!$P$3:$P$805,$A44&"|"&H$6&"|1")) -> 1935.16 | I44: — | J44: — | K44: =IF(ISNUMBER(G44),G44*$F44,"—") -> — | L44: =IF(ISNUMBER(H44),H44*$F44,"—") -> 1935.16 | M44: =IF(ISNUMBER(I44),I44*$F44,"—") -> — | N44: =IF(ISNUMBER(J44),J44*$F44,"—") -> — | O44: =IF($S44=0,"—",MIN(G44:J44)) -> 1935.16 | P44: =IF($S44=0,"—",IF(COUNTIF(G44:J44,O44)>1,"Tie",INDEX($G$6:$J$6,MATCH(O44,G44:J44,0)))) -> HD Fowler | Q44: =IF($S44>=2,MAX(G44:J44)/MIN(G44:J44)-1,"—") -> — | R44: =IF($S44>=2,(MAX(G44:J44)-MIN(G44:J44))*$F44,"—") -> — | S44: =COUNT(G44:J44) -> 1 | T44: =IF($S44<=1,IF($S44=1,"Single quote","—"),"Like-for-like") -> Single quote | U44: =IF(COUNT(W44:Z44)<2,"",IF(MAX(W44:Z44)=MIN(W44:Z44),"OK","Qty differs")) | X44: =IF(COUNTIFS('Quote Lines'!$P$3:$P$805,$A44&"|"&H$6&"|1",'Quote Lines'!$M$3:$M$805,"Y")=0,"",SUMIFS('Quote Lines'!$L$3:$L$805,'Quote Lines'!$P$3:$P$805,$A44&"|"&H$6&"|1",'Quote Lines'!$M$3:$M$805,"Y")) -> 1 | AA44: =IF(ISNUMBER(G44),1+SUMPRODUCT(ISNUMBER($G44:$J44)*($G44:$J44<G44)),"") | AB44: =IF(ISNUMBER(H44),1+SUMPRODUCT(ISNUMBER($G44:$J44)*($G44:$J44<H44)),"") -> 1 | AC44: =IF(ISNUMBER(I44),1+SUMPRODUCT(ISNUMBER($G44:$J44)*($G44:$J44<I44)),"") | AD44: =IF(ISNUMBER(J44),1+SUMPRODUCT(ISNUMBER($G44:$J44)*($G44:$J44<J44)),"") | AE44: =IF(NOT(ISNUMBER(G44)),0,IF($S44<2,5,IF(AA44=1,1,IF(G44=MAX($G44:$J44),4,IF(AA44=2,2,3))))) -> 0 | AF44: =IF(NOT(ISNUMBER(H44)),0,IF($S44<2,5,IF(AB44=1,1,IF(H44=MAX($G44:$J44),4,IF(AB44=2,2,3))))) -> 5 | AG44: =IF(NOT(ISNUMBER(I44)),0,IF($S44<2,5,IF(AC44=1,1,IF(I44=MAX($G44:$J44),4,IF(AC44=2,2,3))))) -> 0 | AH44: =IF(NOT(ISNUMBER(J44)),0,IF($S44<2,5,IF(AD44=1,1,IF(J44=MAX($G44:$J44),4,IF(AD44=2,2,3))))) -> 0 | AI44: =IF($S44>=2,IF(ISNUMBER(G44),G44*$F44,MIN($G44:$J44)*$F44),0) -> 0 | AJ44: =IF($S44>=2,IF(ISNUMBER(H44),H44*$F44,MIN($G44:$J44)*$F44),0) -> 0 | AK44: =IF($S44>=2,IF(ISNUMBER(I44),I44*$F44,MIN($G44:$J44)*$F44),0) -> 0 | AL44: =IF($S44>=2,IF(ISNUMBER(J44),J44*$F44,MIN($G44:$J44)*$F44),0) -> 0 | AM44: =IF($S44>=2,$R44+ROW()/1000000,"") | AN44: =IF($S44>=2,MAX(G44:J44),"") | AO44: =IF($S44>=2,INDEX($G$6:$J$6,MATCH(MAX(G44:J44),G44:J44,0)),"") | AP44: =IF($S44>=2,MIN(G44:J44)*$F44,0) -> 0 | AQ44: =IF($S44>=2,INDEX($G$6:$J$6,MATCH(MIN(G44:J44),G44:J44,0)),"")
A45: R038 | B45: Item 5 | C45: DI spools | D45: 12" x 7'-4" flange x flange DI spool | E45: EA | F45: 1 | G45: — | H45: — | I45: — | J45: =IF(COUNTIF('Quote Lines'!$P$3:$P$805,$A45&"|"&J$6&"|1")=0,"—",SUMIFS('Quote Lines'!$O$3:$O$805,'Quote Lines'!$P$3:$P$805,$A45&"|"&J$6&"|1")/SUMIFS('Quote Lines'!$L$3:$L$805,'Quote Lines'!$P$3:$P$805,$A45&"|"&J$6&"|1")) -> 2434 | K45: =IF(ISNUMBER(G45),G45*$F45,"—") -> — | L45: =IF(ISNUMBER(H45),H45*$F45,"—") -> — | M45: =IF(ISNUMBER(I45),I45*$F45,"—") -> — | N45: =IF(ISNUMBER(J45),J45*$F45,"—") -> 2434 | O45: =IF($S45=0,"—",MIN(G45:J45)) -> 2434 | P45: =IF($S45=0,"—",IF(COUNTIF(G45:J45,O45)>1,"Tie",INDEX($G$6:$J$6,MATCH(O45,G45:J45,0)))) -> Scholzen | Q45: =IF($S45>=2,MAX(G45:J45)/MIN(G45:J45)-1,"—") -> — | R45: =IF($S45>=2,(MAX(G45:J45)-MIN(G45:J45))*$F45,"—") -> — | S45: =COUNT(G45:J45) -> 1 | T45: =IF($S45<=1,IF($S45=1,"Single quote","—"),"Like-for-like") -> Single quote | U45: =IF(COUNT(W45:Z45)<2,"",IF(MAX(W45:Z45)=MIN(W45:Z45),"OK","Qty differs")) | Z45: =IF(COUNTIFS('Quote Lines'!$P$3:$P$805,$A45&"|"&J$6&"|1",'Quote Lines'!$M$3:$M$805,"Y")=0,"",SUMIFS('Quote Lines'!$L$3:$L$805,'Quote Lines'!$P$3:$P$805,$A45&"|"&J$6&"|1",'Quote Lines'!$M$3:$M$805,"Y")) -> 1 | AA45: =IF(ISNUMBER(G45),1+SUMPRODUCT(ISNUMBER($G45:$J45)*($G45:$J45<G45)),"") | AB45: =IF(ISNUMBER(H45),1+SUMPRODUCT(ISNUMBER($G45:$J45)*($G45:$J45<H45)),"") | AC45: =IF(ISNUMBER(I45),1+SUMPRODUCT(ISNUMBER($G45:$J45)*($G45:$J45<I45)),"") | AD45: =IF(ISNUMBER(J45),1+SUMPRODUCT(ISNUMBER($G45:$J45)*($G45:$J45<J45)),"") -> 1 | AE45: =IF(NOT(ISNUMBER(G45)),0,IF($S45<2,5,IF(AA45=1,1,IF(G45=MAX($G45:$J45),4,IF(AA45=2,2,3))))) -> 0 | AF45: =IF(NOT(ISNUMBER(H45)),0,IF($S45<2,5,IF(AB45=1,1,IF(H45=MAX($G45:$J45),4,IF(AB45=2,2,3))))) -> 0 | AG45: =IF(NOT(ISNUMBER(I45)),0,IF($S45<2,5,IF(AC45=1,1,IF(I45=MAX($G45:$J45),4,IF(AC45=2,2,3))))) -> 0 | AH45: =IF(NOT(ISNUMBER(J45)),0,IF($S45<2,5,IF(AD45=1,1,IF(J45=MAX($G45:$J45),4,IF(AD45=2,2,3))))) -> 5 | AI45: =IF($S45>=2,IF(ISNUMBER(G45),G45*$F45,MIN($G45:$J45)*$F45),0) -> 0 | AJ45: =IF($S45>=2,IF(ISNUMBER(H45),H45*$F45,MIN($G45:$J45)*$F45),0) -> 0 | AK45: =IF($S45>=2,IF(ISNUMBER(I45),I45*$F45,MIN($G45:$J45)*$F45),0) -> 0 | AL45: =IF($S45>=2,IF(ISNUMBER(J45),J45*$F45,MIN($G45:$J45)*$F45),0) -> 0 | AM45: =IF($S45>=2,$R45+ROW()/1000000,"") | AN45: =IF($S45>=2,MAX(G45:J45),"") | AO45: =IF($S45>=2,INDEX($G$6:$J$6,MATCH(MAX(G45:J45),G45:J45,0)),"") | AP45: =IF($S45>=2,MIN(G45:J45)*$F45,0) -> 0 | AQ45: =IF($S45>=2,INDEX($G$6:$J$6,MATCH(MIN(G45:J45),G45:J45,0)),"")
A46: R039 | B46: Item 5 | C46: DI spools | D46: 12" x 5'-0" flange x PE DI spool | E46: EA | F46: 1 | G46: =IF(COUNTIF('Quote Lines'!$P$3:$P$805,$A46&"|"&G$6&"|1")=0,"—",SUMIFS('Quote Lines'!$O$3:$O$805,'Quote Lines'!$P$3:$P$805,$A46&"|"&G$6&"|1")/SUMIFS('Quote Lines'!$L$3:$L$805,'Quote Lines'!$P$3:$P$805,$A46&"|"&G$6&"|1")) -> 1706.83 | H46: — | I46: — | J46: — | K46: =IF(ISNUMBER(G46),G46*$F46,"—") -> 1706.83 | L46: =IF(ISNUMBER(H46),H46*$F46,"—") -> — | M46: =IF(ISNUMBER(I46),I46*$F46,"—") -> — | N46: =IF(ISNUMBER(J46),J46*$F46,"—") -> — | O46: =IF($S46=0,"—",MIN(G46:J46)) -> 1706.83 | P46: =IF($S46=0,"—",IF(COUNTIF(G46:J46,O46)>1,"Tie",INDEX($G$6:$J$6,MATCH(O46,G46:J46,0)))) -> Ferguson | Q46: =IF($S46>=2,MAX(G46:J46)/MIN(G46:J46)-1,"—") -> — | R46: =IF($S46>=2,(MAX(G46:J46)-MIN(G46:J46))*$F46,"—") -> — | S46: =COUNT(G46:J46) -> 1 | T46: =IF($S46<=1,IF($S46=1,"Single quote","—"),"Like-for-like") -> Single quote | U46: =IF(COUNT(W46:Z46)<2,"",IF(MAX(W46:Z46)=MIN(W46:Z46),"OK","Qty differs")) | W46: =IF(COUNTIFS('Quote Lines'!$P$3:$P$805,$A46&"|"&G$6&"|1",'Quote Lines'!$M$3:$M$805,"Y")=0,"",SUMIFS('Quote Lines'!$L$3:$L$805,'Quote Lines'!$P$3:$P$805,$A46&"|"&G$6&"|1",'Quote Lines'!$M$3:$M$805,"Y")) -> 1 | AA46: =IF(ISNUMBER(G46),1+SUMPRODUCT(ISNUMBER($G46:$J46)*($G46:$J46<G46)),"") -> 1 | AB46: =IF(ISNUMBER(H46),1+SUMPRODUCT(ISNUMBER($G46:$J46)*($G46:$J46<H46)),"") | AC46: =IF(ISNUMBER(I46),1+SUMPRODUCT(ISNUMBER($G46:$J46)*($G46:$J46<I46)),"") | AD46: =IF(ISNUMBER(J46),1+SUMPRODUCT(ISNUMBER($G46:$J46)*($G46:$J46<J46)),"") | AE46: =IF(NOT(ISNUMBER(G46)),0,IF($S46<2,5,IF(AA46=1,1,IF(G46=MAX($G46:$J46),4,IF(AA46=2,2,3))))) -> 5 | AF46: =IF(NOT(ISNUMBER(H46)),0,IF($S46<2,5,IF(AB46=1,1,IF(H46=MAX($G46:$J46),4,IF(AB46=2,2,3))))) -> 0 | AG46: =IF(NOT(ISNUMBER(I46)),0,IF($S46<2,5,IF(AC46=1,1,IF(I46=MAX($G46:$J46),4,IF(AC46=2,2,3))))) -> 0 | AH46: =IF(NOT(ISNUMBER(J46)),0,IF($S46<2,5,IF(AD46=1,1,IF(J46=MAX($G46:$J46),4,IF(AD46=2,2,3))))) -> 0 | AI46: =IF($S46>=2,IF(ISNUMBER(G46),G46*$F46,MIN($G46:$J46)*$F46),0) -> 0 | AJ46: =IF($S46>=2,IF(ISNUMBER(H46),H46*$F46,MIN($G46:$J46)*$F46),0) -> 0 | AK46: =IF($S46>=2,IF(ISNUMBER(I46),I46*$F46,MIN($G46:$J46)*$F46),0) -> 0 | AL46: =IF($S46>=2,IF(ISNUMBER(J46),J46*$F46,MIN($G46:$J46)*$F46),0) -> 0 | AM46: =IF($S46>=2,$R46+ROW()/1000000,"") | AN46: =IF($S46>=2,MAX(G46:J46),"") | AO46: =IF($S46>=2,INDEX($G$6:$J$6,MATCH(MAX(G46:J46),G46:J46,0)),"") | AP46: =IF($S46>=2,MIN(G46:J46)*$F46,0) -> 0 | AQ46: =IF($S46>=2,INDEX($G$6:$J$6,MATCH(MIN(G46:J46),G46:J46,0)),"")
A47: R040 | B47: Item 5 | C47: DI spools | D47: 12" x 5'-6" flange x PE DI spool | E47: EA | F47: 1 | G47: — | H47: =IF(COUNTIF('Quote Lines'!$P$3:$P$805,$A47&"|"&H$6&"|1")=0,"—",SUMIFS('Quote Lines'!$O$3:$O$805,'Quote Lines'!$P$3:$P$805,$A47&"|"&H$6&"|1")/SUMIFS('Quote Lines'!$L$3:$L$805,'Quote Lines'!$P$3:$P$805,$A47&"|"&H$6&"|1")) -> 1294.51 | I47: — | J47: — | K47: =IF(ISNUMBER(G47),G47*$F47,"—") -> — | L47: =IF(ISNUMBER(H47),H47*$F47,"—") -> 1294.51 | M47: =IF(ISNUMBER(I47),I47*$F47,"—") -> — | N47: =IF(ISNUMBER(J47),J47*$F47,"—") -> — | O47: =IF($S47=0,"—",MIN(G47:J47)) -> 1294.51 | P47: =IF($S47=0,"—",IF(COUNTIF(G47:J47,O47)>1,"Tie",INDEX($G$6:$J$6,MATCH(O47,G47:J47,0)))) -> HD Fowler | Q47: =IF($S47>=2,MAX(G47:J47)/MIN(G47:J47)-1,"—") -> — | R47: =IF($S47>=2,(MAX(G47:J47)-MIN(G47:J47))*$F47,"—") -> — | S47: =COUNT(G47:J47) -> 1 | T47: =IF($S47<=1,IF($S47=1,"Single quote","—"),"Like-for-like") -> Single quote | U47: =IF(COUNT(W47:Z47)<2,"",IF(MAX(W47:Z47)=MIN(W47:Z47),"OK","Qty differs")) | X47: =IF(COUNTIFS('Quote Lines'!$P$3:$P$805,$A47&"|"&H$6&"|1",'Quote Lines'!$M$3:$M$805,"Y")=0,"",SUMIFS('Quote Lines'!$L$3:$L$805,'Quote Lines'!$P$3:$P$805,$A47&"|"&H$6&"|1",'Quote Lines'!$M$3:$M$805,"Y")) -> 1 | AA47: =IF(ISNUMBER(G47),1+SUMPRODUCT(ISNUMBER($G47:$J47)*($G47:$J47<G47)),"") | AB47: =IF(ISNUMBER(H47),1+SUMPRODUCT(ISNUMBER($G47:$J47)*($G47:$J47<H47)),"") -> 1 | AC47: =IF(ISNUMBER(I47),1+SUMPRODUCT(ISNUMBER($G47:$J47)*($G47:$J47<I47)),"") | AD47: =IF(ISNUMBER(J47),1+SUMPRODUCT(ISNUMBER($G47:$J47)*($G47:$J47<J47)),"") | AE47: =IF(NOT(ISNUMBER(G47)),0,IF($S47<2,5,IF(AA47=1,1,IF(G47=MAX($G47:$J47),4,IF(AA47=2,2,3))))) -> 0 | AF47: =IF(NOT(ISNUMBER(H47)),0,IF($S47<2,5,IF(AB47=1,1,IF(H47=MAX($G47:$J47),4,IF(AB47=2,2,3))))) -> 5 | AG47: =IF(NOT(ISNUMBER(I47)),0,IF($S47<2,5,IF(AC47=1,1,IF(I47=MAX($G47:$J47),4,IF(AC47=2,2,3))))) -> 0 | AH47: =IF(NOT(ISNUMBER(J47)),0,IF($S47<2,5,IF(AD47=1,1,IF(J47=MAX($G47:$J47),4,IF(AD47=2,2,3))))) -> 0 | AI47: =IF($S47>=2,IF(ISNUMBER(G47),G47*$F47,MIN($G47:$J47)*$F47),0) -> 0 | AJ47: =IF($S47>=2,IF(ISNUMBER(H47),H47*$F47,MIN($G47:$J47)*$F47),0) -> 0 | AK47: =IF($S47>=2,IF(ISNUMBER(I47),I47*$F47,MIN($G47:$J47)*$F47),0) -> 0 | AL47: =IF($S47>=2,IF(ISNUMBER(J47),J47*$F47,MIN($G47:$J47)*$F47),0) -> 0 | AM47: =IF($S47>=2,$R47+ROW()/1000000,"") | AN47: =IF($S47>=2,MAX(G47:J47),"") | AO47: =IF($S47>=2,INDEX($G$6:$J$6,MATCH(MAX(G47:J47),G47:J47,0)),"") | AP47: =IF($S47>=2,MIN(G47:J47)*$F47,0) -> 0 | AQ47: =IF($S47>=2,INDEX($G$6:$J$6,MATCH(MIN(G47:J47),G47:J47,0)),"")
A48: R041 | B48: Item 5 | C48: DI spools | D48: 12" x 6'-0" flange x PE DI spool | E48: EA | F48: 1 | G48: — | H48: — | I48: — | J48: =IF(COUNTIF('Quote Lines'!$P$3:$P$805,$A48&"|"&J$6&"|1")=0,"—",SUMIFS('Quote Lines'!$O$3:$O$805,'Quote Lines'!$P$3:$P$805,$A48&"|"&J$6&"|1")/SUMIFS('Quote Lines'!$L$3:$L$805,'Quote Lines'!$P$3:$P$805,$A48&"|"&J$6&"|1")) -> 2121 | K48: =IF(ISNUMBER(G48),G48*$F48,"—") -> — | L48: =IF(ISNUMBER(H48),H48*$F48,"—") -> — | M48: =IF(ISNUMBER(I48),I48*$F48,"—") -> — | N48: =IF(ISNUMBER(J48),J48*$F48,"—") -> 2121 | O48: =IF($S48=0,"—",MIN(G48:J48)) -> 2121 | P48: =IF($S48=0,"—",IF(COUNTIF(G48:J48,O48)>1,"Tie",INDEX($G$6:$J$6,MATCH(O48,G48:J48,0)))) -> Scholzen | Q48: =IF($S48>=2,MAX(G48:J48)/MIN(G48:J48)-1,"—") -> — | R48: =IF($S48>=2,(MAX(G48:J48)-MIN(G48:J48))*$F48,"—") -> — | S48: =COUNT(G48:J48) -> 1 | T48: =IF($S48<=1,IF($S48=1,"Single quote","—"),"Like-for-like") -> Single quote | U48: =IF(COUNT(W48:Z48)<2,"",IF(MAX(W48:Z48)=MIN(W48:Z48),"OK","Qty differs")) | Z48: =IF(COUNTIFS('Quote Lines'!$P$3:$P$805,$A48&"|"&J$6&"|1",'Quote Lines'!$M$3:$M$805,"Y")=0,"",SUMIFS('Quote Lines'!$L$3:$L$805,'Quote Lines'!$P$3:$P$805,$A48&"|"&J$6&"|1",'Quote Lines'!$M$3:$M$805,"Y")) -> 1 | AA48: =IF(ISNUMBER(G48),1+SUMPRODUCT(ISNUMBER($G48:$J48)*($G48:$J48<G48)),"") | AB48: =IF(ISNUMBER(H48),1+SUMPRODUCT(ISNUMBER($G48:$J48)*($G48:$J48<H48)),"") | AC48: =IF(ISNUMBER(I48),1+SUMPRODUCT(ISNUMBER($G48:$J48)*($G48:$J48<I48)),"") | AD48: =IF(ISNUMBER(J48),1+SUMPRODUCT(ISNUMBER($G48:$J48)*($G48:$J48<J48)),"") -> 1 | AE48: =IF(NOT(ISNUMBER(G48)),0,IF($S48<2,5,IF(AA48=1,1,IF(G48=MAX($G48:$J48),4,IF(AA48=2,2,3))))) -> 0 | AF48: =IF(NOT(ISNUMBER(H48)),0,IF($S48<2,5,IF(AB48=1,1,IF(H48=MAX($G48:$J48),4,IF(AB48=2,2,3))))) -> 0 | AG48: =IF(NOT(ISNUMBER(I48)),0,IF($S48<2,5,IF(AC48=1,1,IF(I48=MAX($G48:$J48),4,IF(AC48=2,2,3))))) -> 0 | AH48: =IF(NOT(ISNUMBER(J48)),0,IF($S48<2,5,IF(AD48=1,1,IF(J48=MAX($G48:$J48),4,IF(AD48=2,2,3))))) -> 5 | AI48: =IF($S48>=2,IF(ISNUMBER(G48),G48*$F48,MIN($G48:$J48)*$F48),0) -> 0 | AJ48: =IF($S48>=2,IF(ISNUMBER(H48),H48*$F48,MIN($G48:$J48)*$F48),0) -> 0 | AK48: =IF($S48>=2,IF(ISNUMBER(I48),I48*$F48,MIN($G48:$J48)*$F48),0) -> 0 | AL48: =IF($S48>=2,IF(ISNUMBER(J48),J48*$F48,MIN($G48:$J48)*$F48),0) -> 0 | AM48: =IF($S48>=2,$R48+ROW()/1000000,"") | AN48: =IF($S48>=2,MAX(G48:J48),"") | AO48: =IF($S48>=2,INDEX($G$6:$J$6,MATCH(MAX(G48:J48),G48:J48,0)),"") | AP48: =IF($S48>=2,MIN(G48:J48)*$F48,0) -> 0 | AQ48: =IF($S48>=2,INDEX($G$6:$J$6,MATCH(MIN(G48:J48),G48:J48,0)),"")
A49: R042 | B49: Item 5 | C49: DI spools | D49: 12" x 4'-6" flange x PE DI spool | E49: EA | F49: 1 | G49: =IF(COUNTIF('Quote Lines'!$P$3:$P$805,$A49&"|"&G$6&"|1")=0,"—",SUMIFS('Quote Lines'!$O$3:$O$805,'Quote Lines'!$P$3:$P$805,$A49&"|"&G$6&"|1")/SUMIFS('Quote Lines'!$L$3:$L$805,'Quote Lines'!$P$3:$P$805,$A49&"|"&G$6&"|1")) -> 1572.09 | H49: — | I49: — | J49: — | K49: =IF(ISNUMBER(G49),G49*$F49,"—") -> 1572.09 | L49: =IF(ISNUMBER(H49),H49*$F49,"—") -> — | M49: =IF(ISNUMBER(I49),I49*$F49,"—") -> — | N49: =IF(ISNUMBER(J49),J49*$F49,"—") -> — | O49: =IF($S49=0,"—",MIN(G49:J49)) -> 1572.09 | P49: =IF($S49=0,"—",IF(COUNTIF(G49:J49,O49)>1,"Tie",INDEX($G$6:$J$6,MATCH(O49,G49:J49,0)))) -> Ferguson | Q49: =IF($S49>=2,MAX(G49:J49)/MIN(G49:J49)-1,"—") -> — | R49: =IF($S49>=2,(MAX(G49:J49)-MIN(G49:J49))*$F49,"—") -> — | S49: =COUNT(G49:J49) -> 1 | T49: =IF($S49<=1,IF($S49=1,"Single quote","—"),"Like-for-like") -> Single quote | U49: =IF(COUNT(W49:Z49)<2,"",IF(MAX(W49:Z49)=MIN(W49:Z49),"OK","Qty differs")) | W49: =IF(COUNTIFS('Quote Lines'!$P$3:$P$805,$A49&"|"&G$6&"|1",'Quote Lines'!$M$3:$M$805,"Y")=0,"",SUMIFS('Quote Lines'!$L$3:$L$805,'Quote Lines'!$P$3:$P$805,$A49&"|"&G$6&"|1",'Quote Lines'!$M$3:$M$805,"Y")) -> 1 | AA49: =IF(ISNUMBER(G49),1+SUMPRODUCT(ISNUMBER($G49:$J49)*($G49:$J49<G49)),"") -> 1 | AB49: =IF(ISNUMBER(H49),1+SUMPRODUCT(ISNUMBER($G49:$J49)*($G49:$J49<H49)),"") | AC49: =IF(ISNUMBER(I49),1+SUMPRODUCT(ISNUMBER($G49:$J49)*($G49:$J49<I49)),"") | AD49: =IF(ISNUMBER(J49),1+SUMPRODUCT(ISNUMBER($G49:$J49)*($G49:$J49<J49)),"") | AE49: =IF(NOT(ISNUMBER(G49)),0,IF($S49<2,5,IF(AA49=1,1,IF(G49=MAX($G49:$J49),4,IF(AA49=2,2,3))))) -> 5 | AF49: =IF(NOT(ISNUMBER(H49)),0,IF($S49<2,5,IF(AB49=1,1,IF(H49=MAX($G49:$J49),4,IF(AB49=2,2,3))))) -> 0 | AG49: =IF(NOT(ISNUMBER(I49)),0,IF($S49<2,5,IF(AC49=1,1,IF(I49=MAX($G49:$J49),4,IF(AC49=2,2,3))))) -> 0 | AH49: =IF(NOT(ISNUMBER(J49)),0,IF($S49<2,5,IF(AD49=1,1,IF(J49=MAX($G49:$J49),4,IF(AD49=2,2,3))))) -> 0 | AI49: =IF($S49>=2,IF(ISNUMBER(G49),G49*$F49,MIN($G49:$J49)*$F49),0) -> 0 | AJ49: =IF($S49>=2,IF(ISNUMBER(H49),H49*$F49,MIN($G49:$J49)*$F49),0) -> 0 | AK49: =IF($S49>=2,IF(ISNUMBER(I49),I49*$F49,MIN($G49:$J49)*$F49),0) -> 0 | AL49: =IF($S49>=2,IF(ISNUMBER(J49),J49*$F49,MIN($G49:$J49)*$F49),0) -> 0 | AM49: =IF($S49>=2,$R49+ROW()/1000000,"") | AN49: =IF($S49>=2,MAX(G49:J49),"") | AO49: =IF($S49>=2,INDEX($G$6:$J$6,MATCH(MAX(G49:J49),G49:J49,0)),"") | AP49: =IF($S49>=2,MIN(G49:J49)*$F49,0) -> 0 | AQ49: =IF($S49>=2,INDEX($G$6:$J$6,MATCH(MIN(G49:J49),G49:J49,0)),"")
A50: R043 | B50: Item 5 | C50: DI spools | D50: 12" x 4'-0" flange x PE DI spool | E50: EA | F50: 2 | G50: — | H50: — | I50: =IF(COUNTIF('Quote Lines'!$P$3:$P$805,$A50&"|"&I$6&"|1")=0,"—",SUMIFS('Quote Lines'!$O$3:$O$805,'Quote Lines'!$P$3:$P$805,$A50&"|"&I$6&"|1")/SUMIFS('Quote Lines'!$L$3:$L$805,'Quote Lines'!$P$3:$P$805,$A50&"|"&I$6&"|1")) -> 1285.385 | J50: — | K50: =IF(ISNUMBER(G50),G50*$F50,"—") -> — | L50: =IF(ISNUMBER(H50),H50*$F50,"—") -> — | M50: =IF(ISNUMBER(I50),I50*$F50,"—") -> 2570.77 | N50: =IF(ISNUMBER(J50),J50*$F50,"—") -> — | O50: =IF($S50=0,"—",MIN(G50:J50)) -> 1285.385 | P50: =IF($S50=0,"—",IF(COUNTIF(G50:J50,O50)>1,"Tie",INDEX($G$6:$J$6,MATCH(O50,G50:J50,0)))) -> Mountainland | Q50: =IF($S50>=2,MAX(G50:J50)/MIN(G50:J50)-1,"—") -> — | R50: =IF($S50>=2,(MAX(G50:J50)-MIN(G50:J50))*$F50,"—") -> — | S50: =COUNT(G50:J50) -> 1 | T50: =IF($S50<=1,IF($S50=1,"Single quote","—"),"Like-for-like") -> Single quote | U50: =IF(COUNT(W50:Z50)<2,"",IF(MAX(W50:Z50)=MIN(W50:Z50),"OK","Qty differs")) | Y50: =IF(COUNTIFS('Quote Lines'!$P$3:$P$805,$A50&"|"&I$6&"|1",'Quote Lines'!$M$3:$M$805,"Y")=0,"",SUMIFS('Quote Lines'!$L$3:$L$805,'Quote Lines'!$P$3:$P$805,$A50&"|"&I$6&"|1",'Quote Lines'!$M$3:$M$805,"Y")) -> 2 | AA50: =IF(ISNUMBER(G50),1+SUMPRODUCT(ISNUMBER($G50:$J50)*($G50:$J50<G50)),"") | AB50: =IF(ISNUMBER(H50),1+SUMPRODUCT(ISNUMBER($G50:$J50)*($G50:$J50<H50)),"") | AC50: =IF(ISNUMBER(I50),1+SUMPRODUCT(ISNUMBER($G50:$J50)*($G50:$J50<I50)),"") -> 1 | AD50: =IF(ISNUMBER(J50),1+SUMPRODUCT(ISNUMBER($G50:$J50)*($G50:$J50<J50)),"") | AE50: =IF(NOT(ISNUMBER(G50)),0,IF($S50<2,5,IF(AA50=1,1,IF(G50=MAX($G50:$J50),4,IF(AA50=2,2,3))))) -> 0 | AF50: =IF(NOT(ISNUMBER(H50)),0,IF($S50<2,5,IF(AB50=1,1,IF(H50=MAX($G50:$J50),4,IF(AB50=2,2,3))))) -> 0 | AG50: =IF(NOT(ISNUMBER(I50)),0,IF($S50<2,5,IF(AC50=1,1,IF(I50=MAX($G50:$J50),4,IF(AC50=2,2,3))))) -> 5 | AH50: =IF(NOT(ISNUMBER(J50)),0,IF($S50<2,5,IF(AD50=1,1,IF(J50=MAX($G50:$J50),4,IF(AD50=2,2,3))))) -> 0 | AI50: =IF($S50>=2,IF(ISNUMBER(G50),G50*$F50,MIN($G50:$J50)*$F50),0) -> 0 | AJ50: =IF($S50>=2,IF(ISNUMBER(H50),H50*$F50,MIN($G50:$J50)*$F50),0) -> 0 | AK50: =IF($S50>=2,IF(ISNUMBER(I50),I50*$F50,MIN($G50:$J50)*$F50),0) -> 0 | AL50: =IF($S50>=2,IF(ISNUMBER(J50),J50*$F50,MIN($G50:$J50)*$F50),0) -> 0 | AM50: =IF($S50>=2,$R50+ROW()/1000000,"") | AN50: =IF($S50>=2,MAX(G50:J50),"") | AO50: =IF($S50>=2,INDEX($G$6:$J$6,MATCH(MAX(G50:J50),G50:J50,0)),"") | AP50: =IF($S50>=2,MIN(G50:J50)*$F50,0) -> 0 | AQ50: =IF($S50>=2,INDEX($G$6:$J$6,MATCH(MIN(G50:J50),G50:J50,0)),"")
A51: R044 | B51: Item 5 | C51: DI spools | D51: 12" x 3'-0" flange x PE DI spool | E51: EA | F51: 1 | G51: =IF(COUNTIF('Quote Lines'!$P$3:$P$805,$A51&"|"&G$6&"|1")=0,"—",SUMIFS('Quote Lines'!$O$3:$O$805,'Quote Lines'!$P$3:$P$805,$A51&"|"&G$6&"|1")/SUMIFS('Quote Lines'!$L$3:$L$805,'Quote Lines'!$P$3:$P$805,$A51&"|"&G$6&"|1")) -> 1167.83 | H51: =IF(COUNTIF('Quote Lines'!$P$3:$P$805,$A51&"|"&H$6&"|1")=0,"—",SUMIFS('Quote Lines'!$O$3:$O$805,'Quote Lines'!$P$3:$P$805,$A51&"|"&H$6&"|1")/SUMIFS('Quote Lines'!$L$3:$L$805,'Quote Lines'!$P$3:$P$805,$A51&"|"&H$6&"|1")) -> 867.03 | I51: — | J51: — | K51: =IF(ISNUMBER(G51),G51*$F51,"—") -> 1167.83 | L51: =IF(ISNUMBER(H51),H51*$F51,"—") -> 867.03 | M51: =IF(ISNUMBER(I51),I51*$F51,"—") -> — | N51: =IF(ISNUMBER(J51),J51*$F51,"—") -> — | O51: =IF($S51=0,"—",MIN(G51:J51)) -> 867.03 | P51: =IF($S51=0,"—",IF(COUNTIF(G51:J51,O51)>1,"Tie",INDEX($G$6:$J$6,MATCH(O51,G51:J51,0)))) -> HD Fowler | Q51: =IF($S51>=2,MAX(G51:J51)/MIN(G51:J51)-1,"—") -> 0.34693148 | R51: =IF($S51>=2,(MAX(G51:J51)-MIN(G51:J51))*$F51,"—") -> 300.8 | S51: =COUNT(G51:J51) -> 2 | T51: =IF($S51<=1,IF($S51=1,"Single quote","—"),"Like-for-like") -> Like-for-like | U51: =IF(COUNT(W51:Z51)<2,"",IF(MAX(W51:Z51)=MIN(W51:Z51),"OK","Qty differs")) -> OK | W51: =IF(COUNTIFS('Quote Lines'!$P$3:$P$805,$A51&"|"&G$6&"|1",'Quote Lines'!$M$3:$M$805,"Y")=0,"",SUMIFS('Quote Lines'!$L$3:$L$805,'Quote Lines'!$P$3:$P$805,$A51&"|"&G$6&"|1",'Quote Lines'!$M$3:$M$805,"Y")) -> 1 | X51: =IF(COUNTIFS('Quote Lines'!$P$3:$P$805,$A51&"|"&H$6&"|1",'Quote Lines'!$M$3:$M$805,"Y")=0,"",SUMIFS('Quote Lines'!$L$3:$L$805,'Quote Lines'!$P$3:$P$805,$A51&"|"&H$6&"|1",'Quote Lines'!$M$3:$M$805,"Y")) -> 1 | AA51: =IF(ISNUMBER(G51),1+SUMPRODUCT(ISNUMBER($G51:$J51)*($G51:$J51<G51)),"") -> 2 | AB51: =IF(ISNUMBER(H51),1+SUMPRODUCT(ISNUMBER($G51:$J51)*($G51:$J51<H51)),"") -> 1 | AC51: =IF(ISNUMBER(I51),1+SUMPRODUCT(ISNUMBER($G51:$J51)*($G51:$J51<I51)),"") | AD51: =IF(ISNUMBER(J51),1+SUMPRODUCT(ISNUMBER($G51:$J51)*($G51:$J51<J51)),"") | AE51: =IF(NOT(ISNUMBER(G51)),0,IF($S51<2,5,IF(AA51=1,1,IF(G51=MAX($G51:$J51),4,IF(AA51=2,2,3))))) -> 4 | AF51: =IF(NOT(ISNUMBER(H51)),0,IF($S51<2,5,IF(AB51=1,1,IF(H51=MAX($G51:$J51),4,IF(AB51=2,2,3))))) -> 1 | AG51: =IF(NOT(ISNUMBER(I51)),0,IF($S51<2,5,IF(AC51=1,1,IF(I51=MAX($G51:$J51),4,IF(AC51=2,2,3))))) -> 0 | AH51: =IF(NOT(ISNUMBER(J51)),0,IF($S51<2,5,IF(AD51=1,1,IF(J51=MAX($G51:$J51),4,IF(AD51=2,2,3))))) -> 0 | AI51: =IF($S51>=2,IF(ISNUMBER(G51),G51*$F51,MIN($G51:$J51)*$F51),0) -> 1167.83 | AJ51: =IF($S51>=2,IF(ISNUMBER(H51),H51*$F51,MIN($G51:$J51)*$F51),0) -> 867.03 | AK51: =IF($S51>=2,IF(ISNUMBER(I51),I51*$F51,MIN($G51:$J51)*$F51),0) -> 867.03 | AL51: =IF($S51>=2,IF(ISNUMBER(J51),J51*$F51,MIN($G51:$J51)*$F51),0) -> 867.03 | AM51: =IF($S51>=2,$R51+ROW()/1000000,"") -> 300.80005 | AN51: =IF($S51>=2,MAX(G51:J51),"") -> 1167.83 | AO51: =IF($S51>=2,INDEX($G$6:$J$6,MATCH(MAX(G51:J51),G51:J51,0)),"") -> Ferguson | AP51: =IF($S51>=2,MIN(G51:J51)*$F51,0) -> 867.03 | AQ51: =IF($S51>=2,INDEX($G$6:$J$6,MATCH(MIN(G51:J51),G51:J51,0)),"") -> HD Fowler
A52: R045 | B52: Item 5 | C52: DI spools | D52: 12" x 2'-6" flange x PE DI spool | E52: EA | F52: 1 | G52: =IF(COUNTIF('Quote Lines'!$P$3:$P$805,$A52&"|"&G$6&"|1")=0,"—",SUMIFS('Quote Lines'!$O$3:$O$805,'Quote Lines'!$P$3:$P$805,$A52&"|"&G$6&"|1")/SUMIFS('Quote Lines'!$L$3:$L$805,'Quote Lines'!$P$3:$P$805,$A52&"|"&G$6&"|1")) -> 1033.09 | H52: — | I52: — | J52: =IF(COUNTIF('Quote Lines'!$P$3:$P$805,$A52&"|"&J$6&"|1")=0,"—",SUMIFS('Quote Lines'!$O$3:$O$805,'Quote Lines'!$P$3:$P$805,$A52&"|"&J$6&"|1")/SUMIFS('Quote Lines'!$L$3:$L$805,'Quote Lines'!$P$3:$P$805,$A52&"|"&J$6&"|1")) -> 940 | K52: =IF(ISNUMBER(G52),G52*$F52,"—") -> 1033.09 | L52: =IF(ISNUMBER(H52),H52*$F52,"—") -> — | M52: =IF(ISNUMBER(I52),I52*$F52,"—") -> — | N52: =IF(ISNUMBER(J52),J52*$F52,"—") -> 940 | O52: =IF($S52=0,"—",MIN(G52:J52)) -> 940 | P52: =IF($S52=0,"—",IF(COUNTIF(G52:J52,O52)>1,"Tie",INDEX($G$6:$J$6,MATCH(O52,G52:J52,0)))) -> Scholzen | Q52: =IF($S52>=2,MAX(G52:J52)/MIN(G52:J52)-1,"—") -> 0.099031915 | R52: =IF($S52>=2,(MAX(G52:J52)-MIN(G52:J52))*$F52,"—") -> 93.09 | S52: =COUNT(G52:J52) -> 2 | T52: =IF($S52<=1,IF($S52=1,"Single quote","—"),"Like-for-like") -> Like-for-like | U52: =IF(COUNT(W52:Z52)<2,"",IF(MAX(W52:Z52)=MIN(W52:Z52),"OK","Qty differs")) -> OK | W52: =IF(COUNTIFS('Quote Lines'!$P$3:$P$805,$A52&"|"&G$6&"|1",'Quote Lines'!$M$3:$M$805,"Y")=0,"",SUMIFS('Quote Lines'!$L$3:$L$805,'Quote Lines'!$P$3:$P$805,$A52&"|"&G$6&"|1",'Quote Lines'!$M$3:$M$805,"Y")) -> 1 | Z52: =IF(COUNTIFS('Quote Lines'!$P$3:$P$805,$A52&"|"&J$6&"|1",'Quote Lines'!$M$3:$M$805,"Y")=0,"",SUMIFS('Quote Lines'!$L$3:$L$805,'Quote Lines'!$P$3:$P$805,$A52&"|"&J$6&"|1",'Quote Lines'!$M$3:$M$805,"Y")) -> 1 | AA52: =IF(ISNUMBER(G52),1+SUMPRODUCT(ISNUMBER($G52:$J52)*($G52:$J52<G52)),"") -> 2 | AB52: =IF(ISNUMBER(H52),1+SUMPRODUCT(ISNUMBER($G52:$J52)*($G52:$J52<H52)),"") | AC52: =IF(ISNUMBER(I52),1+SUMPRODUCT(ISNUMBER($G52:$J52)*($G52:$J52<I52)),"") | AD52: =IF(ISNUMBER(J52),1+SUMPRODUCT(ISNUMBER($G52:$J52)*($G52:$J52<J52)),"") -> 1 | AE52: =IF(NOT(ISNUMBER(G52)),0,IF($S52<2,5,IF(AA52=1,1,IF(G52=MAX($G52:$J52),4,IF(AA52=2,2,3))))) -> 4 | AF52: =IF(NOT(ISNUMBER(H52)),0,IF($S52<2,5,IF(AB52=1,1,IF(H52=MAX($G52:$J52),4,IF(AB52=2,2,3))))) -> 0 | AG52: =IF(NOT(ISNUMBER(I52)),0,IF($S52<2,5,IF(AC52=1,1,IF(I52=MAX($G52:$J52),4,IF(AC52=2,2,3))))) -> 0 | AH52: =IF(NOT(ISNUMBER(J52)),0,IF($S52<2,5,IF(AD52=1,1,IF(J52=MAX($G52:$J52),4,IF(AD52=2,2,3))))) -> 1 | AI52: =IF($S52>=2,IF(ISNUMBER(G52),G52*$F52,MIN($G52:$J52)*$F52),0) -> 1033.09 | AJ52: =IF($S52>=2,IF(ISNUMBER(H52),H52*$F52,MIN($G52:$J52)*$F52),0) -> 940 | AK52: =IF($S52>=2,IF(ISNUMBER(I52),I52*$F52,MIN($G52:$J52)*$F52),0) -> 940 | AL52: =IF($S52>=2,IF(ISNUMBER(J52),J52*$F52,MIN($G52:$J52)*$F52),0) -> 940 | AM52: =IF($S52>=2,$R52+ROW()/1000000,"") -> 93.090052 | AN52: =IF($S52>=2,MAX(G52:J52),"") -> 1033.09 | AO52: =IF($S52>=2,INDEX($G$6:$J$6,MATCH(MAX(G52:J52),G52:J52,0)),"") -> Ferguson | AP52: =IF($S52>=2,MIN(G52:J52)*$F52,0) -> 940 | AQ52: =IF($S52>=2,INDEX($G$6:$J$6,MATCH(MIN(G52:J52),G52:J52,0)),"") -> Scholzen
A53: R046 | B53: Item 5 | C53: DI spools | D53: 12" x 2'-0" flange x PE DI spool | E53: EA | F53: 1 | G53: — | H53: =IF(COUNTIF('Quote Lines'!$P$3:$P$805,$A53&"|"&H$6&"|1")=0,"—",SUMIFS('Quote Lines'!$O$3:$O$805,'Quote Lines'!$P$3:$P$805,$A53&"|"&H$6&"|1")/SUMIFS('Quote Lines'!$L$3:$L$805,'Quote Lines'!$P$3:$P$805,$A53&"|"&H$6&"|1")) -> 697.8 | I53: — | J53: — | K53: =IF(ISNUMBER(G53),G53*$F53,"—") -> — | L53: =IF(ISNUMBER(H53),H53*$F53,"—") -> 697.8 | M53: =IF(ISNUMBER(I53),I53*$F53,"—") -> — | N53: =IF(ISNUMBER(J53),J53*$F53,"—") -> — | O53: =IF($S53=0,"—",MIN(G53:J53)) -> 697.8 | P53: =IF($S53=0,"—",IF(COUNTIF(G53:J53,O53)>1,"Tie",INDEX($G$6:$J$6,MATCH(O53,G53:J53,0)))) -> HD Fowler | Q53: =IF($S53>=2,MAX(G53:J53)/MIN(G53:J53)-1,"—") -> — | R53: =IF($S53>=2,(MAX(G53:J53)-MIN(G53:J53))*$F53,"—") -> — | S53: =COUNT(G53:J53) -> 1 | T53: =IF($S53<=1,IF($S53=1,"Single quote","—"),"Like-for-like") -> Single quote | U53: =IF(COUNT(W53:Z53)<2,"",IF(MAX(W53:Z53)=MIN(W53:Z53),"OK","Qty differs")) | X53: =IF(COUNTIFS('Quote Lines'!$P$3:$P$805,$A53&"|"&H$6&"|1",'Quote Lines'!$M$3:$M$805,"Y")=0,"",SUMIFS('Quote Lines'!$L$3:$L$805,'Quote Lines'!$P$3:$P$805,$A53&"|"&H$6&"|1",'Quote Lines'!$M$3:$M$805,"Y")) -> 1 | AA53: =IF(ISNUMBER(G53),1+SUMPRODUCT(ISNUMBER($G53:$J53)*($G53:$J53<G53)),"") | AB53: =IF(ISNUMBER(H53),1+SUMPRODUCT(ISNUMBER($G53:$J53)*($G53:$J53<H53)),"") -> 1 | AC53: =IF(ISNUMBER(I53),1+SUMPRODUCT(ISNUMBER($G53:$J53)*($G53:$J53<I53)),"") | AD53: =IF(ISNUMBER(J53),1+SUMPRODUCT(ISNUMBER($G53:$J53)*($G53:$J53<J53)),"") | AE53: =IF(NOT(ISNUMBER(G53)),0,IF($S53<2,5,IF(AA53=1,1,IF(G53=MAX($G53:$J53),4,IF(AA53=2,2,3))))) -> 0 | AF53: =IF(NOT(ISNUMBER(H53)),0,IF($S53<2,5,IF(AB53=1,1,IF(H53=MAX($G53:$J53),4,IF(AB53=2,2,3))))) -> 5 | AG53: =IF(NOT(ISNUMBER(I53)),0,IF($S53<2,5,IF(AC53=1,1,IF(I53=MAX($G53:$J53),4,IF(AC53=2,2,3))))) -> 0 | AH53: =IF(NOT(ISNUMBER(J53)),0,IF($S53<2,5,IF(AD53=1,1,IF(J53=MAX($G53:$J53),4,IF(AD53=2,2,3))))) -> 0 | AI53: =IF($S53>=2,IF(ISNUMBER(G53),G53*$F53,MIN($G53:$J53)*$F53),0) -> 0 | AJ53: =IF($S53>=2,IF(ISNUMBER(H53),H53*$F53,MIN($G53:$J53)*$F53),0) -> 0 | AK53: =IF($S53>=2,IF(ISNUMBER(I53),I53*$F53,MIN($G53:$J53)*$F53),0) -> 0 | AL53: =IF($S53>=2,IF(ISNUMBER(J53),J53*$F53,MIN($G53:$J53)*$F53),0) -> 0 | AM53: =IF($S53>=2,$R53+ROW()/1000000,"") | AN53: =IF($S53>=2,MAX(G53:J53),"") | AO53: =IF($S53>=2,INDEX($G$6:$J$6,MATCH(MAX(G53:J53),G53:J53,0)),"") | AP53: =IF($S53>=2,MIN(G53:J53)*$F53,0) -> 0 | AQ53: =IF($S53>=2,INDEX($G$6:$J$6,MATCH(MIN(G53:J53),G53:J53,0)),"")
A54: R047 | B54: Item 5 | C54: DI spools | D54: 12" x 1'-6" flange x PE DI spool | E54: EA | F54: 1 | G54: — | H54: =IF(COUNTIF('Quote Lines'!$P$3:$P$805,$A54&"|"&H$6&"|1")=0,"—",SUMIFS('Quote Lines'!$O$3:$O$805,'Quote Lines'!$P$3:$P$805,$A54&"|"&H$6&"|1")/SUMIFS('Quote Lines'!$L$3:$L$805,'Quote Lines'!$P$3:$P$805,$A54&"|"&H$6&"|1")) -> 610.99 | I54: =IF(COUNTIF('Quote Lines'!$P$3:$P$805,$A54&"|"&I$6&"|1")=0,"—",SUMIFS('Quote Lines'!$O$3:$O$805,'Quote Lines'!$P$3:$P$805,$A54&"|"&I$6&"|1")/SUMIFS('Quote Lines'!$L$3:$L$805,'Quote Lines'!$P$3:$P$805,$A54&"|"&I$6&"|1")) -> 751.52 | J54: — | K54: =IF(ISNUMBER(G54),G54*$F54,"—") -> — | L54: =IF(ISNUMBER(H54),H54*$F54,"—") -> 610.99 | M54: =IF(ISNUMBER(I54),I54*$F54,"—") -> 751.52 | N54: =IF(ISNUMBER(J54),J54*$F54,"—") -> — | O54: =IF($S54=0,"—",MIN(G54:J54)) -> 610.99 | P54: =IF($S54=0,"—",IF(COUNTIF(G54:J54,O54)>1,"Tie",INDEX($G$6:$J$6,MATCH(O54,G54:J54,0)))) -> HD Fowler | Q54: =IF($S54>=2,MAX(G54:J54)/MIN(G54:J54)-1,"—") -> 0.23000376 | R54: =IF($S54>=2,(MAX(G54:J54)-MIN(G54:J54))*$F54,"—") -> 140.53 | S54: =COUNT(G54:J54) -> 2 | T54: =IF($S54<=1,IF($S54=1,"Single quote","—"),"Like-for-like") -> Like-for-like | U54: =IF(COUNT(W54:Z54)<2,"",IF(MAX(W54:Z54)=MIN(W54:Z54),"OK","Qty differs")) -> OK | X54: =IF(COUNTIFS('Quote Lines'!$P$3:$P$805,$A54&"|"&H$6&"|1",'Quote Lines'!$M$3:$M$805,"Y")=0,"",SUMIFS('Quote Lines'!$L$3:$L$805,'Quote Lines'!$P$3:$P$805,$A54&"|"&H$6&"|1",'Quote Lines'!$M$3:$M$805,"Y")) -> 1 | Y54: =IF(COUNTIFS('Quote Lines'!$P$3:$P$805,$A54&"|"&I$6&"|1",'Quote Lines'!$M$3:$M$805,"Y")=0,"",SUMIFS('Quote Lines'!$L$3:$L$805,'Quote Lines'!$P$3:$P$805,$A54&"|"&I$6&"|1",'Quote Lines'!$M$3:$M$805,"Y")) -> 1 | AA54: =IF(ISNUMBER(G54),1+SUMPRODUCT(ISNUMBER($G54:$J54)*($G54:$J54<G54)),"") | AB54: =IF(ISNUMBER(H54),1+SUMPRODUCT(ISNUMBER($G54:$J54)*($G54:$J54<H54)),"") -> 1 | AC54: =IF(ISNUMBER(I54),1+SUMPRODUCT(ISNUMBER($G54:$J54)*($G54:$J54<I54)),"") -> 2 | AD54: =IF(ISNUMBER(J54),1+SUMPRODUCT(ISNUMBER($G54:$J54)*($G54:$J54<J54)),"") | AE54: =IF(NOT(ISNUMBER(G54)),0,IF($S54<2,5,IF(AA54=1,1,IF(G54=MAX($G54:$J54),4,IF(AA54=2,2,3))))) -> 0 | AF54: =IF(NOT(ISNUMBER(H54)),0,IF($S54<2,5,IF(AB54=1,1,IF(H54=MAX($G54:$J54),4,IF(AB54=2,2,3))))) -> 1 | AG54: =IF(NOT(ISNUMBER(I54)),0,IF($S54<2,5,IF(AC54=1,1,IF(I54=MAX($G54:$J54),4,IF(AC54=2,2,3))))) -> 4 | AH54: =IF(NOT(ISNUMBER(J54)),0,IF($S54<2,5,IF(AD54=1,1,IF(J54=MAX($G54:$J54),4,IF(AD54=2,2,3))))) -> 0 | AI54: =IF($S54>=2,IF(ISNUMBER(G54),G54*$F54,MIN($G54:$J54)*$F54),0) -> 610.99 | AJ54: =IF($S54>=2,IF(ISNUMBER(H54),H54*$F54,MIN($G54:$J54)*$F54),0) -> 610.99 | AK54: =IF($S54>=2,IF(ISNUMBER(I54),I54*$F54,MIN($G54:$J54)*$F54),0) -> 751.52 | AL54: =IF($S54>=2,IF(ISNUMBER(J54),J54*$F54,MIN($G54:$J54)*$F54),0) -> 610.99 | AM54: =IF($S54>=2,$R54+ROW()/1000000,"") -> 140.53005 | AN54: =IF($S54>=2,MAX(G54:J54),"") -> 751.52 | AO54: =IF($S54>=2,INDEX($G$6:$J$6,MATCH(MAX(G54:J54),G54:J54,0)),"") -> Mountainland | AP54: =IF($S54>=2,MIN(G54:J54)*$F54,0) -> 610.99 | AQ54: =IF($S54>=2,INDEX($G$6:$J$6,MATCH(MIN(G54:J54),G54:J54,0)),"") -> HD Fowler
A55: R048 | B55: Item 5 | C55: DI spools | D55: 12" x 0'-10" flange x PE DI spool | E55: EA | F55: 1 | G55: — | H55: — | I55: — | J55: =IF(COUNTIF('Quote Lines'!$P$3:$P$805,$A55&"|"&J$6&"|1")=0,"—",SUMIFS('Quote Lines'!$O$3:$O$805,'Quote Lines'!$P$3:$P$805,$A55&"|"&J$6&"|1")/SUMIFS('Quote Lines'!$L$3:$L$805,'Quote Lines'!$P$3:$P$805,$A55&"|"&J$6&"|1")) -> 628 | K55: =IF(ISNUMBER(G55),G55*$F55,"—") -> — | L55: =IF(ISNUMBER(H55),H55*$F55,"—") -> — | M55: =IF(ISNUMBER(I55),I55*$F55,"—") -> — | N55: =IF(ISNUMBER(J55),J55*$F55,"—") -> 628 | O55: =IF($S55=0,"—",MIN(G55:J55)) -> 628 | P55: =IF($S55=0,"—",IF(COUNTIF(G55:J55,O55)>1,"Tie",INDEX($G$6:$J$6,MATCH(O55,G55:J55,0)))) -> Scholzen | Q55: =IF($S55>=2,MAX(G55:J55)/MIN(G55:J55)-1,"—") -> — | R55: =IF($S55>=2,(MAX(G55:J55)-MIN(G55:J55))*$F55,"—") -> — | S55: =COUNT(G55:J55) -> 1 | T55: =IF($S55<=1,IF($S55=1,"Single quote","—"),"Like-for-like") -> Single quote | U55: =IF(COUNT(W55:Z55)<2,"",IF(MAX(W55:Z55)=MIN(W55:Z55),"OK","Qty differs")) | Z55: =IF(COUNTIFS('Quote Lines'!$P$3:$P$805,$A55&"|"&J$6&"|1",'Quote Lines'!$M$3:$M$805,"Y")=0,"",SUMIFS('Quote Lines'!$L$3:$L$805,'Quote Lines'!$P$3:$P$805,$A55&"|"&J$6&"|1",'Quote Lines'!$M$3:$M$805,"Y")) -> 1 | AA55: =IF(ISNUMBER(G55),1+SUMPRODUCT(ISNUMBER($G55:$J55)*($G55:$J55<G55)),"") | AB55: =IF(ISNUMBER(H55),1+SUMPRODUCT(ISNUMBER($G55:$J55)*($G55:$J55<H55)),"") | AC55: =IF(ISNUMBER(I55),1+SUMPRODUCT(ISNUMBER($G55:$J55)*($G55:$J55<I55)),"") | AD55: =IF(ISNUMBER(J55),1+SUMPRODUCT(ISNUMBER($G55:$J55)*($G55:$J55<J55)),"") -> 1 | AE55: =IF(NOT(ISNUMBER(G55)),0,IF($S55<2,5,IF(AA55=1,1,IF(G55=MAX($G55:$J55),4,IF(AA55=2,2,3))))) -> 0 | AF55: =IF(NOT(ISNUMBER(H55)),0,IF($S55<2,5,IF(AB55=1,1,IF(H55=MAX($G55:$J55),4,IF(AB55=2,2,3))))) -> 0 | AG55: =IF(NOT(ISNUMBER(I55)),0,IF($S55<2,5,IF(AC55=1,1,IF(I55=MAX($G55:$J55),4,IF(AC55=2,2,3))))) -> 0 | AH55: =IF(NOT(ISNUMBER(J55)),0,IF($S55<2,5,IF(AD55=1,1,IF(J55=MAX($G55:$J55),4,IF(AD55=2,2,3))))) -> 5 | AI55: =IF($S55>=2,IF(ISNUMBER(G55),G55*$F55,MIN($G55:$J55)*$F55),0) -> 0 | AJ55: =IF($S55>=2,IF(ISNUMBER(H55),H55*$F55,MIN($G55:$J55)*$F55),0) -> 0 | AK55: =IF($S55>=2,IF(ISNUMBER(I55),I55*$F55,MIN($G55:$J55)*$F55),0) -> 0 | AL55: =IF($S55>=2,IF(ISNUMBER(J55),J55*$F55,MIN($G55:$J55)*$F55),0) -> 0 | AM55: =IF($S55>=2,$R55+ROW()/1000000,"") | AN55: =IF($S55>=2,MAX(G55:J55),"") | AO55: =IF($S55>=2,INDEX($G$6:$J$6,MATCH(MAX(G55:J55),G55:J55,0)),"") | AP55: =IF($S55>=2,MIN(G55:J55)*$F55,0) -> 0 | AQ55: =IF($S55>=2,INDEX($G$6:$J$6,MATCH(MIN(G55:J55),G55:J55,0)),"")
A56: R049 | B56: Item 5 | C56: DI spools | D56: 12" x 4'-0" PE x PE DI spool | E56: EA | F56: 1 | G56: — | H56: =IF(COUNTIF('Quote Lines'!$P$3:$P$805,$A56&"|"&H$6&"|1")=0,"—",SUMIFS('Quote Lines'!$O$3:$O$805,'Quote Lines'!$P$3:$P$805,$A56&"|"&H$6&"|1")/SUMIFS('Quote Lines'!$L$3:$L$805,'Quote Lines'!$P$3:$P$805,$A56&"|"&H$6&"|1")) -> 727.47 | I56: — | J56: — | K56: =IF(ISNUMBER(G56),G56*$F56,"—") -> — | L56: =IF(ISNUMBER(H56),H56*$F56,"—") -> 727.47 | M56: =IF(ISNUMBER(I56),I56*$F56,"—") -> — | N56: =IF(ISNUMBER(J56),J56*$F56,"—") -> — | O56: =IF($S56=0,"—",MIN(G56:J56)) -> 727.47 | P56: =IF($S56=0,"—",IF(COUNTIF(G56:J56,O56)>1,"Tie",INDEX($G$6:$J$6,MATCH(O56,G56:J56,0)))) -> HD Fowler | Q56: =IF($S56>=2,MAX(G56:J56)/MIN(G56:J56)-1,"—") -> — | R56: =IF($S56>=2,(MAX(G56:J56)-MIN(G56:J56))*$F56,"—") -> — | S56: =COUNT(G56:J56) -> 1 | T56: =IF($S56<=1,IF($S56=1,"Single quote","—"),"Like-for-like") -> Single quote | U56: =IF(COUNT(W56:Z56)<2,"",IF(MAX(W56:Z56)=MIN(W56:Z56),"OK","Qty differs")) | X56: =IF(COUNTIFS('Quote Lines'!$P$3:$P$805,$A56&"|"&H$6&"|1",'Quote Lines'!$M$3:$M$805,"Y")=0,"",SUMIFS('Quote Lines'!$L$3:$L$805,'Quote Lines'!$P$3:$P$805,$A56&"|"&H$6&"|1",'Quote Lines'!$M$3:$M$805,"Y")) -> 1 | AA56: =IF(ISNUMBER(G56),1+SUMPRODUCT(ISNUMBER($G56:$J56)*($G56:$J56<G56)),"") | AB56: =IF(ISNUMBER(H56),1+SUMPRODUCT(ISNUMBER($G56:$J56)*($G56:$J56<H56)),"") -> 1 | AC56: =IF(ISNUMBER(I56),1+SUMPRODUCT(ISNUMBER($G56:$J56)*($G56:$J56<I56)),"") | AD56: =IF(ISNUMBER(J56),1+SUMPRODUCT(ISNUMBER($G56:$J56)*($G56:$J56<J56)),"") | AE56: =IF(NOT(ISNUMBER(G56)),0,IF($S56<2,5,IF(AA56=1,1,IF(G56=MAX($G56:$J56),4,IF(AA56=2,2,3))))) -> 0 | AF56: =IF(NOT(ISNUMBER(H56)),0,IF($S56<2,5,IF(AB56=1,1,IF(H56=MAX($G56:$J56),4,IF(AB56=2,2,3))))) -> 5 | AG56: =IF(NOT(ISNUMBER(I56)),0,IF($S56<2,5,IF(AC56=1,1,IF(I56=MAX($G56:$J56),4,IF(AC56=2,2,3))))) -> 0 | AH56: =IF(NOT(ISNUMBER(J56)),0,IF($S56<2,5,IF(AD56=1,1,IF(J56=MAX($G56:$J56),4,IF(AD56=2,2,3))))) -> 0 | AI56: =IF($S56>=2,IF(ISNUMBER(G56),G56*$F56,MIN($G56:$J56)*$F56),0) -> 0 | AJ56: =IF($S56>=2,IF(ISNUMBER(H56),H56*$F56,MIN($G56:$J56)*$F56),0) -> 0 | AK56: =IF($S56>=2,IF(ISNUMBER(I56),I56*$F56,MIN($G56:$J56)*$F56),0) -> 0 | AL56: =IF($S56>=2,IF(ISNUMBER(J56),J56*$F56,MIN($G56:$J56)*$F56),0) -> 0 | AM56: =IF($S56>=2,$R56+ROW()/1000000,"") | AN56: =IF($S56>=2,MAX(G56:J56),"") | AO56: =IF($S56>=2,INDEX($G$6:$J$6,MATCH(MAX(G56:J56),G56:J56,0)),"") | AP56: =IF($S56>=2,MIN(G56:J56)*$F56,0) -> 0 | AQ56: =IF($S56>=2,INDEX($G$6:$J$6,MATCH(MIN(G56:J56),G56:J56,0)),"")
A57: R050 | B57: Item 5 | C57: Valves | D57: 8" Cla-Val 131 electronic control valve + VC-22D controller | E57: EA | F57: 1 | G57: =IF(COUNTIF('Quote Lines'!$P$3:$P$805,$A57&"|"&G$6&"|1")=0,"—",SUMIFS('Quote Lines'!$O$3:$O$805,'Quote Lines'!$P$3:$P$805,$A57&"|"&G$6&"|1")/SUMIFS('Quote Lines'!$L$3:$L$805,'Quote Lines'!$P$3:$P$805,$A57&"|"&G$6&"|1")) -> 37321.6 | H57: =IF(COUNTIF('Quote Lines'!$P$3:$P$805,$A57&"|"&H$6&"|1")=0,"—",SUMIFS('Quote Lines'!$O$3:$O$805,'Quote Lines'!$P$3:$P$805,$A57&"|"&H$6&"|1")/SUMIFS('Quote Lines'!$L$3:$L$805,'Quote Lines'!$P$3:$P$805,$A57&"|"&H$6&"|1")+IFERROR(SUMIFS('Quote Lines'!$O$3:$O$805,'Quote Lines'!$P$3:$P$805,$A57&"|"&H$6&"|2")/SUMIFS('Quote Lines'!$L$3:$L$805,'Quote Lines'!$P$3:$P$805,$A57&"|"&H$6&"|2"),0)) -> 28455.61 | I57: =IF(COUNTIF('Quote Lines'!$P$3:$P$805,$A57&"|"&I$6&"|1")=0,"—",SUMIFS('Quote Lines'!$O$3:$O$805,'Quote Lines'!$P$3:$P$805,$A57&"|"&I$6&"|1")/SUMIFS('Quote Lines'!$L$3:$L$805,'Quote Lines'!$P$3:$P$805,$A57&"|"&I$6&"|1")+IFERROR(SUMIFS('Quote Lines'!$O$3:$O$805,'Quote Lines'!$P$3:$P$805,$A57&"|"&I$6&"|2")/SUMIFS('Quote Lines'!$L$3:$L$805,'Quote Lines'!$P$3:$P$805,$A57&"|"&I$6&"|2"),0)) -> 27719.12 | J57: =IF(COUNTIF('Quote Lines'!$P$3:$P$805,$A57&"|"&J$6&"|1")=0,"—",SUMIFS('Quote Lines'!$O$3:$O$805,'Quote Lines'!$P$3:$P$805,$A57&"|"&J$6&"|1")/SUMIFS('Quote Lines'!$L$3:$L$805,'Quote Lines'!$P$3:$P$805,$A57&"|"&J$6&"|1")) -> 31000 | K57: =IF(ISNUMBER(G57),G57*$F57,"—") -> 37321.6 | L57: =IF(ISNUMBER(H57),H57*$F57,"—") -> 28455.61 | M57: =IF(ISNUMBER(I57),I57*$F57,"—") -> 27719.12 | N57: =IF(ISNUMBER(J57),J57*$F57,"—") -> 31000 | O57: =IF($S57=0,"—",MIN(G57:J57)) -> 27719.12 | P57: =IF($S57=0,"—",IF(COUNTIF(G57:J57,O57)>1,"Tie",INDEX($G$6:$J$6,MATCH(O57,G57:J57,0)))) -> Mountainland | Q57: =IF($S57>=2,MAX(G57:J57)/MIN(G57:J57)-1,"—") -> 0.34642081 | R57: =IF($S57>=2,(MAX(G57:J57)-MIN(G57:J57))*$F57,"—") -> 9602.48 | S57: =COUNT(G57:J57) -> 4 | T57: =IF($S57<=1,IF($S57=1,"Single quote","—"),"Alt spec – verify") -> Alt spec – verify | U57: =IF(COUNT(W57:Z57)<2,"",IF(MAX(W57:Z57)=MIN(W57:Z57),"OK","Qty differs")) -> OK | V57: H = 120V solenoid; M = 24VDC normally-open. Valve + controller priced as one set. Confirm spec / owner-furnished status. | W57: =IF(COUNTIFS('Quote Lines'!$P$3:$P$805,$A57&"|"&G$6&"|1",'Quote Lines'!$M$3:$M$805,"Y")=0,"",SUMIFS('Quote Lines'!$L$3:$L$805,'Quote Lines'!$P$3:$P$805,$A57&"|"&G$6&"|1",'Quote Lines'!$M$3:$M$805,"Y")) -> 1 | X57: =IF(COUNTIFS('Quote Lines'!$P$3:$P$805,$A57&"|"&H$6&"|1",'Quote Lines'!$M$3:$M$805,"Y")=0,"",SUMIFS('Quote Lines'!$L$3:$L$805,'Quote Lines'!$P$3:$P$805,$A57&"|"&H$6&"|1",'Quote Lines'!$M$3:$M$805,"Y")) -> 1 | Y57: =IF(COUNTIFS('Quote Lines'!$P$3:$P$805,$A57&"|"&I$6&"|1",'Quote Lines'!$M$3:$M$805,"Y")=0,"",SUMIFS('Quote Lines'!$L$3:$L$805,'Quote Lines'!$P$3:$P$805,$A57&"|"&I$6&"|1",'Quote Lines'!$M$3:$M$805,"Y")) -> 1 | Z57: =IF(COUNTIFS('Quote Lines'!$P$3:$P$805,$A57&"|"&J$6&"|1",'Quote Lines'!$M$3:$M$805,"Y")=0,"",SUMIFS('Quote Lines'!$L$3:$L$805,'Quote Lines'!$P$3:$P$805,$A57&"|"&J$6&"|1",'Quote Lines'!$M$3:$M$805,"Y")) -> 1 | AA57: =IF(ISNUMBER(G57),1+SUMPRODUCT(ISNUMBER($G57:$J57)*($G57:$J57<G57)),"") -> 4 | AB57: =IF(ISNUMBER(H57),1+SUMPRODUCT(ISNUMBER($G57:$J57)*($G57:$J57<H57)),"") -> 2 | AC57: =IF(ISNUMBER(I57),1+SUMPRODUCT(ISNUMBER($G57:$J57)*($G57:$J57<I57)),"") -> 1 | AD57: =IF(ISNUMBER(J57),1+SUMPRODUCT(ISNUMBER($G57:$J57)*($G57:$J57<J57)),"") -> 3 | AE57: =IF(NOT(ISNUMBER(G57)),0,IF($S57<2,5,IF(AA57=1,1,IF(G57=MAX($G57:$J57),4,IF(AA57=2,2,3))))) -> 4 | AF57: =IF(NOT(ISNUMBER(H57)),0,IF($S57<2,5,IF(AB57=1,1,IF(H57=MAX($G57:$J57),4,IF(AB57=2,2,3))))) -> 2 | AG57: =IF(NOT(ISNUMBER(I57)),0,IF($S57<2,5,IF(AC57=1,1,IF(I57=MAX($G57:$J57),4,IF(AC57=2,2,3))))) -> 1 | AH57: =IF(NOT(ISNUMBER(J57)),0,IF($S57<2,5,IF(AD57=1,1,IF(J57=MAX($G57:$J57),4,IF(AD57=2,2,3))))) -> 3 | AI57: =IF($S57>=2,IF(ISNUMBER(G57),G57*$F57,MIN($G57:$J57)*$F57),0) -> 37321.6 | AJ57: =IF($S57>=2,IF(ISNUMBER(H57),H57*$F57,MIN($G57:$J57)*$F57),0) -> 28455.61 | AK57: =IF($S57>=2,IF(ISNUMBER(I57),I57*$F57,MIN($G57:$J57)*$F57),0) -> 27719.12 | AL57: =IF($S57>=2,IF(ISNUMBER(J57),J57*$F57,MIN($G57:$J57)*$F57),0) -> 31000 | AM57: =IF($S57>=2,$R57+ROW()/1000000,"") -> 9602.4801 | AN57: =IF($S57>=2,MAX(G57:J57),"") -> 37321.6 | AO57: =IF($S57>=2,INDEX($G$6:$J$6,MATCH(MAX(G57:J57),G57:J57,0)),"") -> Ferguson | AP57: =IF($S57>=2,MIN(G57:J57)*$F57,0) -> 27719.12 | AQ57: =IF($S57>=2,INDEX($G$6:$J$6,MATCH(MIN(G57:J57),G57:J57,0)),"") -> Mountainland
A58: R051 | B58: Item 5 | C58: Valves | D58: 8" wafer / lug butterfly valve, gear operator | E58: EA | F58: 2 | G58: =IF(COUNTIF('Quote Lines'!$P$3:$P$805,$A58&"|"&G$6&"|1")=0,"—",SUMIFS('Quote Lines'!$O$3:$O$805,'Quote Lines'!$P$3:$P$805,$A58&"|"&G$6&"|1")/SUMIFS('Quote Lines'!$L$3:$L$805,'Quote Lines'!$P$3:$P$805,$A58&"|"&G$6&"|1")) -> 618.75 | H58: =IF(COUNTIF('Quote Lines'!$P$3:$P$805,$A58&"|"&H$6&"|1")=0,"—",SUMIFS('Quote Lines'!$O$3:$O$805,'Quote Lines'!$P$3:$P$805,$A58&"|"&H$6&"|1")/SUMIFS('Quote Lines'!$L$3:$L$805,'Quote Lines'!$P$3:$P$805,$A58&"|"&H$6&"|1")) -> 612.7 | I58: =IF(COUNTIF('Quote Lines'!$P$3:$P$805,$A58&"|"&I$6&"|1")=0,"—",SUMIFS('Quote Lines'!$O$3:$O$805,'Quote Lines'!$P$3:$P$805,$A58&"|"&I$6&"|1")/SUMIFS('Quote Lines'!$L$3:$L$805,'Quote Lines'!$P$3:$P$805,$A58&"|"&I$6&"|1")) -> 657.425 | J58: — | K58: =IF(ISNUMBER(G58),G58*$F58,"—") -> 1237.5 | L58: =IF(ISNUMBER(H58),H58*$F58,"—") -> 1225.4 | M58: =IF(ISNUMBER(I58),I58*$F58,"—") -> 1314.85 | N58: =IF(ISNUMBER(J58),J58*$F58,"—") -> — | O58: =IF($S58=0,"—",MIN(G58:J58)) -> 612.7 | P58: =IF($S58=0,"—",IF(COUNTIF(G58:J58,O58)>1,"Tie",INDEX($G$6:$J$6,MATCH(O58,G58:J58,0)))) -> HD Fowler | Q58: =IF($S58>=2,MAX(G58:J58)/MIN(G58:J58)-1,"—") -> 0.072996573 | R58: =IF($S58>=2,(MAX(G58:J58)-MIN(G58:J58))*$F58,"—") -> 89.45 | S58: =COUNT(G58:J58) -> 3 | T58: =IF($S58<=1,IF($S58=1,"Single quote","—"),"Like-for-like") -> Like-for-like | U58: =IF(COUNT(W58:Z58)<2,"",IF(MAX(W58:Z58)=MIN(W58:Z58),"OK","Qty differs")) -> OK | W58: =IF(COUNTIFS('Quote Lines'!$P$3:$P$805,$A58&"|"&G$6&"|1",'Quote Lines'!$M$3:$M$805,"Y")=0,"",SUMIFS('Quote Lines'!$L$3:$L$805,'Quote Lines'!$P$3:$P$805,$A58&"|"&G$6&"|1",'Quote Lines'!$M$3:$M$805,"Y")) -> 2 | X58: =IF(COUNTIFS('Quote Lines'!$P$3:$P$805,$A58&"|"&H$6&"|1",'Quote Lines'!$M$3:$M$805,"Y")=0,"",SUMIFS('Quote Lines'!$L$3:$L$805,'Quote Lines'!$P$3:$P$805,$A58&"|"&H$6&"|1",'Quote Lines'!$M$3:$M$805,"Y")) -> 2 | Y58: =IF(COUNTIFS('Quote Lines'!$P$3:$P$805,$A58&"|"&I$6&"|1",'Quote Lines'!$M$3:$M$805,"Y")=0,"",SUMIFS('Quote Lines'!$L$3:$L$805,'Quote Lines'!$P$3:$P$805,$A58&"|"&I$6&"|1",'Quote Lines'!$M$3:$M$805,"Y")) -> 2 | AA58: =IF(ISNUMBER(G58),1+SUMPRODUCT(ISNUMBER($G58:$J58)*($G58:$J58<G58)),"") -> 2 | AB58: =IF(ISNUMBER(H58),1+SUMPRODUCT(ISNUMBER($G58:$J58)*($G58:$J58<H58)),"") -> 1 | AC58: =IF(ISNUMBER(I58),1+SUMPRODUCT(ISNUMBER($G58:$J58)*($G58:$J58<I58)),"") -> 3 | AD58: =IF(ISNUMBER(J58),1+SUMPRODUCT(ISNUMBER($G58:$J58)*($G58:$J58<J58)),"") | AE58: =IF(NOT(ISNUMBER(G58)),0,IF($S58<2,5,IF(AA58=1,1,IF(G58=MAX($G58:$J58),4,IF(AA58=2,2,3))))) -> 2 | AF58: =IF(NOT(ISNUMBER(H58)),0,IF($S58<2,5,IF(AB58=1,1,IF(H58=MAX($G58:$J58),4,IF(AB58=2,2,3))))) -> 1 | AG58: =IF(NOT(ISNUMBER(I58)),0,IF($S58<2,5,IF(AC58=1,1,IF(I58=MAX($G58:$J58),4,IF(AC58=2,2,3))))) -> 4 | AH58: =IF(NOT(ISNUMBER(J58)),0,IF($S58<2,5,IF(AD58=1,1,IF(J58=MAX($G58:$J58),4,IF(AD58=2,2,3))))) -> 0 | AI58: =IF($S58>=2,IF(ISNUMBER(G58),G58*$F58,MIN($G58:$J58)*$F58),0) -> 1237.5 | AJ58: =IF($S58>=2,IF(ISNUMBER(H58),H58*$F58,MIN($G58:$J58)*$F58),0) -> 1225.4 | AK58: =IF($S58>=2,IF(ISNUMBER(I58),I58*$F58,MIN($G58:$J58)*$F58),0) -> 1314.85 | AL58: =IF($S58>=2,IF(ISNUMBER(J58),J58*$F58,MIN($G58:$J58)*$F58),0) -> 1225.4 | AM58: =IF($S58>=2,$R58+ROW()/1000000,"") -> 89.450058 | AN58: =IF($S58>=2,MAX(G58:J58),"") -> 657.425 | AO58: =IF($S58>=2,INDEX($G$6:$J$6,MATCH(MAX(G58:J58),G58:J58,0)),"") -> Mountainland | AP58: =IF($S58>=2,MIN(G58:J58)*$F58,0) -> 1225.4 | AQ58: =IF($S58>=2,INDEX($G$6:$J$6,MATCH(MIN(G58:J58),G58:J58,0)),"") -> HD Fowler
A59: R052 | B59: Item 5 | C59: Valves | D59: 12" AV-TEK double-eccentric butterfly valve w/ electric actuator | E59: EA | F59: 1 | G59: =IF(COUNTIF('Quote Lines'!$P$3:$P$805,$A59&"|"&G$6&"|1")=0,"—",SUMIFS('Quote Lines'!$O$3:$O$805,'Quote Lines'!$P$3:$P$805,$A59&"|"&G$6&"|1")/SUMIFS('Quote Lines'!$L$3:$L$805,'Quote Lines'!$P$3:$P$805,$A59&"|"&G$6&"|1")) -> 19472.57 | H59: =IF(COUNTIF('Quote Lines'!$P$3:$P$805,$A59&"|"&H$6&"|1")=0,"—",SUMIFS('Quote Lines'!$O$3:$O$805,'Quote Lines'!$P$3:$P$805,$A59&"|"&H$6&"|1")/SUMIFS('Quote Lines'!$L$3:$L$805,'Quote Lines'!$P$3:$P$805,$A59&"|"&H$6&"|1")) -> 18442.4 | I59: — | J59: =IF(COUNTIF('Quote Lines'!$P$3:$P$805,$A59&"|"&J$6&"|1")=0,"—",SUMIFS('Quote Lines'!$O$3:$O$805,'Quote Lines'!$P$3:$P$805,$A59&"|"&J$6&"|1")/SUMIFS('Quote Lines'!$L$3:$L$805,'Quote Lines'!$P$3:$P$805,$A59&"|"&J$6&"|1")) -> 20159.85 | K59: =IF(ISNUMBER(G59),G59*$F59,"—") -> 19472.57 | L59: =IF(ISNUMBER(H59),H59*$F59,"—") -> 18442.4 | M59: =IF(ISNUMBER(I59),I59*$F59,"—") -> — | N59: =IF(ISNUMBER(J59),J59*$F59,"—") -> 20159.85 | O59: =IF($S59=0,"—",MIN(G59:J59)) -> 18442.4 | P59: =IF($S59=0,"—",IF(COUNTIF(G59:J59,O59)>1,"Tie",INDEX($G$6:$J$6,MATCH(O59,G59:J59,0)))) -> HD Fowler | Q59: =IF($S59>=2,MAX(G59:J59)/MIN(G59:J59)-1,"—") -> 0.093125081 | R59: =IF($S59>=2,(MAX(G59:J59)-MIN(G59:J59))*$F59,"—") -> 1717.45 | S59: =COUNT(G59:J59) -> 3 | T59: =IF($S59<=1,IF($S59=1,"Single quote","—"),"Like-for-like") -> Like-for-like | U59: =IF(COUNT(W59:Z59)<2,"",IF(MAX(W59:Z59)=MIN(W59:Z59),"OK","Qty differs")) -> OK | W59: =IF(COUNTIFS('Quote Lines'!$P$3:$P$805,$A59&"|"&G$6&"|1",'Quote Lines'!$M$3:$M$805,"Y")=0,"",SUMIFS('Quote Lines'!$L$3:$L$805,'Quote Lines'!$P$3:$P$805,$A59&"|"&G$6&"|1",'Quote Lines'!$M$3:$M$805,"Y")) -> 1 | X59: =IF(COUNTIFS('Quote Lines'!$P$3:$P$805,$A59&"|"&H$6&"|1",'Quote Lines'!$M$3:$M$805,"Y")=0,"",SUMIFS('Quote Lines'!$L$3:$L$805,'Quote Lines'!$P$3:$P$805,$A59&"|"&H$6&"|1",'Quote Lines'!$M$3:$M$805,"Y")) -> 1 | Z59: =IF(COUNTIFS('Quote Lines'!$P$3:$P$805,$A59&"|"&J$6&"|1",'Quote Lines'!$M$3:$M$805,"Y")=0,"",SUMIFS('Quote Lines'!$L$3:$L$805,'Quote Lines'!$P$3:$P$805,$A59&"|"&J$6&"|1",'Quote Lines'!$M$3:$M$805,"Y")) -> 1 | AA59: =IF(ISNUMBER(G59),1+SUMPRODUCT(ISNUMBER($G59:$J59)*($G59:$J59<G59)),"") -> 2 | AB59: =IF(ISNUMBER(H59),1+SUMPRODUCT(ISNUMBER($G59:$J59)*($G59:$J59<H59)),"") -> 1 | AC59: =IF(ISNUMBER(I59),1+SUMPRODUCT(ISNUMBER($G59:$J59)*($G59:$J59<I59)),"") | AD59: =IF(ISNUMBER(J59),1+SUMPRODUCT(ISNUMBER($G59:$J59)*($G59:$J59<J59)),"") -> 3 | AE59: =IF(NOT(ISNUMBER(G59)),0,IF($S59<2,5,IF(AA59=1,1,IF(G59=MAX($G59:$J59),4,IF(AA59=2,2,3))))) -> 2 | AF59: =IF(NOT(ISNUMBER(H59)),0,IF($S59<2,5,IF(AB59=1,1,IF(H59=MAX($G59:$J59),4,IF(AB59=2,2,3))))) -> 1 | AG59: =IF(NOT(ISNUMBER(I59)),0,IF($S59<2,5,IF(AC59=1,1,IF(I59=MAX($G59:$J59),4,IF(AC59=2,2,3))))) -> 0 | AH59: =IF(NOT(ISNUMBER(J59)),0,IF($S59<2,5,IF(AD59=1,1,IF(J59=MAX($G59:$J59),4,IF(AD59=2,2,3))))) -> 4 | AI59: =IF($S59>=2,IF(ISNUMBER(G59),G59*$F59,MIN($G59:$J59)*$F59),0) -> 19472.57 | AJ59: =IF($S59>=2,IF(ISNUMBER(H59),H59*$F59,MIN($G59:$J59)*$F59),0) -> 18442.4 | AK59: =IF($S59>=2,IF(ISNUMBER(I59),I59*$F59,MIN($G59:$J59)*$F59),0) -> 18442.4 | AL59: =IF($S59>=2,IF(ISNUMBER(J59),J59*$F59,MIN($G59:$J59)*$F59),0) -> 20159.85 | AM59: =IF($S59>=2,$R59+ROW()/1000000,"") -> 1717.4501 | AN59: =IF($S59>=2,MAX(G59:J59),"") -> 20159.85 | AO59: =IF($S59>=2,INDEX($G$6:$J$6,MATCH(MAX(G59:J59),G59:J59,0)),"") -> Scholzen | AP59: =IF($S59>=2,MIN(G59:J59)*$F59,0) -> 18442.4 | AQ59: =IF($S59>=2,INDEX($G$6:$J$6,MATCH(MIN(G59:J59),G59:J59,0)),"") -> HD Fowler
A60: R053 | B60: Item 5 | C60: Valves | D60: 12" AV-TEK double-eccentric butterfly valve, NO actuator | E60: EA | F60: 1 | G60: — | H60: — | I60: =IF(COUNTIF('Quote Lines'!$P$3:$P$805,$A60&"|"&I$6&"|1")=0,"—",SUMIFS('Quote Lines'!$O$3:$O$805,'Quote Lines'!$P$3:$P$805,$A60&"|"&I$6&"|1")/SUMIFS('Quote Lines'!$L$3:$L$805,'Quote Lines'!$P$3:$P$805,$A60&"|"&I$6&"|1")) -> 6451.76 | J60: — | K60: =IF(ISNUMBER(G60),G60*$F60,"—") -> — | L60: =IF(ISNUMBER(H60),H60*$F60,"—") -> — | M60: =IF(ISNUMBER(I60),I60*$F60,"—") -> 6451.76 | N60: =IF(ISNUMBER(J60),J60*$F60,"—") -> — | O60: =IF($S60=0,"—",MIN(G60:J60)) -> 6451.76 | P60: =IF($S60=0,"—",IF(COUNTIF(G60:J60,O60)>1,"Tie",INDEX($G$6:$J$6,MATCH(O60,G60:J60,0)))) -> Mountainland | Q60: =IF($S60>=2,MAX(G60:J60)/MIN(G60:J60)-1,"—") -> — | R60: =IF($S60>=2,(MAX(G60:J60)-MIN(G60:J60))*$F60,"—") -> — | S60: =COUNT(G60:J60) -> 1 | T60: =IF($S60<=1,IF($S60=1,"Single quote","—"),"Alt spec – verify") -> Single quote | U60: =IF(COUNT(W60:Z60)<2,"",IF(MAX(W60:Z60)=MIN(W60:Z60),"OK","Qty differs")) | V60: Mountainland quoted the valve without an electric actuator - not comparable to the actuated valves above. | Y60: =IF(COUNTIFS('Quote Lines'!$P$3:$P$805,$A60&"|"&I$6&"|1",'Quote Lines'!$M$3:$M$805,"Y")=0,"",SUMIFS('Quote Lines'!$L$3:$L$805,'Quote Lines'!$P$3:$P$805,$A60&"|"&I$6&"|1",'Quote Lines'!$M$3:$M$805,"Y")) -> 1 | AA60: =IF(ISNUMBER(G60),1+SUMPRODUCT(ISNUMBER($G60:$J60)*($G60:$J60<G60)),"") | AB60: =IF(ISNUMBER(H60),1+SUMPRODUCT(ISNUMBER($G60:$J60)*($G60:$J60<H60)),"") | AC60: =IF(ISNUMBER(I60),1+SUMPRODUCT(ISNUMBER($G60:$J60)*($G60:$J60<I60)),"") -> 1 | AD60: =IF(ISNUMBER(J60),1+SUMPRODUCT(ISNUMBER($G60:$J60)*($G60:$J60<J60)),"") | AE60: =IF(NOT(ISNUMBER(G60)),0,IF($S60<2,5,IF(AA60=1,1,IF(G60=MAX($G60:$J60),4,IF(AA60=2,2,3))))) -> 0 | AF60: =IF(NOT(ISNUMBER(H60)),0,IF($S60<2,5,IF(AB60=1,1,IF(H60=MAX($G60:$J60),4,IF(AB60=2,2,3))))) -> 0 | AG60: =IF(NOT(ISNUMBER(I60)),0,IF($S60<2,5,IF(AC60=1,1,IF(I60=MAX($G60:$J60),4,IF(AC60=2,2,3))))) -> 5 | AH60: =IF(NOT(ISNUMBER(J60)),0,IF($S60<2,5,IF(AD60=1,1,IF(J60=MAX($G60:$J60),4,IF(AD60=2,2,3))))) -> 0 | AI60: =IF($S60>=2,IF(ISNUMBER(G60),G60*$F60,MIN($G60:$J60)*$F60),0) -> 0 | AJ60: =IF($S60>=2,IF(ISNUMBER(H60),H60*$F60,MIN($G60:$J60)*$F60),0) -> 0 | AK60: =IF($S60>=2,IF(ISNUMBER(I60),I60*$F60,MIN($G60:$J60)*$F60),0) -> 0 | AL60: =IF($S60>=2,IF(ISNUMBER(J60),J60*$F60,MIN($G60:$J60)*$F60),0) -> 0 | AM60: =IF($S60>=2,$R60+ROW()/1000000,"") | AN60: =IF($S60>=2,MAX(G60:J60),"") | AO60: =IF($S60>=2,INDEX($G$6:$J$6,MATCH(MAX(G60:J60),G60:J60,0)),"") | AP60: =IF($S60>=2,MIN(G60:J60)*$F60,0) -> 0 | AQ60: =IF($S60>=2,INDEX($G$6:$J$6,MATCH(MIN(G60:J60),G60:J60,0)),"")
A61: R054 | B61: Item 5 | C61: Valves | D61: 10" AV-TEK double-eccentric butterfly valve (handwheel) | E61: EA | F61: 1 | G61: — | H61: — | I61: =IF(COUNTIF('Quote Lines'!$P$3:$P$805,$A61&"|"&I$6&"|1")=0,"—",SUMIFS('Quote Lines'!$O$3:$O$805,'Quote Lines'!$P$3:$P$805,$A61&"|"&I$6&"|1")/SUMIFS('Quote Lines'!$L$3:$L$805,'Quote Lines'!$P$3:$P$805,$A61&"|"&I$6&"|1")) -> 4854.91 | J61: — | K61: =IF(ISNUMBER(G61),G61*$F61,"—") -> — | L61: =IF(ISNUMBER(H61),H61*$F61,"—") -> — | M61: =IF(ISNUMBER(I61),I61*$F61,"—") -> 4854.91 | N61: =IF(ISNUMBER(J61),J61*$F61,"—") -> — | O61: =IF($S61=0,"—",MIN(G61:J61)) -> 4854.91 | P61: =IF($S61=0,"—",IF(COUNTIF(G61:J61,O61)>1,"Tie",INDEX($G$6:$J$6,MATCH(O61,G61:J61,0)))) -> Mountainland | Q61: =IF($S61>=2,MAX(G61:J61)/MIN(G61:J61)-1,"—") -> — | R61: =IF($S61>=2,(MAX(G61:J61)-MIN(G61:J61))*$F61,"—") -> — | S61: =COUNT(G61:J61) -> 1 | T61: =IF($S61<=1,IF($S61=1,"Single quote","—"),"Like-for-like") -> Single quote | U61: =IF(COUNT(W61:Z61)<2,"",IF(MAX(W61:Z61)=MIN(W61:Z61),"OK","Qty differs")) | Y61: =IF(COUNTIFS('Quote Lines'!$P$3:$P$805,$A61&"|"&I$6&"|1",'Quote Lines'!$M$3:$M$805,"Y")=0,"",SUMIFS('Quote Lines'!$L$3:$L$805,'Quote Lines'!$P$3:$P$805,$A61&"|"&I$6&"|1",'Quote Lines'!$M$3:$M$805,"Y")) -> 1 | AA61: =IF(ISNUMBER(G61),1+SUMPRODUCT(ISNUMBER($G61:$J61)*($G61:$J61<G61)),"") | AB61: =IF(ISNUMBER(H61),1+SUMPRODUCT(ISNUMBER($G61:$J61)*($G61:$J61<H61)),"") | AC61: =IF(ISNUMBER(I61),1+SUMPRODUCT(ISNUMBER($G61:$J61)*($G61:$J61<I61)),"") -> 1 | AD61: =IF(ISNUMBER(J61),1+SUMPRODUCT(ISNUMBER($G61:$J61)*($G61:$J61<J61)),"") | AE61: =IF(NOT(ISNUMBER(G61)),0,IF($S61<2,5,IF(AA61=1,1,IF(G61=MAX($G61:$J61),4,IF(AA61=2,2,3))))) -> 0 | AF61: =IF(NOT(ISNUMBER(H61)),0,IF($S61<2,5,IF(AB61=1,1,IF(H61=MAX($G61:$J61),4,IF(AB61=2,2,3))))) -> 0 | AG61: =IF(NOT(ISNUMBER(I61)),0,IF($S61<2,5,IF(AC61=1,1,IF(I61=MAX($G61:$J61),4,IF(AC61=2,2,3))))) -> 5 | AH61: =IF(NOT(ISNUMBER(J61)),0,IF($S61<2,5,IF(AD61=1,1,IF(J61=MAX($G61:$J61),4,IF(AD61=2,2,3))))) -> 0 | AI61: =IF($S61>=2,IF(ISNUMBER(G61),G61*$F61,MIN($G61:$J61)*$F61),0) -> 0 | AJ61: =IF($S61>=2,IF(ISNUMBER(H61),H61*$F61,MIN($G61:$J61)*$F61),0) -> 0 | AK61: =IF($S61>=2,IF(ISNUMBER(I61),I61*$F61,MIN($G61:$J61)*$F61),0) -> 0 | AL61: =IF($S61>=2,IF(ISNUMBER(J61),J61*$F61,MIN($G61:$J61)*$F61),0) -> 0 | AM61: =IF($S61>=2,$R61+ROW()/1000000,"") | AN61: =IF($S61>=2,MAX(G61:J61),"") | AO61: =IF($S61>=2,INDEX($G$6:$J$6,MATCH(MAX(G61:J61),G61:J61,0)),"") | AP61: =IF($S61>=2,MIN(G61:J61)*$F61,0) -> 0 | AQ61: =IF($S61>=2,INDEX($G$6:$J$6,MATCH(MIN(G61:J61),G61:J61,0)),"")
A62: R055 | B62: Item 5 | C62: Valves | D62: 12" MJ x flange resilient-wedge gate valve | E62: EA | F62: 1 | G62: — | H62: =IF(COUNTIF('Quote Lines'!$P$3:$P$805,$A62&"|"&H$6&"|1")=0,"—",SUMIFS('Quote Lines'!$O$3:$O$805,'Quote Lines'!$P$3:$P$805,$A62&"|"&H$6&"|1")/SUMIFS('Quote Lines'!$L$3:$L$805,'Quote Lines'!$P$3:$P$805,$A62&"|"&H$6&"|1")) -> 3181.88 | I62: — | J62: =IF(COUNTIF('Quote Lines'!$P$3:$P$805,$A62&"|"&J$6&"|1")=0,"—",SUMIFS('Quote Lines'!$O$3:$O$805,'Quote Lines'!$P$3:$P$805,$A62&"|"&J$6&"|1")/SUMIFS('Quote Lines'!$L$3:$L$805,'Quote Lines'!$P$3:$P$805,$A62&"|"&J$6&"|1")) -> 3434.76 | K62: =IF(ISNUMBER(G62),G62*$F62,"—") -> — | L62: =IF(ISNUMBER(H62),H62*$F62,"—") -> 3181.88 | M62: =IF(ISNUMBER(I62),I62*$F62,"—") -> — | N62: =IF(ISNUMBER(J62),J62*$F62,"—") -> 3434.76 | O62: =IF($S62=0,"—",MIN(G62:J62)) -> 3181.88 | P62: =IF($S62=0,"—",IF(COUNTIF(G62:J62,O62)>1,"Tie",INDEX($G$6:$J$6,MATCH(O62,G62:J62,0)))) -> HD Fowler | Q62: =IF($S62>=2,MAX(G62:J62)/MIN(G62:J62)-1,"—") -> 0.079475027 | R62: =IF($S62>=2,(MAX(G62:J62)-MIN(G62:J62))*$F62,"—") -> 252.88 | S62: =COUNT(G62:J62) -> 2 | T62: =IF($S62<=1,IF($S62=1,"Single quote","—"),"Like-for-like") -> Like-for-like | U62: =IF(COUNT(W62:Z62)<2,"",IF(MAX(W62:Z62)=MIN(W62:Z62),"OK","Qty differs")) -> OK | X62: =IF(COUNTIFS('Quote Lines'!$P$3:$P$805,$A62&"|"&H$6&"|1",'Quote Lines'!$M$3:$M$805,"Y")=0,"",SUMIFS('Quote Lines'!$L$3:$L$805,'Quote Lines'!$P$3:$P$805,$A62&"|"&H$6&"|1",'Quote Lines'!$M$3:$M$805,"Y")) -> 1 | Z62: =IF(COUNTIFS('Quote Lines'!$P$3:$P$805,$A62&"|"&J$6&"|1",'Quote Lines'!$M$3:$M$805,"Y")=0,"",SUMIFS('Quote Lines'!$L$3:$L$805,'Quote Lines'!$P$3:$P$805,$A62&"|"&J$6&"|1",'Quote Lines'!$M$3:$M$805,"Y")) -> 1 | AA62: =IF(ISNUMBER(G62),1+SUMPRODUCT(ISNUMBER($G62:$J62)*($G62:$J62<G62)),"") | AB62: =IF(ISNUMBER(H62),1+SUMPRODUCT(ISNUMBER($G62:$J62)*($G62:$J62<H62)),"") -> 1 | AC62: =IF(ISNUMBER(I62),1+SUMPRODUCT(ISNUMBER($G62:$J62)*($G62:$J62<I62)),"") | AD62: =IF(ISNUMBER(J62),1+SUMPRODUCT(ISNUMBER($G62:$J62)*($G62:$J62<J62)),"") -> 2 | AE62: =IF(NOT(ISNUMBER(G62)),0,IF($S62<2,5,IF(AA62=1,1,IF(G62=MAX($G62:$J62),4,IF(AA62=2,2,3))))) -> 0 | AF62: =IF(NOT(ISNUMBER(H62)),0,IF($S62<2,5,IF(AB62=1,1,IF(H62=MAX($G62:$J62),4,IF(AB62=2,2,3))))) -> 1 | AG62: =IF(NOT(ISNUMBER(I62)),0,IF($S62<2,5,IF(AC62=1,1,IF(I62=MAX($G62:$J62),4,IF(AC62=2,2,3))))) -> 0 | AH62: =IF(NOT(ISNUMBER(J62)),0,IF($S62<2,5,IF(AD62=1,1,IF(J62=MAX($G62:$J62),4,IF(AD62=2,2,3))))) -> 4 | AI62: =IF($S62>=2,IF(ISNUMBER(G62),G62*$F62,MIN($G62:$J62)*$F62),0) -> 3181.88 | AJ62: =IF($S62>=2,IF(ISNUMBER(H62),H62*$F62,MIN($G62:$J62)*$F62),0) -> 3181.88 | AK62: =IF($S62>=2,IF(ISNUMBER(I62),I62*$F62,MIN($G62:$J62)*$F62),0) -> 3181.88 | AL62: =IF($S62>=2,IF(ISNUMBER(J62),J62*$F62,MIN($G62:$J62)*$F62),0) -> 3434.76 | AM62: =IF($S62>=2,$R62+ROW()/1000000,"") -> 252.88006 | AN62: =IF($S62>=2,MAX(G62:J62),"") -> 3434.76 | AO62: =IF($S62>=2,INDEX($G$6:$J$6,MATCH(MAX(G62:J62),G62:J62,0)),"") -> Scholzen | AP62: =IF($S62>=2,MIN(G62:J62)*$F62,0) -> 3181.88 | AQ62: =IF($S62>=2,INDEX($G$6:$J$6,MATCH(MIN(G62:J62),G62:J62,0)),"") -> HD Fowler
A63: R056 | B63: Item 5 | C63: Valves | D63: 12" flange x flange resilient-wedge gate valve | E63: EA | F63: 1 | G63: — | H63: =IF(COUNTIF('Quote Lines'!$P$3:$P$805,$A63&"|"&H$6&"|1")=0,"—",SUMIFS('Quote Lines'!$O$3:$O$805,'Quote Lines'!$P$3:$P$805,$A63&"|"&H$6&"|1")/SUMIFS('Quote Lines'!$L$3:$L$805,'Quote Lines'!$P$3:$P$805,$A63&"|"&H$6&"|1")) -> 3303.65 | I63: — | J63: =IF(COUNTIF('Quote Lines'!$P$3:$P$805,$A63&"|"&J$6&"|1")=0,"—",SUMIFS('Quote Lines'!$O$3:$O$805,'Quote Lines'!$P$3:$P$805,$A63&"|"&J$6&"|1")/SUMIFS('Quote Lines'!$L$3:$L$805,'Quote Lines'!$P$3:$P$805,$A63&"|"&J$6&"|1")) -> 3662.26 | K63: =IF(ISNUMBER(G63),G63*$F63,"—") -> — | L63: =IF(ISNUMBER(H63),H63*$F63,"—") -> 3303.65 | M63: =IF(ISNUMBER(I63),I63*$F63,"—") -> — | N63: =IF(ISNUMBER(J63),J63*$F63,"—") -> 3662.26 | O63: =IF($S63=0,"—",MIN(G63:J63)) -> 3303.65 | P63: =IF($S63=0,"—",IF(COUNTIF(G63:J63,O63)>1,"Tie",INDEX($G$6:$J$6,MATCH(O63,G63:J63,0)))) -> HD Fowler | Q63: =IF($S63>=2,MAX(G63:J63)/MIN(G63:J63)-1,"—") -> 0.10854963 | R63: =IF($S63>=2,(MAX(G63:J63)-MIN(G63:J63))*$F63,"—") -> 358.61 | S63: =COUNT(G63:J63) -> 2 | T63: =IF($S63<=1,IF($S63=1,"Single quote","—"),"Like-for-like") -> Like-for-like | U63: =IF(COUNT(W63:Z63)<2,"",IF(MAX(W63:Z63)=MIN(W63:Z63),"OK","Qty differs")) -> OK | X63: =IF(COUNTIFS('Quote Lines'!$P$3:$P$805,$A63&"|"&H$6&"|1",'Quote Lines'!$M$3:$M$805,"Y")=0,"",SUMIFS('Quote Lines'!$L$3:$L$805,'Quote Lines'!$P$3:$P$805,$A63&"|"&H$6&"|1",'Quote Lines'!$M$3:$M$805,"Y")) -> 1 | Z63: =IF(COUNTIFS('Quote Lines'!$P$3:$P$805,$A63&"|"&J$6&"|1",'Quote Lines'!$M$3:$M$805,"Y")=0,"",SUMIFS('Quote Lines'!$L$3:$L$805,'Quote Lines'!$P$3:$P$805,$A63&"|"&J$6&"|1",'Quote Lines'!$M$3:$M$805,"Y")) -> 1 | AA63: =IF(ISNUMBER(G63),1+SUMPRODUCT(ISNUMBER($G63:$J63)*($G63:$J63<G63)),"") | AB63: =IF(ISNUMBER(H63),1+SUMPRODUCT(ISNUMBER($G63:$J63)*($G63:$J63<H63)),"") -> 1 | AC63: =IF(ISNUMBER(I63),1+SUMPRODUCT(ISNUMBER($G63:$J63)*($G63:$J63<I63)),"") | AD63: =IF(ISNUMBER(J63),1+SUMPRODUCT(ISNUMBER($G63:$J63)*($G63:$J63<J63)),"") -> 2 | AE63: =IF(NOT(ISNUMBER(G63)),0,IF($S63<2,5,IF(AA63=1,1,IF(G63=MAX($G63:$J63),4,IF(AA63=2,2,3))))) -> 0 | AF63: =IF(NOT(ISNUMBER(H63)),0,IF($S63<2,5,IF(AB63=1,1,IF(H63=MAX($G63:$J63),4,IF(AB63=2,2,3))))) -> 1 | AG63: =IF(NOT(ISNUMBER(I63)),0,IF($S63<2,5,IF(AC63=1,1,IF(I63=MAX($G63:$J63),4,IF(AC63=2,2,3))))) -> 0 | AH63: =IF(NOT(ISNUMBER(J63)),0,IF($S63<2,5,IF(AD63=1,1,IF(J63=MAX($G63:$J63),4,IF(AD63=2,2,3))))) -> 4 | AI63: =IF($S63>=2,IF(ISNUMBER(G63),G63*$F63,MIN($G63:$J63)*$F63),0) -> 3303.65 | AJ63: =IF($S63>=2,IF(ISNUMBER(H63),H63*$F63,MIN($G63:$J63)*$F63),0) -> 3303.65 | AK63: =IF($S63>=2,IF(ISNUMBER(I63),I63*$F63,MIN($G63:$J63)*$F63),0) -> 3303.65 | AL63: =IF($S63>=2,IF(ISNUMBER(J63),J63*$F63,MIN($G63:$J63)*$F63),0) -> 3662.26 | AM63: =IF($S63>=2,$R63+ROW()/1000000,"") -> 358.61006 | AN63: =IF($S63>=2,MAX(G63:J63),"") -> 3662.26 | AO63: =IF($S63>=2,INDEX($G$6:$J$6,MATCH(MAX(G63:J63),G63:J63,0)),"") -> Scholzen | AP63: =IF($S63>=2,MIN(G63:J63)*$F63,0) -> 3303.65 | AQ63: =IF($S63>=2,INDEX($G$6:$J$6,MATCH(MIN(G63:J63),G63:J63,0)),"") -> HD Fowler
